Workbook
Name AvailableCDPs: 'Available CDPs'!$A$4:$A$11
Name Comparison_CDP1: Comparison!$B$8
Name Comparison_CDP2: Comparison!$B$9
Name Summary_CDP: Summary!$B$8
Name WACC: 0.075

Sheet Disclaimer
B2: Disclaimer
B4: This generation outcomes workbook contains data provided by or collected from third parties,
B5: and conclusions, opinions, assumptions or forecasts that are based on that data.
B7: AEMO has made every effort to ensure the quality of the information in this workbook but cannot guarantee
B8: that the information, forecasts and assumptions in it are accurate, complete or appropriate for your
B9: circumstances. This generation outcomes workbook does not include all of the information that an investor,
B10: participant or potential participant in the electricity or gas market might require, and does not amount to a
B11: recommendation of any investment.
B13: Anyone proposing to use the information in this workbook should independently verify and check its
B14: accuracy, completeness and suitability for purpose, and obtain independent and specific advice from
B15: appropriate experts.
B17: This dataset or the information in it may be subsequently updated or amended. This work does
... B28: or in respect of a person’s use of the information in this workbook.

Sheet Index
B2: 2022 ISP Results Workbook
B4: Version History
B5: Version Number | C5: Description
B6: v1.0 | C6: Initial release
B7: v1.1 | C7: Added regional import and export data
B8: v1.2 | C8: Minor fixes
B10: About
B11: This workbook presents generation and cost data for the Draft 2022 ISP. For a complete description of the scenarios and sensitivities, please see the Draft 2022 ISP report.
B13: Index Table
B14: Tab Name | C14: Content Description
B15: CDPs | C15: Description of Candidate Development Pathways
B16: Summary | C16: Summary (calculated) for a selected case
B17: Comparison | C17: Comparison (calculated) between two selected cases
B18: REZ Generation Capacity | C18: Installed capacity by REZ and technology for all cases
B19: REZ Generation | C19: Annual as-generated generation by REZ and technology for all cases

Sheet CDPs
A2: Candidate Development Paths
B4: Purpose | C4: New England REZ Transmission Link | D4: Sydney Ring | E4: Marinus Link | F4: VNI West | G4: HumeLink | H4: Gladstone Grid Reinforcement
A5: CDP1 | B5: Based on Progressive Change least-cost DP | C5: Potential actionable | D5: Potential actionable
A6: CDP2 | B6: Based on Step Change least-cost DP (Progressive Change least-cost with actionable ML and VNI West) | C6: Potential actionable | D6: Potential actionable | E6: Potential actionable | F6: Potential actionable
A8: CDP3 | B8: Based on Hydrogen Superpower least-cost DP | C8: Potential actionable | D8: Potential actionable | E8: Potential actionable | F8: Potential actionable | G8: Potential actionable | H8: Potential actionable
A9: CDP4 | B9: Based on Slow Change least-cost DP (Progressive Change without actionable Sydney Ring) | C9: Potential actionable
A11: CDP5 | B11: Progressive Change least-cost DP, with Marinus Link actionable | C11: Potential actionable | D11: Potential actionable | E11: Potential actionable
A12: CDP6 | B12: Progressive Change, with VNI West actionable | C12: Potential actionable | D12: Potential actionable | F12: Potential actionable
A13: CDP7 | B13: Progressive Change, without New England REZ Transmission Link actionable | D13: Potential actionable
A14: CDP8 | B14: Step Change, with HumeLink actionable | C14: Potential actionable | D14: Potential actionable | E14: Potential actionable | F14: Potential actionable | G14: Potential actionable
A15: CDP9 | B15: No actionable projects
A16: CDP10 | B16: Progressive Change least-cost DP, with actionable Marinus Link and VNI West staged | C16: Potential actionable | D16: Potential actionable | E16: Potential actionable | F16: Stage 1 (Early Works)
A17: CDP11 | B17: Progressive Change least-cost DP, with actionable Marinus Link, VNI West staged, and actionable HumeLink | C17: Potential actionable | D17: Potential actionable | E17: Potential actionable | F17: Stage 1 (Early Works) | G17: Potential actionable
A18: CDP12 | B18: Progressive Change least-cost DP, with actionable Marinus Link, and staged VNI West and HumeLink | C18: Potential actionable | D18: Potential actionable | E18: Potential actionable | F18: Stage 1 (Early Works) | G18: Stage 1 (Early Works)
A19: CDP13 | B19: Progressive Change least-cost DP with staged VNI West and HumeLink, but with Marinus Link not available | C19: Potential actionable | D19: Potential actionable | E19: Never available | F19: Stage 1 (Early Works) | G19: Stage 1 (Early Works)
A20: Counterfactual | B20: No future network augmentation other than committed and anticipated projects/ small intra-regional augmentations/ replacement expenditure projects
A22: Refer to the summary tab for the specific timings of all augmentation options for a selected CDP.

Sheet Summary
A2: ="Case Summary - "&Summary_CDP -> Case Summary - CDP1
A3: Notes
A4: ="1. The discount rate used for calculation is "&TEXT(WACC,"0.0%") -> 1. The discount rate used for calculation is 7.5%
A5: 2. All costs exclude any additional reliability cost savings, competition benefits and early works costs. Further details on these components are provided in Appendix 6.
C7: Description:
A8: Select case | B8: CDP1 | C8: =INDEX(CDPs!$B$5:$B$20,MATCH(Summary_CDP,CDPs!$A$5:$A$20,0),1) -> Based on Progressive Change least-cost DP
A11: Discounted total system costs by year
H14: Real June 2021 dollars ($m) | I14: NPV | J14: 2023-24 | K14: 2024-25 | L14: 2025-26 | M14: 2026-27 | N14: 2027-28 | O14: 2028-29 | P14: 2029-30 | Q14: 2030-31 | R14: 2031-32 | S14: 2032-33 | T14: 2033-34 | U14: 2034-35 | V14: 2035-36 | W14: 2036-37 | X14: 2037-38 | Y14: 2038-39 | Z14: 2039-40 | AA14: 2040-41 | AB14: 2041-42 | AC14: 2042-43 | AD14: 2043-44 | AE14: 2044-45 | AF14: 2045-46 | AG14: 2046-47 | AH14: 2047-48 | AI14: 2048-49 | AJ14: 2049-50 | AK14: 2050-51
H15: Generator Capital | I15: =NPV(WACC,J15:AK15)/(1+WACC)^2 -> 191565.75 | J15: =SUMIFS(Costs!C:C,Costs!$A:$A,Summary_CDP,Costs!$B:$B,$H15)/1000 -> 1069.726 | K15: =SUMIFS(Costs!D:D,Costs!$A:$A,Summary_CDP,Costs!$B:$B,$H15)/1000 -> 2387.4603 | L15: =SUMIFS(Costs!E:E,Costs!$A:$A,Summary_CDP,Costs!$B:$B,$H15)/1000 -> 4374.2223 | M15: =SUMIFS(Costs!F:F,Costs!$A:$A,Summary_CDP,Costs!$B:$B,$H15)/1000 -> 5783.7273 | N15: =SUMIFS(Costs!G:G,Costs!$A:$A,Summary_CDP,Costs!$B:$B,$H15)/1000 -> 8224.1375 | O15: =SUMIFS(Costs!H:H,Costs!$A:$A,Summary_CDP,Costs!$B:$B,$H15)/1000 -> 9945.3866 | P15: =SUMIFS(Costs!I:I,Costs!$A:$A,Summary_CDP,Costs!$B:$B,$H15)/1000 -> 10672.807 | Q15: =SUMIFS(Costs!J:J,Costs!$A:$A,Summary_CDP,Costs!$B:$B,$H15)/1000 -> 12715.458 | R15: =SUMIFS(Costs!K:K,Costs!$A:$A,Summary_CDP,Costs!$B:$B,$H15)/1000 -> 13960.86 | S15: =SUMIFS(Costs!L:L,Costs!$A:$A,Summary_CDP,Costs!$B:$B,$H15)/1000 -> 14875.288 | T15: =SUMIFS(Costs!M:M,Costs!$A:$A,Summary_CDP,Costs!$B:$B,$H15)/1000 -> 17119.351 | U15: =SUMIFS(Costs!N:N,Costs!$A:$A,Summary_CDP,Costs!$B:$B,$H15)/1000 -> 20317.945 | V15: =SUMIFS(Costs!O:O,Costs!$A:$A,Summary_CDP,Costs!$B:$B,$H15)/1000 -> 21905.568 | W15: =SUMIFS(Costs!P:P,Costs!$A:$A,Summary_CDP,Costs!$B:$B,$H15)/1000 -> 24587.463 | X15: =SUMIFS(Costs!Q:Q,Costs!$A:$A,Summary_CDP,Costs!$B:$B,$H15)/1000 -> 27013.54 | Y15: =SUMIFS(Costs!R:R,Costs!$A:$A,Summary_CDP,Costs!$B:$B,$H15)/1000 -> 28595.843 | Z15: =SUMIFS(Costs!S:S,Costs!$A:$A,Summary_CDP,Costs!$B:$B,$H15)/1000 -> 28595.843 | AA15: =SUMIFS(Costs!T:T,Costs!$A:$A,Summary_CDP,Costs!$B:$B,$H15)/1000 -> 30564.406 | AB15: =SUMIFS(Costs!U:U,Costs!$A:$A,Summary_CDP,Costs!$B:$B,$H15)/1000 -> 35942.259 | AC15: =SUMIFS(Costs!V:V,Costs!$A:$A,Summary_CDP,Costs!$B:$B,$H15)/1000 -> 41266.37 | AD15: =SUMIFS(Costs!W:W,Costs!$A:$A,Summary_CDP,Costs!$B:$B,$H15)/1000 -> 47049.177 | AE15: =SUMIFS(Costs!X:X,Costs!$A:$A,Summary_CDP,Costs!$B:$B,$H15)/1000 -> 50669.355 | AF15: =SUMIFS(Costs!Y:Y,Costs!$A:$A,Summary_CDP,Costs!$B:$B,$H15)/1000 -> 57335.328 | AG15: =SUMIFS(Costs!Z:Z,Costs!$A:$A,Summary_CDP,Costs!$B:$B,$H15)/1000 -> 59369.294 | AH15: =SUMIFS(Costs!AA:AA,Costs!$A:$A,Summary_CDP,Costs!$B:$B,$H15)/1000 -> 61501.829 | AI15: =SUMIFS(Costs!AB:AB,Costs!$A:$A,Summary_CDP,Costs!$B:$B,$H15)/1000 -> 65960.368 | AJ15: =SUMIFS(Costs!AC:AC,Costs!$A:$A,Summary_CDP,Costs!$B:$B,$H15)/1000 -> 76833.728 | AK15: =SUMIFS(Costs!AD:AD,Costs!$A:$A,Summary_CDP,Costs!$B:$B,$H15)/1000 -> 74789.891
H16: FOM | I16: =NPV(WACC,J16:AK16)/(1+WACC)^2 -> 48709.898 | J16: =SUMIFS(Costs!C:C,Costs!$A:$A,Summary_CDP,Costs!$B:$B,$H16)/1000 -> 2860.583 | K16: =SUMIFS(Costs!D:D,Costs!$A:$A,Summary_CDP,Costs!$B:$B,$H16)/1000 -> 3037.808 | L16: =SUMIFS(Costs!E:E,Costs!$A:$A,Summary_CDP,Costs!$B:$B,$H16)/1000 -> 3923.4663 | M16: =SUMIFS(Costs!F:F,Costs!$A:$A,Summary_CDP,Costs!$B:$B,$H16)/1000 -> 3276.7732 | N16: =SUMIFS(Costs!G:G,Costs!$A:$A,Summary_CDP,Costs!$B:$B,$H16)/1000 -> 3513.7041 | O16: =SUMIFS(Costs!H:H,Costs!$A:$A,Summary_CDP,Costs!$B:$B,$H16)/1000 -> 3172.8873 | P16: =SUMIFS(Costs!I:I,Costs!$A:$A,Summary_CDP,Costs!$B:$B,$H16)/1000 -> 3122.4962 | Q16: =SUMIFS(Costs!J:J,Costs!$A:$A,Summary_CDP,Costs!$B:$B,$H16)/1000 -> 3612.853 | R16: =SUMIFS(Costs!K:K,Costs!$A:$A,Summary_CDP,Costs!$B:$B,$H16)/1000 -> 3241.5481 | S16: =SUMIFS(Costs!L:L,Costs!$A:$A,Summary_CDP,Costs!$B:$B,$H16)/1000 -> 3417.9183 | T16: =SUMIFS(Costs!M:M,Costs!$A:$A,Summary_CDP,Costs!$B:$B,$H16)/1000 -> 3789.9376 | U16: =SUMIFS(Costs!N:N,Costs!$A:$A,Summary_CDP,Costs!$B:$B,$H16)/1000 -> 4311.1304 | V16: =SUMIFS(Costs!O:O,Costs!$A:$A,Summary_CDP,Costs!$B:$B,$H16)/1000 -> 4656.6671 | W16: =SUMIFS(Costs!P:P,Costs!$A:$A,Summary_CDP,Costs!$B:$B,$H16)/1000 -> 5063.8046 | X16: =SUMIFS(Costs!Q:Q,Costs!$A:$A,Summary_CDP,Costs!$B:$B,$H16)/1000 -> 5505.9835 | Y16: =SUMIFS(Costs!R:R,Costs!$A:$A,Summary_CDP,Costs!$B:$B,$H16)/1000 -> 5773.249 | Z16: =SUMIFS(Costs!S:S,Costs!$A:$A,Summary_CDP,Costs!$B:$B,$H16)/1000 -> 5783.7613 | AA16: =SUMIFS(Costs!T:T,Costs!$A:$A,Summary_CDP,Costs!$B:$B,$H16)/1000 -> 6087.1611 | AB16: =SUMIFS(Costs!U:U,Costs!$A:$A,Summary_CDP,Costs!$B:$B,$H16)/1000 -> 7148.4207 | AC16: =SUMIFS(Costs!V:V,Costs!$A:$A,Summary_CDP,Costs!$B:$B,$H16)/1000 -> 8011.8017 | AD16: =SUMIFS(Costs!W:W,Costs!$A:$A,Summary_CDP,Costs!$B:$B,$H16)/1000 -> 8950.4734 | AE16: =SUMIFS(Costs!X:X,Costs!$A:$A,Summary_CDP,Costs!$B:$B,$H16)/1000 -> 9563.7575 | AF16: =SUMIFS(Costs!Y:Y,Costs!$A:$A,Summary_CDP,Costs!$B:$B,$H16)/1000 -> 10675.594 | AG16: =SUMIFS(Costs!Z:Z,Costs!$A:$A,Summary_CDP,Costs!$B:$B,$H16)/1000 -> 10982.834 | AH16: =SUMIFS(Costs!AA:AA,Costs!$A:$A,Summary_CDP,Costs!$B:$B,$H16)/1000 -> 11370.834 | AI16: =SUMIFS(Costs!AB:AB,Costs!$A:$A,Summary_CDP,Costs!$B:$B,$H16)/1000 -> 12440.226 | AJ16: =SUMIFS(Costs!AC:AC,Costs!$A:$A,Summary_CDP,Costs!$B:$B,$H16)/1000 -> 15027.623 | AK16: =SUMIFS(Costs!AD:AD,Costs!$A:$A,Summary_CDP,Costs!$B:$B,$H16)/1000 -> 14916.946
H17: Fuel | I17: =NPV(WACC,J17:AK17)/(1+WACC)^2 -> 10360.023 | J17: =SUMIFS(Costs!C:C,Costs!$A:$A,Summary_CDP,Costs!$B:$B,$H17)/1000 -> 2571.4853 | K17: =SUMIFS(Costs!D:D,Costs!$A:$A,Summary_CDP,Costs!$B:$B,$H17)/1000 -> 1956.8224 | L17: =SUMIFS(Costs!E:E,Costs!$A:$A,Summary_CDP,Costs!$B:$B,$H17)/1000 -> 1452.8799 | M17: =SUMIFS(Costs!F:F,Costs!$A:$A,Summary_CDP,Costs!$B:$B,$H17)/1000 -> 1372.4358 | N17: =SUMIFS(Costs!G:G,Costs!$A:$A,Summary_CDP,Costs!$B:$B,$H17)/1000 -> 1400.8115 | O17: =SUMIFS(Costs!H:H,Costs!$A:$A,Summary_CDP,Costs!$B:$B,$H17)/1000 -> 1343.8659 | P17: =SUMIFS(Costs!I:I,Costs!$A:$A,Summary_CDP,Costs!$B:$B,$H17)/1000 -> 1010.4777 | Q17: =SUMIFS(Costs!J:J,Costs!$A:$A,Summary_CDP,Costs!$B:$B,$H17)/1000 -> 644.95658 | R17: =SUMIFS(Costs!K:K,Costs!$A:$A,Summary_CDP,Costs!$B:$B,$H17)/1000 -> 543.91285 | S17: =SUMIFS(Costs!L:L,Costs!$A:$A,Summary_CDP,Costs!$B:$B,$H17)/1000 -> 382.17329 | T17: =SUMIFS(Costs!M:M,Costs!$A:$A,Summary_CDP,Costs!$B:$B,$H17)/1000 -> 365.33457 | U17: =SUMIFS(Costs!N:N,Costs!$A:$A,Summary_CDP,Costs!$B:$B,$H17)/1000 -> 634.76277 | V17: =SUMIFS(Costs!O:O,Costs!$A:$A,Summary_CDP,Costs!$B:$B,$H17)/1000 -> 421.46356 | W17: =SUMIFS(Costs!P:P,Costs!$A:$A,Summary_CDP,Costs!$B:$B,$H17)/1000 -> 351.92054 | X17: =SUMIFS(Costs!Q:Q,Costs!$A:$A,Summary_CDP,Costs!$B:$B,$H17)/1000 -> 323.47891 | Y17: =SUMIFS(Costs!R:R,Costs!$A:$A,Summary_CDP,Costs!$B:$B,$H17)/1000 -> 1002.8373 | Z17: =SUMIFS(Costs!S:S,Costs!$A:$A,Summary_CDP,Costs!$B:$B,$H17)/1000 -> 361.3878 | AA17: =SUMIFS(Costs!T:T,Costs!$A:$A,Summary_CDP,Costs!$B:$B,$H17)/1000 -> 356.94145 | AB17: =SUMIFS(Costs!U:U,Costs!$A:$A,Summary_CDP,Costs!$B:$B,$H17)/1000 -> 655.51779 | AC17: =SUMIFS(Costs!V:V,Costs!$A:$A,Summary_CDP,Costs!$B:$B,$H17)/1000 -> 573.3398 | AD17: =SUMIFS(Costs!W:W,Costs!$A:$A,Summary_CDP,Costs!$B:$B,$H17)/1000 -> 973.89924 | AE17: =SUMIFS(Costs!X:X,Costs!$A:$A,Summary_CDP,Costs!$B:$B,$H17)/1000 -> 371.55054 | AF17: =SUMIFS(Costs!Y:Y,Costs!$A:$A,Summary_CDP,Costs!$B:$B,$H17)/1000 -> 560.37162 | AG17: =SUMIFS(Costs!Z:Z,Costs!$A:$A,Summary_CDP,Costs!$B:$B,$H17)/1000 -> 179.03776 | AH17: =SUMIFS(Costs!AA:AA,Costs!$A:$A,Summary_CDP,Costs!$B:$B,$H17)/1000 -> 402.01826 | AI17: =SUMIFS(Costs!AB:AB,Costs!$A:$A,Summary_CDP,Costs!$B:$B,$H17)/1000 -> 220.80547 | AJ17: =SUMIFS(Costs!AC:AC,Costs!$A:$A,Summary_CDP,Costs!$B:$B,$H17)/1000 -> 1428.3273 | AK17: =SUMIFS(Costs!AD:AD,Costs!$A:$A,Summary_CDP,Costs!$B:$B,$H17)/1000 -> 168.70515
H18: VOM | I18: =NPV(WACC,J18:AK18)/(1+WACC)^2 -> 2758.2126 | J18: =SUMIFS(Costs!C:C,Costs!$A:$A,Summary_CDP,Costs!$B:$B,$H18)/1000 -> 667.55342 | K18: =SUMIFS(Costs!D:D,Costs!$A:$A,Summary_CDP,Costs!$B:$B,$H18)/1000 -> 554.62779 | L18: =SUMIFS(Costs!E:E,Costs!$A:$A,Summary_CDP,Costs!$B:$B,$H18)/1000 -> 432.85201 | M18: =SUMIFS(Costs!F:F,Costs!$A:$A,Summary_CDP,Costs!$B:$B,$H18)/1000 -> 397.51649 | N18: =SUMIFS(Costs!G:G,Costs!$A:$A,Summary_CDP,Costs!$B:$B,$H18)/1000 -> 355.12307 | O18: =SUMIFS(Costs!H:H,Costs!$A:$A,Summary_CDP,Costs!$B:$B,$H18)/1000 -> 301.91409 | P18: =SUMIFS(Costs!I:I,Costs!$A:$A,Summary_CDP,Costs!$B:$B,$H18)/1000 -> 245.75677 | Q18: =SUMIFS(Costs!J:J,Costs!$A:$A,Summary_CDP,Costs!$B:$B,$H18)/1000 -> 183.92175 | R18: =SUMIFS(Costs!K:K,Costs!$A:$A,Summary_CDP,Costs!$B:$B,$H18)/1000 -> 136.31456 | S18: =SUMIFS(Costs!L:L,Costs!$A:$A,Summary_CDP,Costs!$B:$B,$H18)/1000 -> 151.58821 | T18: =SUMIFS(Costs!M:M,Costs!$A:$A,Summary_CDP,Costs!$B:$B,$H18)/1000 -> 146.8435 | U18: =SUMIFS(Costs!N:N,Costs!$A:$A,Summary_CDP,Costs!$B:$B,$H18)/1000 -> 157.39793 | V18: =SUMIFS(Costs!O:O,Costs!$A:$A,Summary_CDP,Costs!$B:$B,$H18)/1000 -> 145.72582 | W18: =SUMIFS(Costs!P:P,Costs!$A:$A,Summary_CDP,Costs!$B:$B,$H18)/1000 -> 124.43534 | X18: =SUMIFS(Costs!Q:Q,Costs!$A:$A,Summary_CDP,Costs!$B:$B,$H18)/1000 -> 137.79777 | Y18: =SUMIFS(Costs!R:R,Costs!$A:$A,Summary_CDP,Costs!$B:$B,$H18)/1000 -> 180.31557 | Z18: =SUMIFS(Costs!S:S,Costs!$A:$A,Summary_CDP,Costs!$B:$B,$H18)/1000 -> 86.469488 | AA18: =SUMIFS(Costs!T:T,Costs!$A:$A,Summary_CDP,Costs!$B:$B,$H18)/1000 -> 126.78679 | AB18: =SUMIFS(Costs!U:U,Costs!$A:$A,Summary_CDP,Costs!$B:$B,$H18)/1000 -> 141.47629 | AC18: =SUMIFS(Costs!V:V,Costs!$A:$A,Summary_CDP,Costs!$B:$B,$H18)/1000 -> 111.32145 | AD18: =SUMIFS(Costs!W:W,Costs!$A:$A,Summary_CDP,Costs!$B:$B,$H18)/1000 -> 133.43982 | AE18: =SUMIFS(Costs!X:X,Costs!$A:$A,Summary_CDP,Costs!$B:$B,$H18)/1000 -> 114.55579 | AF18: =SUMIFS(Costs!Y:Y,Costs!$A:$A,Summary_CDP,Costs!$B:$B,$H18)/1000 -> 95.392635 | AG18: =SUMIFS(Costs!Z:Z,Costs!$A:$A,Summary_CDP,Costs!$B:$B,$H18)/1000 -> 86.956633 | AH18: =SUMIFS(Costs!AA:AA,Costs!$A:$A,Summary_CDP,Costs!$B:$B,$H18)/1000 -> 95.554274 | AI18: =SUMIFS(Costs!AB:AB,Costs!$A:$A,Summary_CDP,Costs!$B:$B,$H18)/1000 -> 96.589679 | AJ18: =SUMIFS(Costs!AC:AC,Costs!$A:$A,Summary_CDP,Costs!$B:$B,$H18)/1000 -> 128.91477 | AK18: =SUMIFS(Costs!AD:AD,Costs!$A:$A,Summary_CDP,Costs!$B:$B,$H18)/1000 -> 55.764594
H19: DSP+USE | I19: =NPV(WACC,J19:AK19)/(1+WACC)^2 -> 1694.1682 | J19: =SUMIFS(Costs!C:C,Costs!$A:$A,Summary_CDP,Costs!$B:$B,$H19)/1000 -> 0 | K19: =SUMIFS(Costs!D:D,Costs!$A:$A,Summary_CDP,Costs!$B:$B,$H19)/1000 -> 0 | L19: =SUMIFS(Costs!E:E,Costs!$A:$A,Summary_CDP,Costs!$B:$B,$H19)/1000 -> 0.0076741499 | M19: =SUMIFS(Costs!F:F,Costs!$A:$A,Summary_CDP,Costs!$B:$B,$H19)/1000 -> 23.864212 | N19: =SUMIFS(Costs!G:G,Costs!$A:$A,Summary_CDP,Costs!$B:$B,$H19)/1000 -> 1.9656235 | O19: =SUMIFS(Costs!H:H,Costs!$A:$A,Summary_CDP,Costs!$B:$B,$H19)/1000 -> 6.3085562 | P19: =SUMIFS(Costs!I:I,Costs!$A:$A,Summary_CDP,Costs!$B:$B,$H19)/1000 -> 0 | Q19: =SUMIFS(Costs!J:J,Costs!$A:$A,Summary_CDP,Costs!$B:$B,$H19)/1000 -> 46.927084 | R19: =SUMIFS(Costs!K:K,Costs!$A:$A,Summary_CDP,Costs!$B:$B,$H19)/1000 -> 28.75505 | S19: =SUMIFS(Costs!L:L,Costs!$A:$A,Summary_CDP,Costs!$B:$B,$H19)/1000 -> 40.079009 | T19: =SUMIFS(Costs!M:M,Costs!$A:$A,Summary_CDP,Costs!$B:$B,$H19)/1000 -> 5.3567201 | U19: =SUMIFS(Costs!N:N,Costs!$A:$A,Summary_CDP,Costs!$B:$B,$H19)/1000 -> 144.84237 | V19: =SUMIFS(Costs!O:O,Costs!$A:$A,Summary_CDP,Costs!$B:$B,$H19)/1000 -> 96.210597 | W19: =SUMIFS(Costs!P:P,Costs!$A:$A,Summary_CDP,Costs!$B:$B,$H19)/1000 -> 165.30943 | X19: =SUMIFS(Costs!Q:Q,Costs!$A:$A,Summary_CDP,Costs!$B:$B,$H19)/1000 -> 125.91588 | Y19: =SUMIFS(Costs!R:R,Costs!$A:$A,Summary_CDP,Costs!$B:$B,$H19)/1000 -> 554.11704 | Z19: =SUMIFS(Costs!S:S,Costs!$A:$A,Summary_CDP,Costs!$B:$B,$H19)/1000 -> 261.1371 | AA19: =SUMIFS(Costs!T:T,Costs!$A:$A,Summary_CDP,Costs!$B:$B,$H19)/1000 -> 506.7974 | AB19: =SUMIFS(Costs!U:U,Costs!$A:$A,Summary_CDP,Costs!$B:$B,$H19)/1000 -> 602.5884 | AC19: =SUMIFS(Costs!V:V,Costs!$A:$A,Summary_CDP,Costs!$B:$B,$H19)/1000 -> 599.63019 | AD19: =SUMIFS(Costs!W:W,Costs!$A:$A,Summary_CDP,Costs!$B:$B,$H19)/1000 -> 665.73169 | AE19: =SUMIFS(Costs!X:X,Costs!$A:$A,Summary_CDP,Costs!$B:$B,$H19)/1000 -> 714.838 | AF19: =SUMIFS(Costs!Y:Y,Costs!$A:$A,Summary_CDP,Costs!$B:$B,$H19)/1000 -> 709.05928 | AG19: =SUMIFS(Costs!Z:Z,Costs!$A:$A,Summary_CDP,Costs!$B:$B,$H19)/1000 -> 958.97789 | AH19: =SUMIFS(Costs!AA:AA,Costs!$A:$A,Summary_CDP,Costs!$B:$B,$H19)/1000 -> 491.4111 | AI19: =SUMIFS(Costs!AB:AB,Costs!$A:$A,Summary_CDP,Costs!$B:$B,$H19)/1000 -> 733.17212 | AJ19: =SUMIFS(Costs!AC:AC,Costs!$A:$A,Summary_CDP,Costs!$B:$B,$H19)/1000 -> 1095.43 | AK19: =SUMIFS(Costs!AD:AD,Costs!$A:$A,Summary_CDP,Costs!$B:$B,$H19)/1000 -> 344.92388
H20: REZ Augmentation | I20: =NPV(WACC,J20:AK20)/(1+WACC)^2 -> 15405.894 | J20: =SUMIFS(Costs!C:C,Costs!$A:$A,Summary_CDP,Costs!$B:$B,$H20)/1000 -> 0 | K20: =SUMIFS(Costs!D:D,Costs!$A:$A,Summary_CDP,Costs!$B:$B,$H20)/1000 -> 0 | L20: =SUMIFS(Costs!E:E,Costs!$A:$A,Summary_CDP,Costs!$B:$B,$H20)/1000 -> 62.964973 | M20: =SUMIFS(Costs!F:F,Costs!$A:$A,Summary_CDP,Costs!$B:$B,$H20)/1000 -> 149.27509 | N20: =SUMIFS(Costs!G:G,Costs!$A:$A,Summary_CDP,Costs!$B:$B,$H20)/1000 -> 297.57121 | O20: =SUMIFS(Costs!H:H,Costs!$A:$A,Summary_CDP,Costs!$B:$B,$H20)/1000 -> 451.72413 | P20: =SUMIFS(Costs!I:I,Costs!$A:$A,Summary_CDP,Costs!$B:$B,$H20)/1000 -> 602.43932 | Q20: =SUMIFS(Costs!J:J,Costs!$A:$A,Summary_CDP,Costs!$B:$B,$H20)/1000 -> 722.14499 | R20: =SUMIFS(Costs!K:K,Costs!$A:$A,Summary_CDP,Costs!$B:$B,$H20)/1000 -> 877.81765 | S20: =SUMIFS(Costs!L:L,Costs!$A:$A,Summary_CDP,Costs!$B:$B,$H20)/1000 -> 897.42637 | T20: =SUMIFS(Costs!M:M,Costs!$A:$A,Summary_CDP,Costs!$B:$B,$H20)/1000 -> 1115.0498 | U20: =SUMIFS(Costs!N:N,Costs!$A:$A,Summary_CDP,Costs!$B:$B,$H20)/1000 -> 1743.3625 | V20: =SUMIFS(Costs!O:O,Costs!$A:$A,Summary_CDP,Costs!$B:$B,$H20)/1000 -> 2098.411 | W20: =SUMIFS(Costs!P:P,Costs!$A:$A,Summary_CDP,Costs!$B:$B,$H20)/1000 -> 2309.0609 | X20: =SUMIFS(Costs!Q:Q,Costs!$A:$A,Summary_CDP,Costs!$B:$B,$H20)/1000 -> 2501.4262 | Y20: =SUMIFS(Costs!R:R,Costs!$A:$A,Summary_CDP,Costs!$B:$B,$H20)/1000 -> 2661.7861 | Z20: =SUMIFS(Costs!S:S,Costs!$A:$A,Summary_CDP,Costs!$B:$B,$H20)/1000 -> 2669.0787 | AA20: =SUMIFS(Costs!T:T,Costs!$A:$A,Summary_CDP,Costs!$B:$B,$H20)/1000 -> 2864.1008 | AB20: =SUMIFS(Costs!U:U,Costs!$A:$A,Summary_CDP,Costs!$B:$B,$H20)/1000 -> 3254.3606 | AC20: =SUMIFS(Costs!V:V,Costs!$A:$A,Summary_CDP,Costs!$B:$B,$H20)/1000 -> 3783.8368 | AD20: =SUMIFS(Costs!W:W,Costs!$A:$A,Summary_CDP,Costs!$B:$B,$H20)/1000 -> 3974.4237 | AE20: =SUMIFS(Costs!X:X,Costs!$A:$A,Summary_CDP,Costs!$B:$B,$H20)/1000 -> 4489.4307 | AF20: =SUMIFS(Costs!Y:Y,Costs!$A:$A,Summary_CDP,Costs!$B:$B,$H20)/1000 -> 5217.6553 | AG20: =SUMIFS(Costs!Z:Z,Costs!$A:$A,Summary_CDP,Costs!$B:$B,$H20)/1000 -> 5414.7676 | AH20: =SUMIFS(Costs!AA:AA,Costs!$A:$A,Summary_CDP,Costs!$B:$B,$H20)/1000 -> 5679.092 | AI20: =SUMIFS(Costs!AB:AB,Costs!$A:$A,Summary_CDP,Costs!$B:$B,$H20)/1000 -> 6140.5514 | AJ20: =SUMIFS(Costs!AC:AC,Costs!$A:$A,Summary_CDP,Costs!$B:$B,$H20)/1000 -> 7420.8291 | AK20: =SUMIFS(Costs!AD:AD,Costs!$A:$A,Summary_CDP,Costs!$B:$B,$H20)/1000 -> 7429.0215
H21: Flow Path Augmentation | I21: =NPV(WACC,J21:AK21)/(1+WACC)^2 -> 8844.3062 | J21: =SUMIFS(Costs!C:C,Costs!$A:$A,Summary_CDP,Costs!$B:$B,$H21)/1000 -> 0 | K21: =SUMIFS(Costs!D:D,Costs!$A:$A,Summary_CDP,Costs!$B:$B,$H21)/1000 -> 0 | L21: =SUMIFS(Costs!E:E,Costs!$A:$A,Summary_CDP,Costs!$B:$B,$H21)/1000 -> 0 | M21: =SUMIFS(Costs!F:F,Costs!$A:$A,Summary_CDP,Costs!$B:$B,$H21)/1000 -> 0 | N21: =SUMIFS(Costs!G:G,Costs!$A:$A,Summary_CDP,Costs!$B:$B,$H21)/1000 -> 242.49666 | O21: =SUMIFS(Costs!H:H,Costs!$A:$A,Summary_CDP,Costs!$B:$B,$H21)/1000 -> 535.93068 | P21: =SUMIFS(Costs!I:I,Costs!$A:$A,Summary_CDP,Costs!$B:$B,$H21)/1000 -> 826.2301 | Q21: =SUMIFS(Costs!J:J,Costs!$A:$A,Summary_CDP,Costs!$B:$B,$H21)/1000 -> 936.63792 | R21: =SUMIFS(Costs!K:K,Costs!$A:$A,Summary_CDP,Costs!$B:$B,$H21)/1000 -> 1149.7041 | S21: =SUMIFS(Costs!L:L,Costs!$A:$A,Summary_CDP,Costs!$B:$B,$H21)/1000 -> 1405.8711 | T21: =SUMIFS(Costs!M:M,Costs!$A:$A,Summary_CDP,Costs!$B:$B,$H21)/1000 -> 1405.8711 | U21: =SUMIFS(Costs!N:N,Costs!$A:$A,Summary_CDP,Costs!$B:$B,$H21)/1000 -> 1405.8711 | V21: =SUMIFS(Costs!O:O,Costs!$A:$A,Summary_CDP,Costs!$B:$B,$H21)/1000 -> 1405.8711 | W21: =SUMIFS(Costs!P:P,Costs!$A:$A,Summary_CDP,Costs!$B:$B,$H21)/1000 -> 1405.8711 | X21: =SUMIFS(Costs!Q:Q,Costs!$A:$A,Summary_CDP,Costs!$B:$B,$H21)/1000 -> 1405.8711 | Y21: =SUMIFS(Costs!R:R,Costs!$A:$A,Summary_CDP,Costs!$B:$B,$H21)/1000 -> 1405.8711 | Z21: =SUMIFS(Costs!S:S,Costs!$A:$A,Summary_CDP,Costs!$B:$B,$H21)/1000 -> 1405.8711 | AA21: =SUMIFS(Costs!T:T,Costs!$A:$A,Summary_CDP,Costs!$B:$B,$H21)/1000 -> 1541.0075 | AB21: =SUMIFS(Costs!U:U,Costs!$A:$A,Summary_CDP,Costs!$B:$B,$H21)/1000 -> 1541.0075 | AC21: =SUMIFS(Costs!V:V,Costs!$A:$A,Summary_CDP,Costs!$B:$B,$H21)/1000 -> 1724.9044 | AD21: =SUMIFS(Costs!W:W,Costs!$A:$A,Summary_CDP,Costs!$B:$B,$H21)/1000 -> 1724.9044 | AE21: =SUMIFS(Costs!X:X,Costs!$A:$A,Summary_CDP,Costs!$B:$B,$H21)/1000 -> 1724.9044 | AF21: =SUMIFS(Costs!Y:Y,Costs!$A:$A,Summary_CDP,Costs!$B:$B,$H21)/1000 -> 1926.6512 | AG21: =SUMIFS(Costs!Z:Z,Costs!$A:$A,Summary_CDP,Costs!$B:$B,$H21)/1000 -> 1926.6512 | AH21: =SUMIFS(Costs!AA:AA,Costs!$A:$A,Summary_CDP,Costs!$B:$B,$H21)/1000 -> 1926.6512 | AI21: =SUMIFS(Costs!AB:AB,Costs!$A:$A,Summary_CDP,Costs!$B:$B,$H21)/1000 -> 1926.6512 | AJ21: =SUMIFS(Costs!AC:AC,Costs!$A:$A,Summary_CDP,Costs!$B:$B,$H21)/1000 -> 1926.6512 | AK21: =SUMIFS(Costs!AD:AD,Costs!$A:$A,Summary_CDP,Costs!$B:$B,$H21)/1000 -> 1926.6512
H22: NPV and annual costs | I22: =SUM(I15:I21) -> 279338.25 | J22: =SUM(J15:J21) -> 7169.3478 | K22: =SUM(K15:K21) -> 7936.7185 | L22: =SUM(L15:L21) -> 10246.393 | M22: =SUM(M15:M21) -> 11003.592 | N22: =SUM(N15:N21) -> 14035.81 | O22: =SUM(O15:O21) -> 15758.017 | P22: =SUM(P15:P21) -> 16480.207 | ... AK22: =SUM(AK15:AK21) -> 99631.903
H23: *Net present value as at 1 July 2021
A29: =B30&" capacity by year" -> NEM capacity by year
A30: Select region | B30: NEM
H32: Capacity (MW) | I32: 2023-24 | J32: 2024-25 | K32: 2025-26 | L32: 2026-27 | M32: 2027-28 | N32: 2028-29 | O32: 2029-30 | P32: 2030-31 | Q32: 2031-32 | R32: 2032-33 | S32: 2033-34 | T32: 2034-35 | U32: 2035-36 | V32: 2036-37 | W32: 2037-38 | X32: 2038-39 | Y32: 2039-40 | Z32: 2040-41 | AA32: 2041-42 | AB32: 2042-43 | AC32: 2043-44 | AD32: 2044-45 | AE32: 2045-46 | AF32: 2046-47 | AG32: 2047-48 | AH32: 2048-49 | AI32: 2049-50 | AJ32: 2050-51
H33: Black Coal | I33: =SUMIFS(Capacity!E:E,Capacity!$A:$A,Summary_CDP,Capacity!$B:$B,IF($B$30="NEM","*",$B$30),Capacity!$C:$C,$H33) -> 16456 | J33: =SUMIFS(Capacity!F:F,Capacity!$A:$A,Summary_CDP,Capacity!$B:$B,IF($B$30="NEM","*",$B$30),Capacity!$C:$C,$H33) -> 16456 | K33: =SUMIFS(Capacity!G:G,Capacity!$A:$A,Summary_CDP,Capacity!$B:$B,IF($B$30="NEM","*",$B$30),Capacity!$C:$C,$H33) -> 10402 | L33: =SUMIFS(Capacity!H:H,Capacity!$A:$A,Summary_CDP,Capacity!$B:$B,IF($B$30="NEM","*",$B$30),Capacity!$C:$C,$H33) -> 7547 | M33: =SUMIFS(Capacity!I:I,Capacity!$A:$A,Summary_CDP,Capacity!$B:$B,IF($B$30="NEM","*",$B$30),Capacity!$C:$C,$H33) -> 4202 | N33: =SUMIFS(Capacity!J:J,Capacity!$A:$A,Summary_CDP,Capacity!$B:$B,IF($B$30="NEM","*",$B$30),Capacity!$C:$C,$H33) -> 3082 | O33: =SUMIFS(Capacity!K:K,Capacity!$A:$A,Summary_CDP,Capacity!$B:$B,IF($B$30="NEM","*",$B$30),Capacity!$C:$C,$H33) -> 2242 | P33: =SUMIFS(Capacity!L:L,Capacity!$A:$A,Summary_CDP,Capacity!$B:$B,IF($B$30="NEM","*",$B$30),Capacity!$C:$C,$H33) -> 0 | Q33: =SUMIFS(Capacity!M:M,Capacity!$A:$A,Summary_CDP,Capacity!$B:$B,IF($B$30="NEM","*",$B$30),Capacity!$C:$C,$H33) -> 0 | R33: =SUMIFS(Capacity!N:N,Capacity!$A:$A,Summary_CDP,Capacity!$B:$B,IF($B$30="NEM","*",$B$30),Capacity!$C:$C,$H33) -> 0 | S33: =SUMIFS(Capacity!O:O,Capacity!$A:$A,Summary_CDP,Capacity!$B:$B,IF($B$30="NEM","*",$B$30),Capacity!$C:$C,$H33) -> 0 | T33: =SUMIFS(Capacity!P:P,Capacity!$A:$A,Summary_CDP,Capacity!$B:$B,IF($B$30="NEM","*",$B$30),Capacity!$C:$C,$H33) -> 0 | U33: =SUMIFS(Capacity!Q:Q,Capacity!$A:$A,Summary_CDP,Capacity!$B:$B,IF($B$30="NEM","*",$B$30),Capacity!$C:$C,$H33) -> 0 | V33: =SUMIFS(Capacity!R:R,Capacity!$A:$A,Summary_CDP,Capacity!$B:$B,IF($B$30="NEM","*",$B$30),Capacity!$C:$C,$H33) -> 0 | W33: =SUMIFS(Capacity!S:S,Capacity!$A:$A,Summary_CDP,Capacity!$B:$B,IF($B$30="NEM","*",$B$30),Capacity!$C:$C,$H33) -> 0 | X33: =SUMIFS(Capacity!T:T,Capacity!$A:$A,Summary_CDP,Capacity!$B:$B,IF($B$30="NEM","*",$B$30),Capacity!$C:$C,$H33) -> 0 | Y33: =SUMIFS(Capacity!U:U,Capacity!$A:$A,Summary_CDP,Capacity!$B:$B,IF($B$30="NEM","*",$B$30),Capacity!$C:$C,$H33) -> 0 | Z33: =SUMIFS(Capacity!V:V,Capacity!$A:$A,Summary_CDP,Capacity!$B:$B,IF($B$30="NEM","*",$B$30),Capacity!$C:$C,$H33) -> 0 | AA33: =SUMIFS(Capacity!W:W,Capacity!$A:$A,Summary_CDP,Capacity!$B:$B,IF($B$30="NEM","*",$B$30),Capacity!$C:$C,$H33) -> 0 | AB33: =SUMIFS(Capacity!X:X,Capacity!$A:$A,Summary_CDP,Capacity!$B:$B,IF($B$30="NEM","*",$B$30),Capacity!$C:$C,$H33) -> 0 | AC33: =SUMIFS(Capacity!Y:Y,Capacity!$A:$A,Summary_CDP,Capacity!$B:$B,IF($B$30="NEM","*",$B$30),Capacity!$C:$C,$H33) -> 0 | AD33: =SUMIFS(Capacity!Z:Z,Capacity!$A:$A,Summary_CDP,Capacity!$B:$B,IF($B$30="NEM","*",$B$30),Capacity!$C:$C,$H33) -> 0 | AE33: =SUMIFS(Capacity!AA:AA,Capacity!$A:$A,Summary_CDP,Capacity!$B:$B,IF($B$30="NEM","*",$B$30),Capacity!$C:$C,$H33) -> 0 | AF33: =SUMIFS(Capacity!AB:AB,Capacity!$A:$A,Summary_CDP,Capacity!$B:$B,IF($B$30="NEM","*",$B$30),Capacity!$C:$C,$H33) -> 0 | AG33: =SUMIFS(Capacity!AC:AC,Capacity!$A:$A,Summary_CDP,Capacity!$B:$B,IF($B$30="NEM","*",$B$30),Capacity!$C:$C,$H33) -> 0 | AH33: =SUMIFS(Capacity!AD:AD,Capacity!$A:$A,Summary_CDP,Capacity!$B:$B,IF($B$30="NEM","*",$B$30),Capacity!$C:$C,$H33) -> 0 | AI33: =SUMIFS(Capacity!AE:AE,Capacity!$A:$A,Summary_CDP,Capacity!$B:$B,IF($B$30="NEM","*",$B$30),Capacity!$C:$C,$H33) -> 0 | AJ33: =SUMIFS(Capacity!AF:AF,Capacity!$A:$A,Summary_CDP,Capacity!$B:$B,IF($B$30="NEM","*",$B$30),Capacity!$C:$C,$H33) -> 0
H34: Brown Coal | I34: =SUMIFS(Capacity!E:E,Capacity!$A:$A,Summary_CDP,Capacity!$B:$B,IF($B$30="NEM","*",$B$30),Capacity!$C:$C,$H34) -> 4820 | J34: =SUMIFS(Capacity!F:F,Capacity!$A:$A,Summary_CDP,Capacity!$B:$B,IF($B$30="NEM","*",$B$30),Capacity!$C:$C,$H34) -> 4820 | K34: =SUMIFS(Capacity!G:G,Capacity!$A:$A,Summary_CDP,Capacity!$B:$B,IF($B$30="NEM","*",$B$30),Capacity!$C:$C,$H34) -> 3385 | L34: =SUMIFS(Capacity!H:H,Capacity!$A:$A,Summary_CDP,Capacity!$B:$B,IF($B$30="NEM","*",$B$30),Capacity!$C:$C,$H34) -> 2805 | M34: =SUMIFS(Capacity!I:I,Capacity!$A:$A,Summary_CDP,Capacity!$B:$B,IF($B$30="NEM","*",$B$30),Capacity!$C:$C,$H34) -> 1665 | N34: =SUMIFS(Capacity!J:J,Capacity!$A:$A,Summary_CDP,Capacity!$B:$B,IF($B$30="NEM","*",$B$30),Capacity!$C:$C,$H34) -> 1120 | O34: =SUMIFS(Capacity!K:K,Capacity!$A:$A,Summary_CDP,Capacity!$B:$B,IF($B$30="NEM","*",$B$30),Capacity!$C:$C,$H34) -> 1120 | P34: =SUMIFS(Capacity!L:L,Capacity!$A:$A,Summary_CDP,Capacity!$B:$B,IF($B$30="NEM","*",$B$30),Capacity!$C:$C,$H34) -> 0 | Q34: =SUMIFS(Capacity!M:M,Capacity!$A:$A,Summary_CDP,Capacity!$B:$B,IF($B$30="NEM","*",$B$30),Capacity!$C:$C,$H34) -> 0 | R34: =SUMIFS(Capacity!N:N,Capacity!$A:$A,Summary_CDP,Capacity!$B:$B,IF($B$30="NEM","*",$B$30),Capacity!$C:$C,$H34) -> 0 | S34: =SUMIFS(Capacity!O:O,Capacity!$A:$A,Summary_CDP,Capacity!$B:$B,IF($B$30="NEM","*",$B$30),Capacity!$C:$C,$H34) -> 0 | T34: =SUMIFS(Capacity!P:P,Capacity!$A:$A,Summary_CDP,Capacity!$B:$B,IF($B$30="NEM","*",$B$30),Capacity!$C:$C,$H34) -> 0 | U34: =SUMIFS(Capacity!Q:Q,Capacity!$A:$A,Summary_CDP,Capacity!$B:$B,IF($B$30="NEM","*",$B$30),Capacity!$C:$C,$H34) -> 0 | V34: =SUMIFS(Capacity!R:R,Capacity!$A:$A,Summary_CDP,Capacity!$B:$B,IF($B$30="NEM","*",$B$30),Capacity!$C:$C,$H34) -> 0 | W34: =SUMIFS(Capacity!S:S,Capacity!$A:$A,Summary_CDP,Capacity!$B:$B,IF($B$30="NEM","*",$B$30),Capacity!$C:$C,$H34) -> 0 | X34: =SUMIFS(Capacity!T:T,Capacity!$A:$A,Summary_CDP,Capacity!$B:$B,IF($B$30="NEM","*",$B$30),Capacity!$C:$C,$H34) -> 0 | Y34: =SUMIFS(Capacity!U:U,Capacity!$A:$A,Summary_CDP,Capacity!$B:$B,IF($B$30="NEM","*",$B$30),Capacity!$C:$C,$H34) -> 0 | Z34: =SUMIFS(Capacity!V:V,Capacity!$A:$A,Summary_CDP,Capacity!$B:$B,IF($B$30="NEM","*",$B$30),Capacity!$C:$C,$H34) -> 0 | AA34: =SUMIFS(Capacity!W:W,Capacity!$A:$A,Summary_CDP,Capacity!$B:$B,IF($B$30="NEM","*",$B$30),Capacity!$C:$C,$H34) -> 0 | AB34: =SUMIFS(Capacity!X:X,Capacity!$A:$A,Summary_CDP,Capacity!$B:$B,IF($B$30="NEM","*",$B$30),Capacity!$C:$C,$H34) -> 0 | AC34: =SUMIFS(Capacity!Y:Y,Capacity!$A:$A,Summary_CDP,Capacity!$B:$B,IF($B$30="NEM","*",$B$30),Capacity!$C:$C,$H34) -> 0 | AD34: =SUMIFS(Capacity!Z:Z,Capacity!$A:$A,Summary_CDP,Capacity!$B:$B,IF($B$30="NEM","*",$B$30),Capacity!$C:$C,$H34) -> 0 | AE34: =SUMIFS(Capacity!AA:AA,Capacity!$A:$A,Summary_CDP,Capacity!$B:$B,IF($B$30="NEM","*",$B$30),Capacity!$C:$C,$H34) -> 0 | AF34: =SUMIFS(Capacity!AB:AB,Capacity!$A:$A,Summary_CDP,Capacity!$B:$B,IF($B$30="NEM","*",$B$30),Capacity!$C:$C,$H34) -> 0 | AG34: =SUMIFS(Capacity!AC:AC,Capacity!$A:$A,Summary_CDP,Capacity!$B:$B,IF($B$30="NEM","*",$B$30),Capacity!$C:$C,$H34) -> 0 | AH34: =SUMIFS(Capacity!AD:AD,Capacity!$A:$A,Summary_CDP,Capacity!$B:$B,IF($B$30="NEM","*",$B$30),Capacity!$C:$C,$H34) -> 0 | AI34: =SUMIFS(Capacity!AE:AE,Capacity!$A:$A,Summary_CDP,Capacity!$B:$B,IF($B$30="NEM","*",$B$30),Capacity!$C:$C,$H34) -> 0 | AJ34: =SUMIFS(Capacity!AF:AF,Capacity!$A:$A,Summary_CDP,Capacity!$B:$B,IF($B$30="NEM","*",$B$30),Capacity!$C:$C,$H34) -> 0
H35: Mid-merit Gas | I35: =SUMIFS(Capacity!E:E,Capacity!$A:$A,Summary_CDP,Capacity!$B:$B,IF($B$30="NEM","*",$B$30),Capacity!$C:$C,$H35) -> 4074.9 | J35: =SUMIFS(Capacity!F:F,Capacity!$A:$A,Summary_CDP,Capacity!$B:$B,IF($B$30="NEM","*",$B$30),Capacity!$C:$C,$H35) -> 4074.9 | K35: =SUMIFS(Capacity!G:G,Capacity!$A:$A,Summary_CDP,Capacity!$B:$B,IF($B$30="NEM","*",$B$30),Capacity!$C:$C,$H35) -> 2386.9 | L35: =SUMIFS(Capacity!H:H,Capacity!$A:$A,Summary_CDP,Capacity!$B:$B,IF($B$30="NEM","*",$B$30),Capacity!$C:$C,$H35) -> 2386.9 | M35: =SUMIFS(Capacity!I:I,Capacity!$A:$A,Summary_CDP,Capacity!$B:$B,IF($B$30="NEM","*",$B$30),Capacity!$C:$C,$H35) -> 2386.9 | N35: =SUMIFS(Capacity!J:J,Capacity!$A:$A,Summary_CDP,Capacity!$B:$B,IF($B$30="NEM","*",$B$30),Capacity!$C:$C,$H35) -> 2386.9 | O35: =SUMIFS(Capacity!K:K,Capacity!$A:$A,Summary_CDP,Capacity!$B:$B,IF($B$30="NEM","*",$B$30),Capacity!$C:$C,$H35) -> 2386.9 | P35: =SUMIFS(Capacity!L:L,Capacity!$A:$A,Summary_CDP,Capacity!$B:$B,IF($B$30="NEM","*",$B$30),Capacity!$C:$C,$H35) -> 2386.9 | Q35: =SUMIFS(Capacity!M:M,Capacity!$A:$A,Summary_CDP,Capacity!$B:$B,IF($B$30="NEM","*",$B$30),Capacity!$C:$C,$H35) -> 2386.9 | R35: =SUMIFS(Capacity!N:N,Capacity!$A:$A,Summary_CDP,Capacity!$B:$B,IF($B$30="NEM","*",$B$30),Capacity!$C:$C,$H35) -> 2386.9 | S35: =SUMIFS(Capacity!O:O,Capacity!$A:$A,Summary_CDP,Capacity!$B:$B,IF($B$30="NEM","*",$B$30),Capacity!$C:$C,$H35) -> 2386.9 | T35: =SUMIFS(Capacity!P:P,Capacity!$A:$A,Summary_CDP,Capacity!$B:$B,IF($B$30="NEM","*",$B$30),Capacity!$C:$C,$H35) -> 2386.9 | U35: =SUMIFS(Capacity!Q:Q,Capacity!$A:$A,Summary_CDP,Capacity!$B:$B,IF($B$30="NEM","*",$B$30),Capacity!$C:$C,$H35) -> 2386.9 | V35: =SUMIFS(Capacity!R:R,Capacity!$A:$A,Summary_CDP,Capacity!$B:$B,IF($B$30="NEM","*",$B$30),Capacity!$C:$C,$H35) -> 2001.9 | W35: =SUMIFS(Capacity!S:S,Capacity!$A:$A,Summary_CDP,Capacity!$B:$B,IF($B$30="NEM","*",$B$30),Capacity!$C:$C,$H35) -> 1472.9 | X35: =SUMIFS(Capacity!T:T,Capacity!$A:$A,Summary_CDP,Capacity!$B:$B,IF($B$30="NEM","*",$B$30),Capacity!$C:$C,$H35) -> 1472.9 | Y35: =SUMIFS(Capacity!U:U,Capacity!$A:$A,Summary_CDP,Capacity!$B:$B,IF($B$30="NEM","*",$B$30),Capacity!$C:$C,$H35) -> 1328.5 | Z35: =SUMIFS(Capacity!V:V,Capacity!$A:$A,Summary_CDP,Capacity!$B:$B,IF($B$30="NEM","*",$B$30),Capacity!$C:$C,$H35) -> 1328.5 | AA35: =SUMIFS(Capacity!W:W,Capacity!$A:$A,Summary_CDP,Capacity!$B:$B,IF($B$30="NEM","*",$B$30),Capacity!$C:$C,$H35) -> 1328.5 | AB35: =SUMIFS(Capacity!X:X,Capacity!$A:$A,Summary_CDP,Capacity!$B:$B,IF($B$30="NEM","*",$B$30),Capacity!$C:$C,$H35) -> 1328.5 | AC35: =SUMIFS(Capacity!Y:Y,Capacity!$A:$A,Summary_CDP,Capacity!$B:$B,IF($B$30="NEM","*",$B$30),Capacity!$C:$C,$H35) -> 888.5 | AD35: =SUMIFS(Capacity!Z:Z,Capacity!$A:$A,Summary_CDP,Capacity!$B:$B,IF($B$30="NEM","*",$B$30),Capacity!$C:$C,$H35) -> 888.5 | AE35: =SUMIFS(Capacity!AA:AA,Capacity!$A:$A,Summary_CDP,Capacity!$B:$B,IF($B$30="NEM","*",$B$30),Capacity!$C:$C,$H35) -> 244 | AF35: =SUMIFS(Capacity!AB:AB,Capacity!$A:$A,Summary_CDP,Capacity!$B:$B,IF($B$30="NEM","*",$B$30),Capacity!$C:$C,$H35) -> 0 | AG35: =SUMIFS(Capacity!AC:AC,Capacity!$A:$A,Summary_CDP,Capacity!$B:$B,IF($B$30="NEM","*",$B$30),Capacity!$C:$C,$H35) -> 0 | AH35: =SUMIFS(Capacity!AD:AD,Capacity!$A:$A,Summary_CDP,Capacity!$B:$B,IF($B$30="NEM","*",$B$30),Capacity!$C:$C,$H35) -> 0 | AI35: =SUMIFS(Capacity!AE:AE,Capacity!$A:$A,Summary_CDP,Capacity!$B:$B,IF($B$30="NEM","*",$B$30),Capacity!$C:$C,$H35) -> 0 | AJ35: =SUMIFS(Capacity!AF:AF,Capacity!$A:$A,Summary_CDP,Capacity!$B:$B,IF($B$30="NEM","*",$B$30),Capacity!$C:$C,$H35) -> 0
H36: Mid-merit Gas with CCS | I36: =SUMIFS(Capacity!E:E,Capacity!$A:$A,Summary_CDP,Capacity!$B:$B,IF($B$30="NEM","*",$B$30),Capacity!$C:$C,$H36) -> 0 | J36: =SUMIFS(Capacity!F:F,Capacity!$A:$A,Summary_CDP,Capacity!$B:$B,IF($B$30="NEM","*",$B$30),Capacity!$C:$C,$H36) -> 0 | K36: =SUMIFS(Capacity!G:G,Capacity!$A:$A,Summary_CDP,Capacity!$B:$B,IF($B$30="NEM","*",$B$30),Capacity!$C:$C,$H36) -> 0 | L36: =SUMIFS(Capacity!H:H,Capacity!$A:$A,Summary_CDP,Capacity!$B:$B,IF($B$30="NEM","*",$B$30),Capacity!$C:$C,$H36) -> 0 | M36: =SUMIFS(Capacity!I:I,Capacity!$A:$A,Summary_CDP,Capacity!$B:$B,IF($B$30="NEM","*",$B$30),Capacity!$C:$C,$H36) -> 0 | N36: =SUMIFS(Capacity!J:J,Capacity!$A:$A,Summary_CDP,Capacity!$B:$B,IF($B$30="NEM","*",$B$30),Capacity!$C:$C,$H36) -> 0 | O36: =SUMIFS(Capacity!K:K,Capacity!$A:$A,Summary_CDP,Capacity!$B:$B,IF($B$30="NEM","*",$B$30),Capacity!$C:$C,$H36) -> 0 | P36: =SUMIFS(Capacity!L:L,Capacity!$A:$A,Summary_CDP,Capacity!$B:$B,IF($B$30="NEM","*",$B$30),Capacity!$C:$C,$H36) -> 0 | Q36: =SUMIFS(Capacity!M:M,Capacity!$A:$A,Summary_CDP,Capacity!$B:$B,IF($B$30="NEM","*",$B$30),Capacity!$C:$C,$H36) -> 0 | R36: =SUMIFS(Capacity!N:N,Capacity!$A:$A,Summary_CDP,Capacity!$B:$B,IF($B$30="NEM","*",$B$30),Capacity!$C:$C,$H36) -> 0 | S36: =SUMIFS(Capacity!O:O,Capacity!$A:$A,Summary_CDP,Capacity!$B:$B,IF($B$30="NEM","*",$B$30),Capacity!$C:$C,$H36) -> 0 | T36: =SUMIFS(Capacity!P:P,Capacity!$A:$A,Summary_CDP,Capacity!$B:$B,IF($B$30="NEM","*",$B$30),Capacity!$C:$C,$H36) -> 0 | U36: =SUMIFS(Capacity!Q:Q,Capacity!$A:$A,Summary_CDP,Capacity!$B:$B,IF($B$30="NEM","*",$B$30),Capacity!$C:$C,$H36) -> 0 | V36: =SUMIFS(Capacity!R:R,Capacity!$A:$A,Summary_CDP,Capacity!$B:$B,IF($B$30="NEM","*",$B$30),Capacity!$C:$C,$H36) -> 0 | W36: =SUMIFS(Capacity!S:S,Capacity!$A:$A,Summary_CDP,Capacity!$B:$B,IF($B$30="NEM","*",$B$30),Capacity!$C:$C,$H36) -> 0 | X36: =SUMIFS(Capacity!T:T,Capacity!$A:$A,Summary_CDP,Capacity!$B:$B,IF($B$30="NEM","*",$B$30),Capacity!$C:$C,$H36) -> 0 | Y36: =SUMIFS(Capacity!U:U,Capacity!$A:$A,Summary_CDP,Capacity!$B:$B,IF($B$30="NEM","*",$B$30),Capacity!$C:$C,$H36) -> 0 | Z36: =SUMIFS(Capacity!V:V,Capacity!$A:$A,Summary_CDP,Capacity!$B:$B,IF($B$30="NEM","*",$B$30),Capacity!$C:$C,$H36) -> 0 | AA36: =SUMIFS(Capacity!W:W,Capacity!$A:$A,Summary_CDP,Capacity!$B:$B,IF($B$30="NEM","*",$B$30),Capacity!$C:$C,$H36) -> 0 | AB36: =SUMIFS(Capacity!X:X,Capacity!$A:$A,Summary_CDP,Capacity!$B:$B,IF($B$30="NEM","*",$B$30),Capacity!$C:$C,$H36) -> 0 | AC36: =SUMIFS(Capacity!Y:Y,Capacity!$A:$A,Summary_CDP,Capacity!$B:$B,IF($B$30="NEM","*",$B$30),Capacity!$C:$C,$H36) -> 0 | AD36: =SUMIFS(Capacity!Z:Z,Capacity!$A:$A,Summary_CDP,Capacity!$B:$B,IF($B$30="NEM","*",$B$30),Capacity!$C:$C,$H36) -> 0 | AE36: =SUMIFS(Capacity!AA:AA,Capacity!$A:$A,Summary_CDP,Capacity!$B:$B,IF($B$30="NEM","*",$B$30),Capacity!$C:$C,$H36) -> 0 | AF36: =SUMIFS(Capacity!AB:AB,Capacity!$A:$A,Summary_CDP,Capacity!$B:$B,IF($B$30="NEM","*",$B$30),Capacity!$C:$C,$H36) -> 0 | AG36: =SUMIFS(Capacity!AC:AC,Capacity!$A:$A,Summary_CDP,Capacity!$B:$B,IF($B$30="NEM","*",$B$30),Capacity!$C:$C,$H36) -> 0 | AH36: =SUMIFS(Capacity!AD:AD,Capacity!$A:$A,Summary_CDP,Capacity!$B:$B,IF($B$30="NEM","*",$B$30),Capacity!$C:$C,$H36) -> 0 | AI36: =SUMIFS(Capacity!AE:AE,Capacity!$A:$A,Summary_CDP,Capacity!$B:$B,IF($B$30="NEM","*",$B$30),Capacity!$C:$C,$H36) -> 0 | AJ36: =SUMIFS(Capacity!AF:AF,Capacity!$A:$A,Summary_CDP,Capacity!$B:$B,IF($B$30="NEM","*",$B$30),Capacity!$C:$C,$H36) -> 0
H37: Peaking Gas+Liquids | I37: =SUMIFS(Capacity!E:E,Capacity!$A:$A,Summary_CDP,Capacity!$B:$B,IF($B$30="NEM","*",$B$30),Capacity!$C:$C,$H37) -> 8305.359 | J37: =SUMIFS(Capacity!F:F,Capacity!$A:$A,Summary_CDP,Capacity!$B:$B,IF($B$30="NEM","*",$B$30),Capacity!$C:$C,$H37) -> 8305.359 | K37: =SUMIFS(Capacity!G:G,Capacity!$A:$A,Summary_CDP,Capacity!$B:$B,IF($B$30="NEM","*",$B$30),Capacity!$C:$C,$H37) -> 8305.359 | L37: =SUMIFS(Capacity!H:H,Capacity!$A:$A,Summary_CDP,Capacity!$B:$B,IF($B$30="NEM","*",$B$30),Capacity!$C:$C,$H37) -> 8305.359 | M37: =SUMIFS(Capacity!I:I,Capacity!$A:$A,Summary_CDP,Capacity!$B:$B,IF($B$30="NEM","*",$B$30),Capacity!$C:$C,$H37) -> 8305.359 | N37: =SUMIFS(Capacity!J:J,Capacity!$A:$A,Summary_CDP,Capacity!$B:$B,IF($B$30="NEM","*",$B$30),Capacity!$C:$C,$H37) -> 8773.7137 | O37: =SUMIFS(Capacity!K:K,Capacity!$A:$A,Summary_CDP,Capacity!$B:$B,IF($B$30="NEM","*",$B$30),Capacity!$C:$C,$H37) -> 8773.7137 | P37: =SUMIFS(Capacity!L:L,Capacity!$A:$A,Summary_CDP,Capacity!$B:$B,IF($B$30="NEM","*",$B$30),Capacity!$C:$C,$H37) -> 8391.2137 | Q37: =SUMIFS(Capacity!M:M,Capacity!$A:$A,Summary_CDP,Capacity!$B:$B,IF($B$30="NEM","*",$B$30),Capacity!$C:$C,$H37) -> 8391.2137 | R37: =SUMIFS(Capacity!N:N,Capacity!$A:$A,Summary_CDP,Capacity!$B:$B,IF($B$30="NEM","*",$B$30),Capacity!$C:$C,$H37) -> 8114.3537 | S37: =SUMIFS(Capacity!O:O,Capacity!$A:$A,Summary_CDP,Capacity!$B:$B,IF($B$30="NEM","*",$B$30),Capacity!$C:$C,$H37) -> 7652.3537 | T37: =SUMIFS(Capacity!P:P,Capacity!$A:$A,Summary_CDP,Capacity!$B:$B,IF($B$30="NEM","*",$B$30),Capacity!$C:$C,$H37) -> 7535.3537 | U37: =SUMIFS(Capacity!Q:Q,Capacity!$A:$A,Summary_CDP,Capacity!$B:$B,IF($B$30="NEM","*",$B$30),Capacity!$C:$C,$H37) -> 7405.3537 | V37: =SUMIFS(Capacity!R:R,Capacity!$A:$A,Summary_CDP,Capacity!$B:$B,IF($B$30="NEM","*",$B$30),Capacity!$C:$C,$H37) -> 7405.3537 | W37: =SUMIFS(Capacity!S:S,Capacity!$A:$A,Summary_CDP,Capacity!$B:$B,IF($B$30="NEM","*",$B$30),Capacity!$C:$C,$H37) -> 7405.3537 | X37: =SUMIFS(Capacity!T:T,Capacity!$A:$A,Summary_CDP,Capacity!$B:$B,IF($B$30="NEM","*",$B$30),Capacity!$C:$C,$H37) -> 9269.5644 | Y37: =SUMIFS(Capacity!U:U,Capacity!$A:$A,Summary_CDP,Capacity!$B:$B,IF($B$30="NEM","*",$B$30),Capacity!$C:$C,$H37) -> 8829.5644 | Z37: =SUMIFS(Capacity!V:V,Capacity!$A:$A,Summary_CDP,Capacity!$B:$B,IF($B$30="NEM","*",$B$30),Capacity!$C:$C,$H37) -> 8709.5644 | AA37: =SUMIFS(Capacity!W:W,Capacity!$A:$A,Summary_CDP,Capacity!$B:$B,IF($B$30="NEM","*",$B$30),Capacity!$C:$C,$H37) -> 8900.6327 | AB37: =SUMIFS(Capacity!X:X,Capacity!$A:$A,Summary_CDP,Capacity!$B:$B,IF($B$30="NEM","*",$B$30),Capacity!$C:$C,$H37) -> 8806.6327 | AC37: =SUMIFS(Capacity!Y:Y,Capacity!$A:$A,Summary_CDP,Capacity!$B:$B,IF($B$30="NEM","*",$B$30),Capacity!$C:$C,$H37) -> 12156.547 | AD37: =SUMIFS(Capacity!Z:Z,Capacity!$A:$A,Summary_CDP,Capacity!$B:$B,IF($B$30="NEM","*",$B$30),Capacity!$C:$C,$H37) -> 11386.989 | AE37: =SUMIFS(Capacity!AA:AA,Capacity!$A:$A,Summary_CDP,Capacity!$B:$B,IF($B$30="NEM","*",$B$30),Capacity!$C:$C,$H37) -> 11386.989 | AF37: =SUMIFS(Capacity!AB:AB,Capacity!$A:$A,Summary_CDP,Capacity!$B:$B,IF($B$30="NEM","*",$B$30),Capacity!$C:$C,$H37) -> 10683.989 | AG37: =SUMIFS(Capacity!AC:AC,Capacity!$A:$A,Summary_CDP,Capacity!$B:$B,IF($B$30="NEM","*",$B$30),Capacity!$C:$C,$H37) -> 10099.989 | AH37: =SUMIFS(Capacity!AD:AD,Capacity!$A:$A,Summary_CDP,Capacity!$B:$B,IF($B$30="NEM","*",$B$30),Capacity!$C:$C,$H37) -> 10099.989 | AI37: =SUMIFS(Capacity!AE:AE,Capacity!$A:$A,Summary_CDP,Capacity!$B:$B,IF($B$30="NEM","*",$B$30),Capacity!$C:$C,$H37) -> 11825.917 | AJ37: =SUMIFS(Capacity!AF:AF,Capacity!$A:$A,Summary_CDP,Capacity!$B:$B,IF($B$30="NEM","*",$B$30),Capacity!$C:$C,$H37) -> 11421.917
H38: Hydrogen Turbine | I38: =SUMIFS(Capacity!E:E,Capacity!$A:$A,Summary_CDP,Capacity!$B:$B,IF($B$30="NEM","*",$B$30),Capacity!$C:$C,$H38) -> 0 | J38: =SUMIFS(Capacity!F:F,Capacity!$A:$A,Summary_CDP,Capacity!$B:$B,IF($B$30="NEM","*",$B$30),Capacity!$C:$C,$H38) -> 0 | K38: =SUMIFS(Capacity!G:G,Capacity!$A:$A,Summary_CDP,Capacity!$B:$B,IF($B$30="NEM","*",$B$30),Capacity!$C:$C,$H38) -> 0 | L38: =SUMIFS(Capacity!H:H,Capacity!$A:$A,Summary_CDP,Capacity!$B:$B,IF($B$30="NEM","*",$B$30),Capacity!$C:$C,$H38) -> 0 | M38: =SUMIFS(Capacity!I:I,Capacity!$A:$A,Summary_CDP,Capacity!$B:$B,IF($B$30="NEM","*",$B$30),Capacity!$C:$C,$H38) -> 0 | N38: =SUMIFS(Capacity!J:J,Capacity!$A:$A,Summary_CDP,Capacity!$B:$B,IF($B$30="NEM","*",$B$30),Capacity!$C:$C,$H38) -> 0 | O38: =SUMIFS(Capacity!K:K,Capacity!$A:$A,Summary_CDP,Capacity!$B:$B,IF($B$30="NEM","*",$B$30),Capacity!$C:$C,$H38) -> 0 | P38: =SUMIFS(Capacity!L:L,Capacity!$A:$A,Summary_CDP,Capacity!$B:$B,IF($B$30="NEM","*",$B$30),Capacity!$C:$C,$H38) -> 0 | Q38: =SUMIFS(Capacity!M:M,Capacity!$A:$A,Summary_CDP,Capacity!$B:$B,IF($B$30="NEM","*",$B$30),Capacity!$C:$C,$H38) -> 0 | R38: =SUMIFS(Capacity!N:N,Capacity!$A:$A,Summary_CDP,Capacity!$B:$B,IF($B$30="NEM","*",$B$30),Capacity!$C:$C,$H38) -> 0 | S38: =SUMIFS(Capacity!O:O,Capacity!$A:$A,Summary_CDP,Capacity!$B:$B,IF($B$30="NEM","*",$B$30),Capacity!$C:$C,$H38) -> 0 | T38: =SUMIFS(Capacity!P:P,Capacity!$A:$A,Summary_CDP,Capacity!$B:$B,IF($B$30="NEM","*",$B$30),Capacity!$C:$C,$H38) -> 0 | U38: =SUMIFS(Capacity!Q:Q,Capacity!$A:$A,Summary_CDP,Capacity!$B:$B,IF($B$30="NEM","*",$B$30),Capacity!$C:$C,$H38) -> 0 | V38: =SUMIFS(Capacity!R:R,Capacity!$A:$A,Summary_CDP,Capacity!$B:$B,IF($B$30="NEM","*",$B$30),Capacity!$C:$C,$H38) -> 0 | W38: =SUMIFS(Capacity!S:S,Capacity!$A:$A,Summary_CDP,Capacity!$B:$B,IF($B$30="NEM","*",$B$30),Capacity!$C:$C,$H38) -> 0 | X38: =SUMIFS(Capacity!T:T,Capacity!$A:$A,Summary_CDP,Capacity!$B:$B,IF($B$30="NEM","*",$B$30),Capacity!$C:$C,$H38) -> 0 | Y38: =SUMIFS(Capacity!U:U,Capacity!$A:$A,Summary_CDP,Capacity!$B:$B,IF($B$30="NEM","*",$B$30),Capacity!$C:$C,$H38) -> 0 | Z38: =SUMIFS(Capacity!V:V,Capacity!$A:$A,Summary_CDP,Capacity!$B:$B,IF($B$30="NEM","*",$B$30),Capacity!$C:$C,$H38) -> 0 | AA38: =SUMIFS(Capacity!W:W,Capacity!$A:$A,Summary_CDP,Capacity!$B:$B,IF($B$30="NEM","*",$B$30),Capacity!$C:$C,$H38) -> 0 | AB38: =SUMIFS(Capacity!X:X,Capacity!$A:$A,Summary_CDP,Capacity!$B:$B,IF($B$30="NEM","*",$B$30),Capacity!$C:$C,$H38) -> 0 | AC38: =SUMIFS(Capacity!Y:Y,Capacity!$A:$A,Summary_CDP,Capacity!$B:$B,IF($B$30="NEM","*",$B$30),Capacity!$C:$C,$H38) -> 0 | AD38: =SUMIFS(Capacity!Z:Z,Capacity!$A:$A,Summary_CDP,Capacity!$B:$B,IF($B$30="NEM","*",$B$30),Capacity!$C:$C,$H38) -> 0 | AE38: =SUMIFS(Capacity!AA:AA,Capacity!$A:$A,Summary_CDP,Capacity!$B:$B,IF($B$30="NEM","*",$B$30),Capacity!$C:$C,$H38) -> 0 | AF38: =SUMIFS(Capacity!AB:AB,Capacity!$A:$A,Summary_CDP,Capacity!$B:$B,IF($B$30="NEM","*",$B$30),Capacity!$C:$C,$H38) -> 0 | AG38: =SUMIFS(Capacity!AC:AC,Capacity!$A:$A,Summary_CDP,Capacity!$B:$B,IF($B$30="NEM","*",$B$30),Capacity!$C:$C,$H38) -> 0 | AH38: =SUMIFS(Capacity!AD:AD,Capacity!$A:$A,Summary_CDP,Capacity!$B:$B,IF($B$30="NEM","*",$B$30),Capacity!$C:$C,$H38) -> 0 | AI38: =SUMIFS(Capacity!AE:AE,Capacity!$A:$A,Summary_CDP,Capacity!$B:$B,IF($B$30="NEM","*",$B$30),Capacity!$C:$C,$H38) -> 8612.6106 | AJ38: =SUMIFS(Capacity!AF:AF,Capacity!$A:$A,Summary_CDP,Capacity!$B:$B,IF($B$30="NEM","*",$B$30),Capacity!$C:$C,$H38) -> 8612.6106
H39: Hydro | I39: =SUMIFS(Capacity!E:E,Capacity!$A:$A,Summary_CDP,Capacity!$B:$B,IF($B$30="NEM","*",$B$30),Capacity!$C:$C,$H39) -> 6818.12 | J39: =SUMIFS(Capacity!F:F,Capacity!$A:$A,Summary_CDP,Capacity!$B:$B,IF($B$30="NEM","*",$B$30),Capacity!$C:$C,$H39) -> 6818.12 | K39: =SUMIFS(Capacity!G:G,Capacity!$A:$A,Summary_CDP,Capacity!$B:$B,IF($B$30="NEM","*",$B$30),Capacity!$C:$C,$H39) -> 6818.12 | L39: =SUMIFS(Capacity!H:H,Capacity!$A:$A,Summary_CDP,Capacity!$B:$B,IF($B$30="NEM","*",$B$30),Capacity!$C:$C,$H39) -> 6818.12 | M39: =SUMIFS(Capacity!I:I,Capacity!$A:$A,Summary_CDP,Capacity!$B:$B,IF($B$30="NEM","*",$B$30),Capacity!$C:$C,$H39) -> 6818.12 | N39: =SUMIFS(Capacity!J:J,Capacity!$A:$A,Summary_CDP,Capacity!$B:$B,IF($B$30="NEM","*",$B$30),Capacity!$C:$C,$H39) -> 6818.12 | O39: =SUMIFS(Capacity!K:K,Capacity!$A:$A,Summary_CDP,Capacity!$B:$B,IF($B$30="NEM","*",$B$30),Capacity!$C:$C,$H39) -> 7208.12 | P39: =SUMIFS(Capacity!L:L,Capacity!$A:$A,Summary_CDP,Capacity!$B:$B,IF($B$30="NEM","*",$B$30),Capacity!$C:$C,$H39) -> 7208.12 | Q39: =SUMIFS(Capacity!M:M,Capacity!$A:$A,Summary_CDP,Capacity!$B:$B,IF($B$30="NEM","*",$B$30),Capacity!$C:$C,$H39) -> 7208.12 | R39: =SUMIFS(Capacity!N:N,Capacity!$A:$A,Summary_CDP,Capacity!$B:$B,IF($B$30="NEM","*",$B$30),Capacity!$C:$C,$H39) -> 7208.12 | S39: =SUMIFS(Capacity!O:O,Capacity!$A:$A,Summary_CDP,Capacity!$B:$B,IF($B$30="NEM","*",$B$30),Capacity!$C:$C,$H39) -> 7208.12 | T39: =SUMIFS(Capacity!P:P,Capacity!$A:$A,Summary_CDP,Capacity!$B:$B,IF($B$30="NEM","*",$B$30),Capacity!$C:$C,$H39) -> 7208.12 | U39: =SUMIFS(Capacity!Q:Q,Capacity!$A:$A,Summary_CDP,Capacity!$B:$B,IF($B$30="NEM","*",$B$30),Capacity!$C:$C,$H39) -> 7208.12 | V39: =SUMIFS(Capacity!R:R,Capacity!$A:$A,Summary_CDP,Capacity!$B:$B,IF($B$30="NEM","*",$B$30),Capacity!$C:$C,$H39) -> 7208.12 | W39: =SUMIFS(Capacity!S:S,Capacity!$A:$A,Summary_CDP,Capacity!$B:$B,IF($B$30="NEM","*",$B$30),Capacity!$C:$C,$H39) -> 7121.72 | X39: =SUMIFS(Capacity!T:T,Capacity!$A:$A,Summary_CDP,Capacity!$B:$B,IF($B$30="NEM","*",$B$30),Capacity!$C:$C,$H39) -> 7121.72 | Y39: =SUMIFS(Capacity!U:U,Capacity!$A:$A,Summary_CDP,Capacity!$B:$B,IF($B$30="NEM","*",$B$30),Capacity!$C:$C,$H39) -> 7121.72 | Z39: =SUMIFS(Capacity!V:V,Capacity!$A:$A,Summary_CDP,Capacity!$B:$B,IF($B$30="NEM","*",$B$30),Capacity!$C:$C,$H39) -> 7121.72 | AA39: =SUMIFS(Capacity!W:W,Capacity!$A:$A,Summary_CDP,Capacity!$B:$B,IF($B$30="NEM","*",$B$30),Capacity!$C:$C,$H39) -> 7121.72 | AB39: =SUMIFS(Capacity!X:X,Capacity!$A:$A,Summary_CDP,Capacity!$B:$B,IF($B$30="NEM","*",$B$30),Capacity!$C:$C,$H39) -> 7055.72 | AC39: =SUMIFS(Capacity!Y:Y,Capacity!$A:$A,Summary_CDP,Capacity!$B:$B,IF($B$30="NEM","*",$B$30),Capacity!$C:$C,$H39) -> 7055.72 | AD39: =SUMIFS(Capacity!Z:Z,Capacity!$A:$A,Summary_CDP,Capacity!$B:$B,IF($B$30="NEM","*",$B$30),Capacity!$C:$C,$H39) -> 7055.72 | AE39: =SUMIFS(Capacity!AA:AA,Capacity!$A:$A,Summary_CDP,Capacity!$B:$B,IF($B$30="NEM","*",$B$30),Capacity!$C:$C,$H39) -> 7055.72 | AF39: =SUMIFS(Capacity!AB:AB,Capacity!$A:$A,Summary_CDP,Capacity!$B:$B,IF($B$30="NEM","*",$B$30),Capacity!$C:$C,$H39) -> 7055.72 | AG39: =SUMIFS(Capacity!AC:AC,Capacity!$A:$A,Summary_CDP,Capacity!$B:$B,IF($B$30="NEM","*",$B$30),Capacity!$C:$C,$H39) -> 7055.72 | AH39: =SUMIFS(Capacity!AD:AD,Capacity!$A:$A,Summary_CDP,Capacity!$B:$B,IF($B$30="NEM","*",$B$30),Capacity!$C:$C,$H39) -> 7055.72 | AI39: =SUMIFS(Capacity!AE:AE,Capacity!$A:$A,Summary_CDP,Capacity!$B:$B,IF($B$30="NEM","*",$B$30),Capacity!$C:$C,$H39) -> 7055.72 | AJ39: =SUMIFS(Capacity!AF:AF,Capacity!$A:$A,Summary_CDP,Capacity!$B:$B,IF($B$30="NEM","*",$B$30),Capacity!$C:$C,$H39) -> 7055.72
H40: Utility-scale Storage | I40: =SUMIFS(Capacity!E:E,Capacity!$A:$A,Summary_CDP,Capacity!$B:$B,IF($B$30="NEM","*",$B$30),Capacity!$C:$C,$H40) -> 1558.56 | J40: =SUMIFS(Capacity!F:F,Capacity!$A:$A,Summary_CDP,Capacity!$B:$B,IF($B$30="NEM","*",$B$30),Capacity!$C:$C,$H40) -> 1557.46 | K40: =SUMIFS(Capacity!G:G,Capacity!$A:$A,Summary_CDP,Capacity!$B:$B,IF($B$30="NEM","*",$B$30),Capacity!$C:$C,$H40) -> 3555.2419 | L40: =SUMIFS(Capacity!H:H,Capacity!$A:$A,Summary_CDP,Capacity!$B:$B,IF($B$30="NEM","*",$B$30),Capacity!$C:$C,$H40) -> 6481.0463 | M40: =SUMIFS(Capacity!I:I,Capacity!$A:$A,Summary_CDP,Capacity!$B:$B,IF($B$30="NEM","*",$B$30),Capacity!$C:$C,$H40) -> 9216.1182 | N40: =SUMIFS(Capacity!J:J,Capacity!$A:$A,Summary_CDP,Capacity!$B:$B,IF($B$30="NEM","*",$B$30),Capacity!$C:$C,$H40) -> 11055.301 | O40: =SUMIFS(Capacity!K:K,Capacity!$A:$A,Summary_CDP,Capacity!$B:$B,IF($B$30="NEM","*",$B$30),Capacity!$C:$C,$H40) -> 11057.244 | P40: =SUMIFS(Capacity!L:L,Capacity!$A:$A,Summary_CDP,Capacity!$B:$B,IF($B$30="NEM","*",$B$30),Capacity!$C:$C,$H40) -> 13439.528 | Q40: =SUMIFS(Capacity!M:M,Capacity!$A:$A,Summary_CDP,Capacity!$B:$B,IF($B$30="NEM","*",$B$30),Capacity!$C:$C,$H40) -> 13439.528 | R40: =SUMIFS(Capacity!N:N,Capacity!$A:$A,Summary_CDP,Capacity!$B:$B,IF($B$30="NEM","*",$B$30),Capacity!$C:$C,$H40) -> 13440.628 | S40: =SUMIFS(Capacity!O:O,Capacity!$A:$A,Summary_CDP,Capacity!$B:$B,IF($B$30="NEM","*",$B$30),Capacity!$C:$C,$H40) -> 13510.828 | T40: =SUMIFS(Capacity!P:P,Capacity!$A:$A,Summary_CDP,Capacity!$B:$B,IF($B$30="NEM","*",$B$30),Capacity!$C:$C,$H40) -> 13583.136 | U40: =SUMIFS(Capacity!Q:Q,Capacity!$A:$A,Summary_CDP,Capacity!$B:$B,IF($B$30="NEM","*",$B$30),Capacity!$C:$C,$H40) -> 16177.431 | V40: =SUMIFS(Capacity!R:R,Capacity!$A:$A,Summary_CDP,Capacity!$B:$B,IF($B$30="NEM","*",$B$30),Capacity!$C:$C,$H40) -> 17005.87 | W40: =SUMIFS(Capacity!S:S,Capacity!$A:$A,Summary_CDP,Capacity!$B:$B,IF($B$30="NEM","*",$B$30),Capacity!$C:$C,$H40) -> 18485.694 | X40: =SUMIFS(Capacity!T:T,Capacity!$A:$A,Summary_CDP,Capacity!$B:$B,IF($B$30="NEM","*",$B$30),Capacity!$C:$C,$H40) -> 18793.375 | Y40: =SUMIFS(Capacity!U:U,Capacity!$A:$A,Summary_CDP,Capacity!$B:$B,IF($B$30="NEM","*",$B$30),Capacity!$C:$C,$H40) -> 18792.275 | Z40: =SUMIFS(Capacity!V:V,Capacity!$A:$A,Summary_CDP,Capacity!$B:$B,IF($B$30="NEM","*",$B$30),Capacity!$C:$C,$H40) -> 20103.707 | AA40: =SUMIFS(Capacity!W:W,Capacity!$A:$A,Summary_CDP,Capacity!$B:$B,IF($B$30="NEM","*",$B$30),Capacity!$C:$C,$H40) -> 28248.188 | AB40: =SUMIFS(Capacity!X:X,Capacity!$A:$A,Summary_CDP,Capacity!$B:$B,IF($B$30="NEM","*",$B$30),Capacity!$C:$C,$H40) -> 28349.645 | AC40: =SUMIFS(Capacity!Y:Y,Capacity!$A:$A,Summary_CDP,Capacity!$B:$B,IF($B$30="NEM","*",$B$30),Capacity!$C:$C,$H40) -> 28840.233 | AD40: =SUMIFS(Capacity!Z:Z,Capacity!$A:$A,Summary_CDP,Capacity!$B:$B,IF($B$30="NEM","*",$B$30),Capacity!$C:$C,$H40) -> 30780.653 | AE40: =SUMIFS(Capacity!AA:AA,Capacity!$A:$A,Summary_CDP,Capacity!$B:$B,IF($B$30="NEM","*",$B$30),Capacity!$C:$C,$H40) -> 37455.491 | AF40: =SUMIFS(Capacity!AB:AB,Capacity!$A:$A,Summary_CDP,Capacity!$B:$B,IF($B$30="NEM","*",$B$30),Capacity!$C:$C,$H40) -> 37382.733 | AG40: =SUMIFS(Capacity!AC:AC,Capacity!$A:$A,Summary_CDP,Capacity!$B:$B,IF($B$30="NEM","*",$B$30),Capacity!$C:$C,$H40) -> 37047.052 | AH40: =SUMIFS(Capacity!AD:AD,Capacity!$A:$A,Summary_CDP,Capacity!$B:$B,IF($B$30="NEM","*",$B$30),Capacity!$C:$C,$H40) -> 47750.401 | AI40: =SUMIFS(Capacity!AE:AE,Capacity!$A:$A,Summary_CDP,Capacity!$B:$B,IF($B$30="NEM","*",$B$30),Capacity!$C:$C,$H40) -> 71709.968 | AJ40: =SUMIFS(Capacity!AF:AF,Capacity!$A:$A,Summary_CDP,Capacity!$B:$B,IF($B$30="NEM","*",$B$30),Capacity!$C:$C,$H40) -> 69913.132
H41: Coordinated DER Storage | I41: =SUMIFS(Capacity!E:E,Capacity!$A:$A,Summary_CDP,Capacity!$B:$B,IF($B$30="NEM","*",$B$30),Capacity!$C:$C,$H41) -> 366.507 | J41: =SUMIFS(Capacity!F:F,Capacity!$A:$A,Summary_CDP,Capacity!$B:$B,IF($B$30="NEM","*",$B$30),Capacity!$C:$C,$H41) -> 731.507 | K41: =SUMIFS(Capacity!G:G,Capacity!$A:$A,Summary_CDP,Capacity!$B:$B,IF($B$30="NEM","*",$B$30),Capacity!$C:$C,$H41) -> 1218.992 | L41: =SUMIFS(Capacity!H:H,Capacity!$A:$A,Summary_CDP,Capacity!$B:$B,IF($B$30="NEM","*",$B$30),Capacity!$C:$C,$H41) -> 1822.853 | M41: =SUMIFS(Capacity!I:I,Capacity!$A:$A,Summary_CDP,Capacity!$B:$B,IF($B$30="NEM","*",$B$30),Capacity!$C:$C,$H41) -> 2558.481 | N41: =SUMIFS(Capacity!J:J,Capacity!$A:$A,Summary_CDP,Capacity!$B:$B,IF($B$30="NEM","*",$B$30),Capacity!$C:$C,$H41) -> 3412.119 | O41: =SUMIFS(Capacity!K:K,Capacity!$A:$A,Summary_CDP,Capacity!$B:$B,IF($B$30="NEM","*",$B$30),Capacity!$C:$C,$H41) -> 4696.274 | P41: =SUMIFS(Capacity!L:L,Capacity!$A:$A,Summary_CDP,Capacity!$B:$B,IF($B$30="NEM","*",$B$30),Capacity!$C:$C,$H41) -> 5829.8005 | Q41: =SUMIFS(Capacity!M:M,Capacity!$A:$A,Summary_CDP,Capacity!$B:$B,IF($B$30="NEM","*",$B$30),Capacity!$C:$C,$H41) -> 7024.5443 | R41: =SUMIFS(Capacity!N:N,Capacity!$A:$A,Summary_CDP,Capacity!$B:$B,IF($B$30="NEM","*",$B$30),Capacity!$C:$C,$H41) -> 8398.683 | S41: =SUMIFS(Capacity!O:O,Capacity!$A:$A,Summary_CDP,Capacity!$B:$B,IF($B$30="NEM","*",$B$30),Capacity!$C:$C,$H41) -> 10091.142 | T41: =SUMIFS(Capacity!P:P,Capacity!$A:$A,Summary_CDP,Capacity!$B:$B,IF($B$30="NEM","*",$B$30),Capacity!$C:$C,$H41) -> 11935.595 | U41: =SUMIFS(Capacity!Q:Q,Capacity!$A:$A,Summary_CDP,Capacity!$B:$B,IF($B$30="NEM","*",$B$30),Capacity!$C:$C,$H41) -> 13875.121 | V41: =SUMIFS(Capacity!R:R,Capacity!$A:$A,Summary_CDP,Capacity!$B:$B,IF($B$30="NEM","*",$B$30),Capacity!$C:$C,$H41) -> 15894.635 | W41: =SUMIFS(Capacity!S:S,Capacity!$A:$A,Summary_CDP,Capacity!$B:$B,IF($B$30="NEM","*",$B$30),Capacity!$C:$C,$H41) -> 17933.751 | X41: =SUMIFS(Capacity!T:T,Capacity!$A:$A,Summary_CDP,Capacity!$B:$B,IF($B$30="NEM","*",$B$30),Capacity!$C:$C,$H41) -> 19983.078 | Y41: =SUMIFS(Capacity!U:U,Capacity!$A:$A,Summary_CDP,Capacity!$B:$B,IF($B$30="NEM","*",$B$30),Capacity!$C:$C,$H41) -> 21671.677 | Z41: =SUMIFS(Capacity!V:V,Capacity!$A:$A,Summary_CDP,Capacity!$B:$B,IF($B$30="NEM","*",$B$30),Capacity!$C:$C,$H41) -> 23318.225 | AA41: =SUMIFS(Capacity!W:W,Capacity!$A:$A,Summary_CDP,Capacity!$B:$B,IF($B$30="NEM","*",$B$30),Capacity!$C:$C,$H41) -> 24889.356 | AB41: =SUMIFS(Capacity!X:X,Capacity!$A:$A,Summary_CDP,Capacity!$B:$B,IF($B$30="NEM","*",$B$30),Capacity!$C:$C,$H41) -> 26447.73 | AC41: =SUMIFS(Capacity!Y:Y,Capacity!$A:$A,Summary_CDP,Capacity!$B:$B,IF($B$30="NEM","*",$B$30),Capacity!$C:$C,$H41) -> 28117.47 | AD41: =SUMIFS(Capacity!Z:Z,Capacity!$A:$A,Summary_CDP,Capacity!$B:$B,IF($B$30="NEM","*",$B$30),Capacity!$C:$C,$H41) -> 29806.333 | AE41: =SUMIFS(Capacity!AA:AA,Capacity!$A:$A,Summary_CDP,Capacity!$B:$B,IF($B$30="NEM","*",$B$30),Capacity!$C:$C,$H41) -> 31258.097 | AF41: =SUMIFS(Capacity!AB:AB,Capacity!$A:$A,Summary_CDP,Capacity!$B:$B,IF($B$30="NEM","*",$B$30),Capacity!$C:$C,$H41) -> 32733.875 | AG41: =SUMIFS(Capacity!AC:AC,Capacity!$A:$A,Summary_CDP,Capacity!$B:$B,IF($B$30="NEM","*",$B$30),Capacity!$C:$C,$H41) -> 34233.92 | AH41: =SUMIFS(Capacity!AD:AD,Capacity!$A:$A,Summary_CDP,Capacity!$B:$B,IF($B$30="NEM","*",$B$30),Capacity!$C:$C,$H41) -> 35763.291 | AI41: =SUMIFS(Capacity!AE:AE,Capacity!$A:$A,Summary_CDP,Capacity!$B:$B,IF($B$30="NEM","*",$B$30),Capacity!$C:$C,$H41) -> 37313.352 | AJ41: =SUMIFS(Capacity!AF:AF,Capacity!$A:$A,Summary_CDP,Capacity!$B:$B,IF($B$30="NEM","*",$B$30),Capacity!$C:$C,$H41) -> 37421.09
H42: Distributed Storage | I42: =SUMIFS(Capacity!E:E,Capacity!$A:$A,Summary_CDP,Capacity!$B:$B,IF($B$30="NEM","*",$B$30),Capacity!$C:$C,$H42) -> 1615.687 | J42: =SUMIFS(Capacity!F:F,Capacity!$A:$A,Summary_CDP,Capacity!$B:$B,IF($B$30="NEM","*",$B$30),Capacity!$C:$C,$H42) -> 2523.858 | K42: =SUMIFS(Capacity!G:G,Capacity!$A:$A,Summary_CDP,Capacity!$B:$B,IF($B$30="NEM","*",$B$30),Capacity!$C:$C,$H42) -> 3346.118 | L42: =SUMIFS(Capacity!H:H,Capacity!$A:$A,Summary_CDP,Capacity!$B:$B,IF($B$30="NEM","*",$B$30),Capacity!$C:$C,$H42) -> 4039.736 | M42: =SUMIFS(Capacity!I:I,Capacity!$A:$A,Summary_CDP,Capacity!$B:$B,IF($B$30="NEM","*",$B$30),Capacity!$C:$C,$H42) -> 4643.731 | N42: =SUMIFS(Capacity!J:J,Capacity!$A:$A,Summary_CDP,Capacity!$B:$B,IF($B$30="NEM","*",$B$30),Capacity!$C:$C,$H42) -> 5111.685 | O42: =SUMIFS(Capacity!K:K,Capacity!$A:$A,Summary_CDP,Capacity!$B:$B,IF($B$30="NEM","*",$B$30),Capacity!$C:$C,$H42) -> 5870.22 | P42: =SUMIFS(Capacity!L:L,Capacity!$A:$A,Summary_CDP,Capacity!$B:$B,IF($B$30="NEM","*",$B$30),Capacity!$C:$C,$H42) -> 6883.914 | Q42: =SUMIFS(Capacity!M:M,Capacity!$A:$A,Summary_CDP,Capacity!$B:$B,IF($B$30="NEM","*",$B$30),Capacity!$C:$C,$H42) -> 7823.741 | R42: =SUMIFS(Capacity!N:N,Capacity!$A:$A,Summary_CDP,Capacity!$B:$B,IF($B$30="NEM","*",$B$30),Capacity!$C:$C,$H42) -> 8822.021 | S42: =SUMIFS(Capacity!O:O,Capacity!$A:$A,Summary_CDP,Capacity!$B:$B,IF($B$30="NEM","*",$B$30),Capacity!$C:$C,$H42) -> 10032.986 | T42: =SUMIFS(Capacity!P:P,Capacity!$A:$A,Summary_CDP,Capacity!$B:$B,IF($B$30="NEM","*",$B$30),Capacity!$C:$C,$H42) -> 11279.352 | U42: =SUMIFS(Capacity!Q:Q,Capacity!$A:$A,Summary_CDP,Capacity!$B:$B,IF($B$30="NEM","*",$B$30),Capacity!$C:$C,$H42) -> 12411.971 | V42: =SUMIFS(Capacity!R:R,Capacity!$A:$A,Summary_CDP,Capacity!$B:$B,IF($B$30="NEM","*",$B$30),Capacity!$C:$C,$H42) -> 13450.545 | W42: =SUMIFS(Capacity!S:S,Capacity!$A:$A,Summary_CDP,Capacity!$B:$B,IF($B$30="NEM","*",$B$30),Capacity!$C:$C,$H42) -> 14351.891 | X42: =SUMIFS(Capacity!T:T,Capacity!$A:$A,Summary_CDP,Capacity!$B:$B,IF($B$30="NEM","*",$B$30),Capacity!$C:$C,$H42) -> 15102.709 | Y42: =SUMIFS(Capacity!U:U,Capacity!$A:$A,Summary_CDP,Capacity!$B:$B,IF($B$30="NEM","*",$B$30),Capacity!$C:$C,$H42) -> 15417.929 | Z42: =SUMIFS(Capacity!V:V,Capacity!$A:$A,Summary_CDP,Capacity!$B:$B,IF($B$30="NEM","*",$B$30),Capacity!$C:$C,$H42) -> 15594.936 | AA42: =SUMIFS(Capacity!W:W,Capacity!$A:$A,Summary_CDP,Capacity!$B:$B,IF($B$30="NEM","*",$B$30),Capacity!$C:$C,$H42) -> 15616.079 | AB42: =SUMIFS(Capacity!X:X,Capacity!$A:$A,Summary_CDP,Capacity!$B:$B,IF($B$30="NEM","*",$B$30),Capacity!$C:$C,$H42) -> 15610.974 | AC42: =SUMIFS(Capacity!Y:Y,Capacity!$A:$A,Summary_CDP,Capacity!$B:$B,IF($B$30="NEM","*",$B$30),Capacity!$C:$C,$H42) -> 15555.227 | AD42: =SUMIFS(Capacity!Z:Z,Capacity!$A:$A,Summary_CDP,Capacity!$B:$B,IF($B$30="NEM","*",$B$30),Capacity!$C:$C,$H42) -> 15481.949 | AE42: =SUMIFS(Capacity!AA:AA,Capacity!$A:$A,Summary_CDP,Capacity!$B:$B,IF($B$30="NEM","*",$B$30),Capacity!$C:$C,$H42) -> 15387.778 | AF42: =SUMIFS(Capacity!AB:AB,Capacity!$A:$A,Summary_CDP,Capacity!$B:$B,IF($B$30="NEM","*",$B$30),Capacity!$C:$C,$H42) -> 15277.058 | AG42: =SUMIFS(Capacity!AC:AC,Capacity!$A:$A,Summary_CDP,Capacity!$B:$B,IF($B$30="NEM","*",$B$30),Capacity!$C:$C,$H42) -> 15144.979 | AH42: =SUMIFS(Capacity!AD:AD,Capacity!$A:$A,Summary_CDP,Capacity!$B:$B,IF($B$30="NEM","*",$B$30),Capacity!$C:$C,$H42) -> 15000.321 | AI42: =SUMIFS(Capacity!AE:AE,Capacity!$A:$A,Summary_CDP,Capacity!$B:$B,IF($B$30="NEM","*",$B$30),Capacity!$C:$C,$H42) -> 14832.36 | AJ42: =SUMIFS(Capacity!AF:AF,Capacity!$A:$A,Summary_CDP,Capacity!$B:$B,IF($B$30="NEM","*",$B$30),Capacity!$C:$C,$H42) -> 14832.36
H43: Solar Thermal | I43: =SUMIFS(Capacity!E:E,Capacity!$A:$A,Summary_CDP,Capacity!$B:$B,IF($B$30="NEM","*",$B$30),Capacity!$C:$C,$H43) -> 0 | J43: =SUMIFS(Capacity!F:F,Capacity!$A:$A,Summary_CDP,Capacity!$B:$B,IF($B$30="NEM","*",$B$30),Capacity!$C:$C,$H43) -> 0 | K43: =SUMIFS(Capacity!G:G,Capacity!$A:$A,Summary_CDP,Capacity!$B:$B,IF($B$30="NEM","*",$B$30),Capacity!$C:$C,$H43) -> 0 | L43: =SUMIFS(Capacity!H:H,Capacity!$A:$A,Summary_CDP,Capacity!$B:$B,IF($B$30="NEM","*",$B$30),Capacity!$C:$C,$H43) -> 0 | M43: =SUMIFS(Capacity!I:I,Capacity!$A:$A,Summary_CDP,Capacity!$B:$B,IF($B$30="NEM","*",$B$30),Capacity!$C:$C,$H43) -> 0 | N43: =SUMIFS(Capacity!J:J,Capacity!$A:$A,Summary_CDP,Capacity!$B:$B,IF($B$30="NEM","*",$B$30),Capacity!$C:$C,$H43) -> 0 | O43: =SUMIFS(Capacity!K:K,Capacity!$A:$A,Summary_CDP,Capacity!$B:$B,IF($B$30="NEM","*",$B$30),Capacity!$C:$C,$H43) -> 0 | P43: =SUMIFS(Capacity!L:L,Capacity!$A:$A,Summary_CDP,Capacity!$B:$B,IF($B$30="NEM","*",$B$30),Capacity!$C:$C,$H43) -> 0 | Q43: =SUMIFS(Capacity!M:M,Capacity!$A:$A,Summary_CDP,Capacity!$B:$B,IF($B$30="NEM","*",$B$30),Capacity!$C:$C,$H43) -> 0 | R43: =SUMIFS(Capacity!N:N,Capacity!$A:$A,Summary_CDP,Capacity!$B:$B,IF($B$30="NEM","*",$B$30),Capacity!$C:$C,$H43) -> 0 | S43: =SUMIFS(Capacity!O:O,Capacity!$A:$A,Summary_CDP,Capacity!$B:$B,IF($B$30="NEM","*",$B$30),Capacity!$C:$C,$H43) -> 0 | T43: =SUMIFS(Capacity!P:P,Capacity!$A:$A,Summary_CDP,Capacity!$B:$B,IF($B$30="NEM","*",$B$30),Capacity!$C:$C,$H43) -> 0 | U43: =SUMIFS(Capacity!Q:Q,Capacity!$A:$A,Summary_CDP,Capacity!$B:$B,IF($B$30="NEM","*",$B$30),Capacity!$C:$C,$H43) -> 0 | V43: =SUMIFS(Capacity!R:R,Capacity!$A:$A,Summary_CDP,Capacity!$B:$B,IF($B$30="NEM","*",$B$30),Capacity!$C:$C,$H43) -> 0 | W43: =SUMIFS(Capacity!S:S,Capacity!$A:$A,Summary_CDP,Capacity!$B:$B,IF($B$30="NEM","*",$B$30),Capacity!$C:$C,$H43) -> 0 | X43: =SUMIFS(Capacity!T:T,Capacity!$A:$A,Summary_CDP,Capacity!$B:$B,IF($B$30="NEM","*",$B$30),Capacity!$C:$C,$H43) -> 0 | Y43: =SUMIFS(Capacity!U:U,Capacity!$A:$A,Summary_CDP,Capacity!$B:$B,IF($B$30="NEM","*",$B$30),Capacity!$C:$C,$H43) -> 0 | Z43: =SUMIFS(Capacity!V:V,Capacity!$A:$A,Summary_CDP,Capacity!$B:$B,IF($B$30="NEM","*",$B$30),Capacity!$C:$C,$H43) -> 0 | AA43: =SUMIFS(Capacity!W:W,Capacity!$A:$A,Summary_CDP,Capacity!$B:$B,IF($B$30="NEM","*",$B$30),Capacity!$C:$C,$H43) -> 0 | AB43: =SUMIFS(Capacity!X:X,Capacity!$A:$A,Summary_CDP,Capacity!$B:$B,IF($B$30="NEM","*",$B$30),Capacity!$C:$C,$H43) -> 0 | AC43: =SUMIFS(Capacity!Y:Y,Capacity!$A:$A,Summary_CDP,Capacity!$B:$B,IF($B$30="NEM","*",$B$30),Capacity!$C:$C,$H43) -> 0 | AD43: =SUMIFS(Capacity!Z:Z,Capacity!$A:$A,Summary_CDP,Capacity!$B:$B,IF($B$30="NEM","*",$B$30),Capacity!$C:$C,$H43) -> 0 | AE43: =SUMIFS(Capacity!AA:AA,Capacity!$A:$A,Summary_CDP,Capacity!$B:$B,IF($B$30="NEM","*",$B$30),Capacity!$C:$C,$H43) -> 0 | AF43: =SUMIFS(Capacity!AB:AB,Capacity!$A:$A,Summary_CDP,Capacity!$B:$B,IF($B$30="NEM","*",$B$30),Capacity!$C:$C,$H43) -> 0 | AG43: =SUMIFS(Capacity!AC:AC,Capacity!$A:$A,Summary_CDP,Capacity!$B:$B,IF($B$30="NEM","*",$B$30),Capacity!$C:$C,$H43) -> 0 | AH43: =SUMIFS(Capacity!AD:AD,Capacity!$A:$A,Summary_CDP,Capacity!$B:$B,IF($B$30="NEM","*",$B$30),Capacity!$C:$C,$H43) -> 0 | AI43: =SUMIFS(Capacity!AE:AE,Capacity!$A:$A,Summary_CDP,Capacity!$B:$B,IF($B$30="NEM","*",$B$30),Capacity!$C:$C,$H43) -> 0 | AJ43: =SUMIFS(Capacity!AF:AF,Capacity!$A:$A,Summary_CDP,Capacity!$B:$B,IF($B$30="NEM","*",$B$30),Capacity!$C:$C,$H43) -> 0
H44: Offshore Wind | I44: =SUMIFS(Capacity!E:E,Capacity!$A:$A,Summary_CDP,Capacity!$B:$B,IF($B$30="NEM","*",$B$30),Capacity!$C:$C,$H44) -> 0 | J44: =SUMIFS(Capacity!F:F,Capacity!$A:$A,Summary_CDP,Capacity!$B:$B,IF($B$30="NEM","*",$B$30),Capacity!$C:$C,$H44) -> 0 | K44: =SUMIFS(Capacity!G:G,Capacity!$A:$A,Summary_CDP,Capacity!$B:$B,IF($B$30="NEM","*",$B$30),Capacity!$C:$C,$H44) -> 0 | L44: =SUMIFS(Capacity!H:H,Capacity!$A:$A,Summary_CDP,Capacity!$B:$B,IF($B$30="NEM","*",$B$30),Capacity!$C:$C,$H44) -> 0 | M44: =SUMIFS(Capacity!I:I,Capacity!$A:$A,Summary_CDP,Capacity!$B:$B,IF($B$30="NEM","*",$B$30),Capacity!$C:$C,$H44) -> 0 | N44: =SUMIFS(Capacity!J:J,Capacity!$A:$A,Summary_CDP,Capacity!$B:$B,IF($B$30="NEM","*",$B$30),Capacity!$C:$C,$H44) -> 0 | O44: =SUMIFS(Capacity!K:K,Capacity!$A:$A,Summary_CDP,Capacity!$B:$B,IF($B$30="NEM","*",$B$30),Capacity!$C:$C,$H44) -> 0 | P44: =SUMIFS(Capacity!L:L,Capacity!$A:$A,Summary_CDP,Capacity!$B:$B,IF($B$30="NEM","*",$B$30),Capacity!$C:$C,$H44) -> 0 | Q44: =SUMIFS(Capacity!M:M,Capacity!$A:$A,Summary_CDP,Capacity!$B:$B,IF($B$30="NEM","*",$B$30),Capacity!$C:$C,$H44) -> 0 | R44: =SUMIFS(Capacity!N:N,Capacity!$A:$A,Summary_CDP,Capacity!$B:$B,IF($B$30="NEM","*",$B$30),Capacity!$C:$C,$H44) -> 0 | S44: =SUMIFS(Capacity!O:O,Capacity!$A:$A,Summary_CDP,Capacity!$B:$B,IF($B$30="NEM","*",$B$30),Capacity!$C:$C,$H44) -> 0 | T44: =SUMIFS(Capacity!P:P,Capacity!$A:$A,Summary_CDP,Capacity!$B:$B,IF($B$30="NEM","*",$B$30),Capacity!$C:$C,$H44) -> 0 | U44: =SUMIFS(Capacity!Q:Q,Capacity!$A:$A,Summary_CDP,Capacity!$B:$B,IF($B$30="NEM","*",$B$30),Capacity!$C:$C,$H44) -> 0 | V44: =SUMIFS(Capacity!R:R,Capacity!$A:$A,Summary_CDP,Capacity!$B:$B,IF($B$30="NEM","*",$B$30),Capacity!$C:$C,$H44) -> 0 | W44: =SUMIFS(Capacity!S:S,Capacity!$A:$A,Summary_CDP,Capacity!$B:$B,IF($B$30="NEM","*",$B$30),Capacity!$C:$C,$H44) -> 0 | X44: =SUMIFS(Capacity!T:T,Capacity!$A:$A,Summary_CDP,Capacity!$B:$B,IF($B$30="NEM","*",$B$30),Capacity!$C:$C,$H44) -> 0 | Y44: =SUMIFS(Capacity!U:U,Capacity!$A:$A,Summary_CDP,Capacity!$B:$B,IF($B$30="NEM","*",$B$30),Capacity!$C:$C,$H44) -> 0 | Z44: =SUMIFS(Capacity!V:V,Capacity!$A:$A,Summary_CDP,Capacity!$B:$B,IF($B$30="NEM","*",$B$30),Capacity!$C:$C,$H44) -> 0 | AA44: =SUMIFS(Capacity!W:W,Capacity!$A:$A,Summary_CDP,Capacity!$B:$B,IF($B$30="NEM","*",$B$30),Capacity!$C:$C,$H44) -> 0 | AB44: =SUMIFS(Capacity!X:X,Capacity!$A:$A,Summary_CDP,Capacity!$B:$B,IF($B$30="NEM","*",$B$30),Capacity!$C:$C,$H44) -> 0 | AC44: =SUMIFS(Capacity!Y:Y,Capacity!$A:$A,Summary_CDP,Capacity!$B:$B,IF($B$30="NEM","*",$B$30),Capacity!$C:$C,$H44) -> 0 | AD44: =SUMIFS(Capacity!Z:Z,Capacity!$A:$A,Summary_CDP,Capacity!$B:$B,IF($B$30="NEM","*",$B$30),Capacity!$C:$C,$H44) -> 0 | AE44: =SUMIFS(Capacity!AA:AA,Capacity!$A:$A,Summary_CDP,Capacity!$B:$B,IF($B$30="NEM","*",$B$30),Capacity!$C:$C,$H44) -> 0 | AF44: =SUMIFS(Capacity!AB:AB,Capacity!$A:$A,Summary_CDP,Capacity!$B:$B,IF($B$30="NEM","*",$B$30),Capacity!$C:$C,$H44) -> 0 | AG44: =SUMIFS(Capacity!AC:AC,Capacity!$A:$A,Summary_CDP,Capacity!$B:$B,IF($B$30="NEM","*",$B$30),Capacity!$C:$C,$H44) -> 0 | AH44: =SUMIFS(Capacity!AD:AD,Capacity!$A:$A,Summary_CDP,Capacity!$B:$B,IF($B$30="NEM","*",$B$30),Capacity!$C:$C,$H44) -> 0 | AI44: =SUMIFS(Capacity!AE:AE,Capacity!$A:$A,Summary_CDP,Capacity!$B:$B,IF($B$30="NEM","*",$B$30),Capacity!$C:$C,$H44) -> 0 | AJ44: =SUMIFS(Capacity!AF:AF,Capacity!$A:$A,Summary_CDP,Capacity!$B:$B,IF($B$30="NEM","*",$B$30),Capacity!$C:$C,$H44) -> 0
... H47: Distributed PV | I47: =SUMIFS(Capacity!E:E,Capacity!$A:$A,Summary_CDP,Capacity!$B:$B,IF($B$30="NEM","*",$B$30),Capacity!$C:$C,$H47) -> 22580.879 | J47: =SUMIFS(Capacity!F:F,Capacity!$A:$A,Summary_CDP,Capacity!$B:$B,IF($B$30="NEM","*",$B$30),Capacity!$C:$C,$H47) -> 25525.236 | K47: =SUMIFS(Capacity!G:G,Capacity!$A:$A,Summary_CDP,Capacity!$B:$B,IF($B$30="NEM","*",$B$30),Capacity!$C:$C,$H47) -> 28511.228 | L47: =SUMIFS(Capacity!H:H,Capacity!$A:$A,Summary_CDP,Capacity!$B:$B,IF($B$30="NEM","*",$B$30),Capacity!$C:$C,$H47) -> 31371.068 | M47: =SUMIFS(Capacity!I:I,Capacity!$A:$A,Summary_CDP,Capacity!$B:$B,IF($B$30="NEM","*",$B$30),Capacity!$C:$C,$H47) -> 34250.879 | N47: =SUMIFS(Capacity!J:J,Capacity!$A:$A,Summary_CDP,Capacity!$B:$B,IF($B$30="NEM","*",$B$30),Capacity!$C:$C,$H47) -> 36995.19 | O47: =SUMIFS(Capacity!K:K,Capacity!$A:$A,Summary_CDP,Capacity!$B:$B,IF($B$30="NEM","*",$B$30),Capacity!$C:$C,$H47) -> 39671.427 | P47: =SUMIFS(Capacity!L:L,Capacity!$A:$A,Summary_CDP,Capacity!$B:$B,IF($B$30="NEM","*",$B$30),Capacity!$C:$C,$H47) -> 42224.097 | Q47: =SUMIFS(Capacity!M:M,Capacity!$A:$A,Summary_CDP,Capacity!$B:$B,IF($B$30="NEM","*",$B$30),Capacity!$C:$C,$H47) -> 44602.898 | R47: =SUMIFS(Capacity!N:N,Capacity!$A:$A,Summary_CDP,Capacity!$B:$B,IF($B$30="NEM","*",$B$30),Capacity!$C:$C,$H47) -> 46967.917 | S47: =SUMIFS(Capacity!O:O,Capacity!$A:$A,Summary_CDP,Capacity!$B:$B,IF($B$30="NEM","*",$B$30),Capacity!$C:$C,$H47) -> 49314.53 | T47: =SUMIFS(Capacity!P:P,Capacity!$A:$A,Summary_CDP,Capacity!$B:$B,IF($B$30="NEM","*",$B$30),Capacity!$C:$C,$H47) -> 51629.562 | U47: =SUMIFS(Capacity!Q:Q,Capacity!$A:$A,Summary_CDP,Capacity!$B:$B,IF($B$30="NEM","*",$B$30),Capacity!$C:$C,$H47) -> 53792.153 | V47: =SUMIFS(Capacity!R:R,Capacity!$A:$A,Summary_CDP,Capacity!$B:$B,IF($B$30="NEM","*",$B$30),Capacity!$C:$C,$H47) -> 55825.533 | W47: =SUMIFS(Capacity!S:S,Capacity!$A:$A,Summary_CDP,Capacity!$B:$B,IF($B$30="NEM","*",$B$30),Capacity!$C:$C,$H47) -> 57761.441 | X47: =SUMIFS(Capacity!T:T,Capacity!$A:$A,Summary_CDP,Capacity!$B:$B,IF($B$30="NEM","*",$B$30),Capacity!$C:$C,$H47) -> 59706.34 | Y47: =SUMIFS(Capacity!U:U,Capacity!$A:$A,Summary_CDP,Capacity!$B:$B,IF($B$30="NEM","*",$B$30),Capacity!$C:$C,$H47) -> 61699.201 | Z47: =SUMIFS(Capacity!V:V,Capacity!$A:$A,Summary_CDP,Capacity!$B:$B,IF($B$30="NEM","*",$B$30),Capacity!$C:$C,$H47) -> 63698.761 | AA47: =SUMIFS(Capacity!W:W,Capacity!$A:$A,Summary_CDP,Capacity!$B:$B,IF($B$30="NEM","*",$B$30),Capacity!$C:$C,$H47) -> 65697.667 | AB47: =SUMIFS(Capacity!X:X,Capacity!$A:$A,Summary_CDP,Capacity!$B:$B,IF($B$30="NEM","*",$B$30),Capacity!$C:$C,$H47) -> 67668.603 | AC47: =SUMIFS(Capacity!Y:Y,Capacity!$A:$A,Summary_CDP,Capacity!$B:$B,IF($B$30="NEM","*",$B$30),Capacity!$C:$C,$H47) -> 69644.036 | AD47: =SUMIFS(Capacity!Z:Z,Capacity!$A:$A,Summary_CDP,Capacity!$B:$B,IF($B$30="NEM","*",$B$30),Capacity!$C:$C,$H47) -> 71609.243 | AE47: =SUMIFS(Capacity!AA:AA,Capacity!$A:$A,Summary_CDP,Capacity!$B:$B,IF($B$30="NEM","*",$B$30),Capacity!$C:$C,$H47) -> 73546.328 | AF47: =SUMIFS(Capacity!AB:AB,Capacity!$A:$A,Summary_CDP,Capacity!$B:$B,IF($B$30="NEM","*",$B$30),Capacity!$C:$C,$H47) -> 75464.245 | AG47: =SUMIFS(Capacity!AC:AC,Capacity!$A:$A,Summary_CDP,Capacity!$B:$B,IF($B$30="NEM","*",$B$30),Capacity!$C:$C,$H47) -> 77368.609 | AH47: =SUMIFS(Capacity!AD:AD,Capacity!$A:$A,Summary_CDP,Capacity!$B:$B,IF($B$30="NEM","*",$B$30),Capacity!$C:$C,$H47) -> 79270.833 | AI47: =SUMIFS(Capacity!AE:AE,Capacity!$A:$A,Summary_CDP,Capacity!$B:$B,IF($B$30="NEM","*",$B$30),Capacity!$C:$C,$H47) -> 81161.108 | AJ47: =SUMIFS(Capacity!AF:AF,Capacity!$A:$A,Summary_CDP,Capacity!$B:$B,IF($B$30="NEM","*",$B$30),Capacity!$C:$C,$H47) -> 81161.108
H48: Dispatchable Capacity | I48: =SUM(I33:I41,I50) -> 43277.559 | J48: =SUM(J33:J41,J50) -> 43739.021 | K48: =SUM(K33:K41,K50) -> 37282.985 | L48: =SUM(L33:L41,L50) -> 37680.413 | M48: =SUM(M33:M41,M50) -> 36873.571 | N48: =SUM(N33:N41,N50) -> 38601.286 | O48: =SUM(O33:O41,O50) -> 39608.132 | P48: =SUM(P33:P41,P50) -> 39495.443 | ... AJ48: =SUM(AJ33:AJ41,AJ50) -> 139322.2
H50: DSP | I50: =SUMIFS(Capacity!E:E,Capacity!$A:$A,Summary_CDP,Capacity!$B:$B,IF($B$30="NEM","*",$B$30),Capacity!$C:$C,$H50) -> 878.11259 | J50: =SUMIFS(Capacity!F:F,Capacity!$A:$A,Summary_CDP,Capacity!$B:$B,IF($B$30="NEM","*",$B$30),Capacity!$C:$C,$H50) -> 975.67471 | K50: =SUMIFS(Capacity!G:G,Capacity!$A:$A,Summary_CDP,Capacity!$B:$B,IF($B$30="NEM","*",$B$30),Capacity!$C:$C,$H50) -> 1211.3723 | L50: =SUMIFS(Capacity!H:H,Capacity!$A:$A,Summary_CDP,Capacity!$B:$B,IF($B$30="NEM","*",$B$30),Capacity!$C:$C,$H50) -> 1514.1344 | M50: =SUMIFS(Capacity!I:I,Capacity!$A:$A,Summary_CDP,Capacity!$B:$B,IF($B$30="NEM","*",$B$30),Capacity!$C:$C,$H50) -> 1721.593 | N50: =SUMIFS(Capacity!J:J,Capacity!$A:$A,Summary_CDP,Capacity!$B:$B,IF($B$30="NEM","*",$B$30),Capacity!$C:$C,$H50) -> 1953.1323 | O50: =SUMIFS(Capacity!K:K,Capacity!$A:$A,Summary_CDP,Capacity!$B:$B,IF($B$30="NEM","*",$B$30),Capacity!$C:$C,$H50) -> 2123.8801 | P50: =SUMIFS(Capacity!L:L,Capacity!$A:$A,Summary_CDP,Capacity!$B:$B,IF($B$30="NEM","*",$B$30),Capacity!$C:$C,$H50) -> 2239.881 | Q50: =SUMIFS(Capacity!M:M,Capacity!$A:$A,Summary_CDP,Capacity!$B:$B,IF($B$30="NEM","*",$B$30),Capacity!$C:$C,$H50) -> 2370.9514 | R50: =SUMIFS(Capacity!N:N,Capacity!$A:$A,Summary_CDP,Capacity!$B:$B,IF($B$30="NEM","*",$B$30),Capacity!$C:$C,$H50) -> 2493.5342 | S50: =SUMIFS(Capacity!O:O,Capacity!$A:$A,Summary_CDP,Capacity!$B:$B,IF($B$30="NEM","*",$B$30),Capacity!$C:$C,$H50) -> 2622.6242 | T50: =SUMIFS(Capacity!P:P,Capacity!$A:$A,Summary_CDP,Capacity!$B:$B,IF($B$30="NEM","*",$B$30),Capacity!$C:$C,$H50) -> 2759.2277 | U50: =SUMIFS(Capacity!Q:Q,Capacity!$A:$A,Summary_CDP,Capacity!$B:$B,IF($B$30="NEM","*",$B$30),Capacity!$C:$C,$H50) -> 2896.6808 | V50: =SUMIFS(Capacity!R:R,Capacity!$A:$A,Summary_CDP,Capacity!$B:$B,IF($B$30="NEM","*",$B$30),Capacity!$C:$C,$H50) -> 3014.9736 | W50: =SUMIFS(Capacity!S:S,Capacity!$A:$A,Summary_CDP,Capacity!$B:$B,IF($B$30="NEM","*",$B$30),Capacity!$C:$C,$H50) -> 3172.5557 | X50: =SUMIFS(Capacity!T:T,Capacity!$A:$A,Summary_CDP,Capacity!$B:$B,IF($B$30="NEM","*",$B$30),Capacity!$C:$C,$H50) -> 3313.3502 | Y50: =SUMIFS(Capacity!U:U,Capacity!$A:$A,Summary_CDP,Capacity!$B:$B,IF($B$30="NEM","*",$B$30),Capacity!$C:$C,$H50) -> 3471.5477 | Z50: =SUMIFS(Capacity!V:V,Capacity!$A:$A,Summary_CDP,Capacity!$B:$B,IF($B$30="NEM","*",$B$30),Capacity!$C:$C,$H50) -> 3610.8012 | AA50: =SUMIFS(Capacity!W:W,Capacity!$A:$A,Summary_CDP,Capacity!$B:$B,IF($B$30="NEM","*",$B$30),Capacity!$C:$C,$H50) -> 3736.325 | AB50: =SUMIFS(Capacity!X:X,Capacity!$A:$A,Summary_CDP,Capacity!$B:$B,IF($B$30="NEM","*",$B$30),Capacity!$C:$C,$H50) -> 3868.0521 | AC50: =SUMIFS(Capacity!Y:Y,Capacity!$A:$A,Summary_CDP,Capacity!$B:$B,IF($B$30="NEM","*",$B$30),Capacity!$C:$C,$H50) -> 4025.7774 | AD50: =SUMIFS(Capacity!Z:Z,Capacity!$A:$A,Summary_CDP,Capacity!$B:$B,IF($B$30="NEM","*",$B$30),Capacity!$C:$C,$H50) -> 4150.9648 | AE50: =SUMIFS(Capacity!AA:AA,Capacity!$A:$A,Summary_CDP,Capacity!$B:$B,IF($B$30="NEM","*",$B$30),Capacity!$C:$C,$H50) -> 4289.7799 | AF50: =SUMIFS(Capacity!AB:AB,Capacity!$A:$A,Summary_CDP,Capacity!$B:$B,IF($B$30="NEM","*",$B$30),Capacity!$C:$C,$H50) -> 4451.5987 | AG50: =SUMIFS(Capacity!AC:AC,Capacity!$A:$A,Summary_CDP,Capacity!$B:$B,IF($B$30="NEM","*",$B$30),Capacity!$C:$C,$H50) -> 4615.6782 | AH50: =SUMIFS(Capacity!AD:AD,Capacity!$A:$A,Summary_CDP,Capacity!$B:$B,IF($B$30="NEM","*",$B$30),Capacity!$C:$C,$H50) -> 4735.5743 | AI50: =SUMIFS(Capacity!AE:AE,Capacity!$A:$A,Summary_CDP,Capacity!$B:$B,IF($B$30="NEM","*",$B$30),Capacity!$C:$C,$H50) -> 4897.7347 | AJ50: =SUMIFS(Capacity!AF:AF,Capacity!$A:$A,Summary_CDP,Capacity!$B:$B,IF($B$30="NEM","*",$B$30),Capacity!$C:$C,$H50) -> 4897.7347
A53: =B54&" generation by year" -> NEM generation by year
A54: Select region | B54: NEM
H56: As-generated generation (GWh) | I56: 2023-24 | J56: 2024-25 | K56: 2025-26 | L56: 2026-27 | M56: 2027-28 | N56: 2028-29 | O56: 2029-30 | P56: 2030-31 | Q56: 2031-32 | R56: 2032-33 | S56: 2033-34 | T56: 2034-35 | U56: 2035-36 | V56: 2036-37 | W56: 2037-38 | X56: 2038-39 | Y56: 2039-40 | Z56: 2040-41 | AA56: 2041-42 | AB56: 2042-43 | AC56: 2043-44 | AD56: 2044-45 | AE56: 2045-46 | AF56: 2046-47 | AG56: 2047-48 | AH56: 2048-49 | AI56: 2049-50 | AJ56: 2050-51
H57: Black Coal | I57: =SUMIFS(Generation!D:D,Generation!$A:$A,Summary_CDP,Generation!$B:$B,IF($B$54="NEM","*",$B$54),Generation!$C:$C,$H57) -> 77553.079 | J57: =SUMIFS(Generation!E:E,Generation!$A:$A,Summary_CDP,Generation!$B:$B,IF($B$54="NEM","*",$B$54),Generation!$C:$C,$H57) -> 67729.144 | K57: =SUMIFS(Generation!F:F,Generation!$A:$A,Summary_CDP,Generation!$B:$B,IF($B$54="NEM","*",$B$54),Generation!$C:$C,$H57) -> 47172.607 | L57: =SUMIFS(Generation!G:G,Generation!$A:$A,Summary_CDP,Generation!$B:$B,IF($B$54="NEM","*",$B$54),Generation!$C:$C,$H57) -> 37477.529 | M57: =SUMIFS(Generation!H:H,Generation!$A:$A,Summary_CDP,Generation!$B:$B,IF($B$54="NEM","*",$B$54),Generation!$C:$C,$H57) -> 20728.433 | N57: =SUMIFS(Generation!I:I,Generation!$A:$A,Summary_CDP,Generation!$B:$B,IF($B$54="NEM","*",$B$54),Generation!$C:$C,$H57) -> 16671.683 | O57: =SUMIFS(Generation!J:J,Generation!$A:$A,Summary_CDP,Generation!$B:$B,IF($B$54="NEM","*",$B$54),Generation!$C:$C,$H57) -> 11571.077 | P57: =SUMIFS(Generation!K:K,Generation!$A:$A,Summary_CDP,Generation!$B:$B,IF($B$54="NEM","*",$B$54),Generation!$C:$C,$H57) -> 0 | Q57: =SUMIFS(Generation!L:L,Generation!$A:$A,Summary_CDP,Generation!$B:$B,IF($B$54="NEM","*",$B$54),Generation!$C:$C,$H57) -> 0 | R57: =SUMIFS(Generation!M:M,Generation!$A:$A,Summary_CDP,Generation!$B:$B,IF($B$54="NEM","*",$B$54),Generation!$C:$C,$H57) -> 0 | S57: =SUMIFS(Generation!N:N,Generation!$A:$A,Summary_CDP,Generation!$B:$B,IF($B$54="NEM","*",$B$54),Generation!$C:$C,$H57) -> 0 | T57: =SUMIFS(Generation!O:O,Generation!$A:$A,Summary_CDP,Generation!$B:$B,IF($B$54="NEM","*",$B$54),Generation!$C:$C,$H57) -> 0 | U57: =SUMIFS(Generation!P:P,Generation!$A:$A,Summary_CDP,Generation!$B:$B,IF($B$54="NEM","*",$B$54),Generation!$C:$C,$H57) -> 0 | V57: =SUMIFS(Generation!Q:Q,Generation!$A:$A,Summary_CDP,Generation!$B:$B,IF($B$54="NEM","*",$B$54),Generation!$C:$C,$H57) -> 0 | W57: =SUMIFS(Generation!R:R,Generation!$A:$A,Summary_CDP,Generation!$B:$B,IF($B$54="NEM","*",$B$54),Generation!$C:$C,$H57) -> 0 | X57: =SUMIFS(Generation!S:S,Generation!$A:$A,Summary_CDP,Generation!$B:$B,IF($B$54="NEM","*",$B$54),Generation!$C:$C,$H57) -> 0 | Y57: =SUMIFS(Generation!T:T,Generation!$A:$A,Summary_CDP,Generation!$B:$B,IF($B$54="NEM","*",$B$54),Generation!$C:$C,$H57) -> 0 | Z57: =SUMIFS(Generation!U:U,Generation!$A:$A,Summary_CDP,Generation!$B:$B,IF($B$54="NEM","*",$B$54),Generation!$C:$C,$H57) -> 0 | AA57: =SUMIFS(Generation!V:V,Generation!$A:$A,Summary_CDP,Generation!$B:$B,IF($B$54="NEM","*",$B$54),Generation!$C:$C,$H57) -> 0 | AB57: =SUMIFS(Generation!W:W,Generation!$A:$A,Summary_CDP,Generation!$B:$B,IF($B$54="NEM","*",$B$54),Generation!$C:$C,$H57) -> 0 | AC57: =SUMIFS(Generation!X:X,Generation!$A:$A,Summary_CDP,Generation!$B:$B,IF($B$54="NEM","*",$B$54),Generation!$C:$C,$H57) -> 0 | AD57: =SUMIFS(Generation!Y:Y,Generation!$A:$A,Summary_CDP,Generation!$B:$B,IF($B$54="NEM","*",$B$54),Generation!$C:$C,$H57) -> 0 | AE57: =SUMIFS(Generation!Z:Z,Generation!$A:$A,Summary_CDP,Generation!$B:$B,IF($B$54="NEM","*",$B$54),Generation!$C:$C,$H57) -> 0 | AF57: =SUMIFS(Generation!AA:AA,Generation!$A:$A,Summary_CDP,Generation!$B:$B,IF($B$54="NEM","*",$B$54),Generation!$C:$C,$H57) -> 0 | AG57: =SUMIFS(Generation!AB:AB,Generation!$A:$A,Summary_CDP,Generation!$B:$B,IF($B$54="NEM","*",$B$54),Generation!$C:$C,$H57) -> 0 | AH57: =SUMIFS(Generation!AC:AC,Generation!$A:$A,Summary_CDP,Generation!$B:$B,IF($B$54="NEM","*",$B$54),Generation!$C:$C,$H57) -> 0 | AI57: =SUMIFS(Generation!AD:AD,Generation!$A:$A,Summary_CDP,Generation!$B:$B,IF($B$54="NEM","*",$B$54),Generation!$C:$C,$H57) -> 0 | AJ57: =SUMIFS(Generation!AE:AE,Generation!$A:$A,Summary_CDP,Generation!$B:$B,IF($B$54="NEM","*",$B$54),Generation!$C:$C,$H57) -> 0
H58: Brown Coal | I58: =SUMIFS(Generation!D:D,Generation!$A:$A,Summary_CDP,Generation!$B:$B,IF($B$54="NEM","*",$B$54),Generation!$C:$C,$H58) -> 31199.076 | J58: =SUMIFS(Generation!E:E,Generation!$A:$A,Summary_CDP,Generation!$B:$B,IF($B$54="NEM","*",$B$54),Generation!$C:$C,$H58) -> 26710.757 | K58: =SUMIFS(Generation!F:F,Generation!$A:$A,Summary_CDP,Generation!$B:$B,IF($B$54="NEM","*",$B$54),Generation!$C:$C,$H58) -> 19228.597 | L58: =SUMIFS(Generation!G:G,Generation!$A:$A,Summary_CDP,Generation!$B:$B,IF($B$54="NEM","*",$B$54),Generation!$C:$C,$H58) -> 16321.513 | M58: =SUMIFS(Generation!H:H,Generation!$A:$A,Summary_CDP,Generation!$B:$B,IF($B$54="NEM","*",$B$54),Generation!$C:$C,$H58) -> 10440.935 | N58: =SUMIFS(Generation!I:I,Generation!$A:$A,Summary_CDP,Generation!$B:$B,IF($B$54="NEM","*",$B$54),Generation!$C:$C,$H58) -> 6937.0605 | O58: =SUMIFS(Generation!J:J,Generation!$A:$A,Summary_CDP,Generation!$B:$B,IF($B$54="NEM","*",$B$54),Generation!$C:$C,$H58) -> 6292.0501 | P58: =SUMIFS(Generation!K:K,Generation!$A:$A,Summary_CDP,Generation!$B:$B,IF($B$54="NEM","*",$B$54),Generation!$C:$C,$H58) -> 0 | Q58: =SUMIFS(Generation!L:L,Generation!$A:$A,Summary_CDP,Generation!$B:$B,IF($B$54="NEM","*",$B$54),Generation!$C:$C,$H58) -> 0 | R58: =SUMIFS(Generation!M:M,Generation!$A:$A,Summary_CDP,Generation!$B:$B,IF($B$54="NEM","*",$B$54),Generation!$C:$C,$H58) -> 0 | S58: =SUMIFS(Generation!N:N,Generation!$A:$A,Summary_CDP,Generation!$B:$B,IF($B$54="NEM","*",$B$54),Generation!$C:$C,$H58) -> 0 | T58: =SUMIFS(Generation!O:O,Generation!$A:$A,Summary_CDP,Generation!$B:$B,IF($B$54="NEM","*",$B$54),Generation!$C:$C,$H58) -> 0 | U58: =SUMIFS(Generation!P:P,Generation!$A:$A,Summary_CDP,Generation!$B:$B,IF($B$54="NEM","*",$B$54),Generation!$C:$C,$H58) -> 0 | V58: =SUMIFS(Generation!Q:Q,Generation!$A:$A,Summary_CDP,Generation!$B:$B,IF($B$54="NEM","*",$B$54),Generation!$C:$C,$H58) -> 0 | W58: =SUMIFS(Generation!R:R,Generation!$A:$A,Summary_CDP,Generation!$B:$B,IF($B$54="NEM","*",$B$54),Generation!$C:$C,$H58) -> 0 | X58: =SUMIFS(Generation!S:S,Generation!$A:$A,Summary_CDP,Generation!$B:$B,IF($B$54="NEM","*",$B$54),Generation!$C:$C,$H58) -> 0 | Y58: =SUMIFS(Generation!T:T,Generation!$A:$A,Summary_CDP,Generation!$B:$B,IF($B$54="NEM","*",$B$54),Generation!$C:$C,$H58) -> 0 | Z58: =SUMIFS(Generation!U:U,Generation!$A:$A,Summary_CDP,Generation!$B:$B,IF($B$54="NEM","*",$B$54),Generation!$C:$C,$H58) -> 0 | AA58: =SUMIFS(Generation!V:V,Generation!$A:$A,Summary_CDP,Generation!$B:$B,IF($B$54="NEM","*",$B$54),Generation!$C:$C,$H58) -> 0 | AB58: =SUMIFS(Generation!W:W,Generation!$A:$A,Summary_CDP,Generation!$B:$B,IF($B$54="NEM","*",$B$54),Generation!$C:$C,$H58) -> 0 | AC58: =SUMIFS(Generation!X:X,Generation!$A:$A,Summary_CDP,Generation!$B:$B,IF($B$54="NEM","*",$B$54),Generation!$C:$C,$H58) -> 0 | AD58: =SUMIFS(Generation!Y:Y,Generation!$A:$A,Summary_CDP,Generation!$B:$B,IF($B$54="NEM","*",$B$54),Generation!$C:$C,$H58) -> 0 | AE58: =SUMIFS(Generation!Z:Z,Generation!$A:$A,Summary_CDP,Generation!$B:$B,IF($B$54="NEM","*",$B$54),Generation!$C:$C,$H58) -> 0 | AF58: =SUMIFS(Generation!AA:AA,Generation!$A:$A,Summary_CDP,Generation!$B:$B,IF($B$54="NEM","*",$B$54),Generation!$C:$C,$H58) -> 0 | AG58: =SUMIFS(Generation!AB:AB,Generation!$A:$A,Summary_CDP,Generation!$B:$B,IF($B$54="NEM","*",$B$54),Generation!$C:$C,$H58) -> 0 | AH58: =SUMIFS(Generation!AC:AC,Generation!$A:$A,Summary_CDP,Generation!$B:$B,IF($B$54="NEM","*",$B$54),Generation!$C:$C,$H58) -> 0 | AI58: =SUMIFS(Generation!AD:AD,Generation!$A:$A,Summary_CDP,Generation!$B:$B,IF($B$54="NEM","*",$B$54),Generation!$C:$C,$H58) -> 0 | AJ58: =SUMIFS(Generation!AE:AE,Generation!$A:$A,Summary_CDP,Generation!$B:$B,IF($B$54="NEM","*",$B$54),Generation!$C:$C,$H58) -> 0
H59: Mid-merit Gas | I59: =SUMIFS(Generation!D:D,Generation!$A:$A,Summary_CDP,Generation!$B:$B,IF($B$54="NEM","*",$B$54),Generation!$C:$C,$H59) -> 8716.0503 | J59: =SUMIFS(Generation!E:E,Generation!$A:$A,Summary_CDP,Generation!$B:$B,IF($B$54="NEM","*",$B$54),Generation!$C:$C,$H59) -> 3413.2064 | K59: =SUMIFS(Generation!F:F,Generation!$A:$A,Summary_CDP,Generation!$B:$B,IF($B$54="NEM","*",$B$54),Generation!$C:$C,$H59) -> 4453.2616 | L59: =SUMIFS(Generation!G:G,Generation!$A:$A,Summary_CDP,Generation!$B:$B,IF($B$54="NEM","*",$B$54),Generation!$C:$C,$H59) -> 5908.1028 | M59: =SUMIFS(Generation!H:H,Generation!$A:$A,Summary_CDP,Generation!$B:$B,IF($B$54="NEM","*",$B$54),Generation!$C:$C,$H59) -> 7410.8223 | N59: =SUMIFS(Generation!I:I,Generation!$A:$A,Summary_CDP,Generation!$B:$B,IF($B$54="NEM","*",$B$54),Generation!$C:$C,$H59) -> 6949.5117 | O59: =SUMIFS(Generation!J:J,Generation!$A:$A,Summary_CDP,Generation!$B:$B,IF($B$54="NEM","*",$B$54),Generation!$C:$C,$H59) -> 5338.1052 | P59: =SUMIFS(Generation!K:K,Generation!$A:$A,Summary_CDP,Generation!$B:$B,IF($B$54="NEM","*",$B$54),Generation!$C:$C,$H59) -> 5097.5172 | Q59: =SUMIFS(Generation!L:L,Generation!$A:$A,Summary_CDP,Generation!$B:$B,IF($B$54="NEM","*",$B$54),Generation!$C:$C,$H59) -> 3629.5213 | R59: =SUMIFS(Generation!M:M,Generation!$A:$A,Summary_CDP,Generation!$B:$B,IF($B$54="NEM","*",$B$54),Generation!$C:$C,$H59) -> 2908.9362 | S59: =SUMIFS(Generation!N:N,Generation!$A:$A,Summary_CDP,Generation!$B:$B,IF($B$54="NEM","*",$B$54),Generation!$C:$C,$H59) -> 4265.0825 | T59: =SUMIFS(Generation!O:O,Generation!$A:$A,Summary_CDP,Generation!$B:$B,IF($B$54="NEM","*",$B$54),Generation!$C:$C,$H59) -> 4866.9316 | U59: =SUMIFS(Generation!P:P,Generation!$A:$A,Summary_CDP,Generation!$B:$B,IF($B$54="NEM","*",$B$54),Generation!$C:$C,$H59) -> 4768.7266 | V59: =SUMIFS(Generation!Q:Q,Generation!$A:$A,Summary_CDP,Generation!$B:$B,IF($B$54="NEM","*",$B$54),Generation!$C:$C,$H59) -> 2641.6215 | W59: =SUMIFS(Generation!R:R,Generation!$A:$A,Summary_CDP,Generation!$B:$B,IF($B$54="NEM","*",$B$54),Generation!$C:$C,$H59) -> 2861.9853 | X59: =SUMIFS(Generation!S:S,Generation!$A:$A,Summary_CDP,Generation!$B:$B,IF($B$54="NEM","*",$B$54),Generation!$C:$C,$H59) -> 3097.6503 | Y59: =SUMIFS(Generation!T:T,Generation!$A:$A,Summary_CDP,Generation!$B:$B,IF($B$54="NEM","*",$B$54),Generation!$C:$C,$H59) -> 1519.3116 | Z59: =SUMIFS(Generation!U:U,Generation!$A:$A,Summary_CDP,Generation!$B:$B,IF($B$54="NEM","*",$B$54),Generation!$C:$C,$H59) -> 2407.4759 | AA59: =SUMIFS(Generation!V:V,Generation!$A:$A,Summary_CDP,Generation!$B:$B,IF($B$54="NEM","*",$B$54),Generation!$C:$C,$H59) -> 2227.4556 | AB59: =SUMIFS(Generation!W:W,Generation!$A:$A,Summary_CDP,Generation!$B:$B,IF($B$54="NEM","*",$B$54),Generation!$C:$C,$H59) -> 1611.8299 | AC59: =SUMIFS(Generation!X:X,Generation!$A:$A,Summary_CDP,Generation!$B:$B,IF($B$54="NEM","*",$B$54),Generation!$C:$C,$H59) -> 1052.343 | AD59: =SUMIFS(Generation!Y:Y,Generation!$A:$A,Summary_CDP,Generation!$B:$B,IF($B$54="NEM","*",$B$54),Generation!$C:$C,$H59) -> 686.12768 | AE59: =SUMIFS(Generation!Z:Z,Generation!$A:$A,Summary_CDP,Generation!$B:$B,IF($B$54="NEM","*",$B$54),Generation!$C:$C,$H59) -> 114.19631 | AF59: =SUMIFS(Generation!AA:AA,Generation!$A:$A,Summary_CDP,Generation!$B:$B,IF($B$54="NEM","*",$B$54),Generation!$C:$C,$H59) -> 0 | AG59: =SUMIFS(Generation!AB:AB,Generation!$A:$A,Summary_CDP,Generation!$B:$B,IF($B$54="NEM","*",$B$54),Generation!$C:$C,$H59) -> 0 | AH59: =SUMIFS(Generation!AC:AC,Generation!$A:$A,Summary_CDP,Generation!$B:$B,IF($B$54="NEM","*",$B$54),Generation!$C:$C,$H59) -> 0 | AI59: =SUMIFS(Generation!AD:AD,Generation!$A:$A,Summary_CDP,Generation!$B:$B,IF($B$54="NEM","*",$B$54),Generation!$C:$C,$H59) -> 0 | AJ59: =SUMIFS(Generation!AE:AE,Generation!$A:$A,Summary_CDP,Generation!$B:$B,IF($B$54="NEM","*",$B$54),Generation!$C:$C,$H59) -> 0
H60: Mid-merit Gas with CCS | I60: =SUMIFS(Generation!D:D,Generation!$A:$A,Summary_CDP,Generation!$B:$B,IF($B$54="NEM","*",$B$54),Generation!$C:$C,$H60) -> 0 | J60: =SUMIFS(Generation!E:E,Generation!$A:$A,Summary_CDP,Generation!$B:$B,IF($B$54="NEM","*",$B$54),Generation!$C:$C,$H60) -> 0 | K60: =SUMIFS(Generation!F:F,Generation!$A:$A,Summary_CDP,Generation!$B:$B,IF($B$54="NEM","*",$B$54),Generation!$C:$C,$H60) -> 0 | L60: =SUMIFS(Generation!G:G,Generation!$A:$A,Summary_CDP,Generation!$B:$B,IF($B$54="NEM","*",$B$54),Generation!$C:$C,$H60) -> 0 | M60: =SUMIFS(Generation!H:H,Generation!$A:$A,Summary_CDP,Generation!$B:$B,IF($B$54="NEM","*",$B$54),Generation!$C:$C,$H60) -> 0 | N60: =SUMIFS(Generation!I:I,Generation!$A:$A,Summary_CDP,Generation!$B:$B,IF($B$54="NEM","*",$B$54),Generation!$C:$C,$H60) -> 0 | O60: =SUMIFS(Generation!J:J,Generation!$A:$A,Summary_CDP,Generation!$B:$B,IF($B$54="NEM","*",$B$54),Generation!$C:$C,$H60) -> 0 | P60: =SUMIFS(Generation!K:K,Generation!$A:$A,Summary_CDP,Generation!$B:$B,IF($B$54="NEM","*",$B$54),Generation!$C:$C,$H60) -> 0 | Q60: =SUMIFS(Generation!L:L,Generation!$A:$A,Summary_CDP,Generation!$B:$B,IF($B$54="NEM","*",$B$54),Generation!$C:$C,$H60) -> 0 | R60: =SUMIFS(Generation!M:M,Generation!$A:$A,Summary_CDP,Generation!$B:$B,IF($B$54="NEM","*",$B$54),Generation!$C:$C,$H60) -> 0 | S60: =SUMIFS(Generation!N:N,Generation!$A:$A,Summary_CDP,Generation!$B:$B,IF($B$54="NEM","*",$B$54),Generation!$C:$C,$H60) -> 0 | T60: =SUMIFS(Generation!O:O,Generation!$A:$A,Summary_CDP,Generation!$B:$B,IF($B$54="NEM","*",$B$54),Generation!$C:$C,$H60) -> 0 | U60: =SUMIFS(Generation!P:P,Generation!$A:$A,Summary_CDP,Generation!$B:$B,IF($B$54="NEM","*",$B$54),Generation!$C:$C,$H60) -> 0 | V60: =SUMIFS(Generation!Q:Q,Generation!$A:$A,Summary_CDP,Generation!$B:$B,IF($B$54="NEM","*",$B$54),Generation!$C:$C,$H60) -> 0 | W60: =SUMIFS(Generation!R:R,Generation!$A:$A,Summary_CDP,Generation!$B:$B,IF($B$54="NEM","*",$B$54),Generation!$C:$C,$H60) -> 0 | X60: =SUMIFS(Generation!S:S,Generation!$A:$A,Summary_CDP,Generation!$B:$B,IF($B$54="NEM","*",$B$54),Generation!$C:$C,$H60) -> 0 | Y60: =SUMIFS(Generation!T:T,Generation!$A:$A,Summary_CDP,Generation!$B:$B,IF($B$54="NEM","*",$B$54),Generation!$C:$C,$H60) -> 0 | Z60: =SUMIFS(Generation!U:U,Generation!$A:$A,Summary_CDP,Generation!$B:$B,IF($B$54="NEM","*",$B$54),Generation!$C:$C,$H60) -> 0 | AA60: =SUMIFS(Generation!V:V,Generation!$A:$A,Summary_CDP,Generation!$B:$B,IF($B$54="NEM","*",$B$54),Generation!$C:$C,$H60) -> 0 | AB60: =SUMIFS(Generation!W:W,Generation!$A:$A,Summary_CDP,Generation!$B:$B,IF($B$54="NEM","*",$B$54),Generation!$C:$C,$H60) -> 0 | AC60: =SUMIFS(Generation!X:X,Generation!$A:$A,Summary_CDP,Generation!$B:$B,IF($B$54="NEM","*",$B$54),Generation!$C:$C,$H60) -> 0 | AD60: =SUMIFS(Generation!Y:Y,Generation!$A:$A,Summary_CDP,Generation!$B:$B,IF($B$54="NEM","*",$B$54),Generation!$C:$C,$H60) -> 0 | AE60: =SUMIFS(Generation!Z:Z,Generation!$A:$A,Summary_CDP,Generation!$B:$B,IF($B$54="NEM","*",$B$54),Generation!$C:$C,$H60) -> 0 | AF60: =SUMIFS(Generation!AA:AA,Generation!$A:$A,Summary_CDP,Generation!$B:$B,IF($B$54="NEM","*",$B$54),Generation!$C:$C,$H60) -> 0 | AG60: =SUMIFS(Generation!AB:AB,Generation!$A:$A,Summary_CDP,Generation!$B:$B,IF($B$54="NEM","*",$B$54),Generation!$C:$C,$H60) -> 0 | AH60: =SUMIFS(Generation!AC:AC,Generation!$A:$A,Summary_CDP,Generation!$B:$B,IF($B$54="NEM","*",$B$54),Generation!$C:$C,$H60) -> 0 | AI60: =SUMIFS(Generation!AD:AD,Generation!$A:$A,Summary_CDP,Generation!$B:$B,IF($B$54="NEM","*",$B$54),Generation!$C:$C,$H60) -> 0 | AJ60: =SUMIFS(Generation!AE:AE,Generation!$A:$A,Summary_CDP,Generation!$B:$B,IF($B$54="NEM","*",$B$54),Generation!$C:$C,$H60) -> 0
H61: Peaking Gas+Liquids | I61: =SUMIFS(Generation!D:D,Generation!$A:$A,Summary_CDP,Generation!$B:$B,IF($B$54="NEM","*",$B$54),Generation!$C:$C,$H61) -> 471.31127 | J61: =SUMIFS(Generation!E:E,Generation!$A:$A,Summary_CDP,Generation!$B:$B,IF($B$54="NEM","*",$B$54),Generation!$C:$C,$H61) -> 235.15012 | K61: =SUMIFS(Generation!F:F,Generation!$A:$A,Summary_CDP,Generation!$B:$B,IF($B$54="NEM","*",$B$54),Generation!$C:$C,$H61) -> 311.98423 | L61: =SUMIFS(Generation!G:G,Generation!$A:$A,Summary_CDP,Generation!$B:$B,IF($B$54="NEM","*",$B$54),Generation!$C:$C,$H61) -> 672.72306 | M61: =SUMIFS(Generation!H:H,Generation!$A:$A,Summary_CDP,Generation!$B:$B,IF($B$54="NEM","*",$B$54),Generation!$C:$C,$H61) -> 2700.2431 | N61: =SUMIFS(Generation!I:I,Generation!$A:$A,Summary_CDP,Generation!$B:$B,IF($B$54="NEM","*",$B$54),Generation!$C:$C,$H61) -> 3997.2561 | O61: =SUMIFS(Generation!J:J,Generation!$A:$A,Summary_CDP,Generation!$B:$B,IF($B$54="NEM","*",$B$54),Generation!$C:$C,$H61) -> 3185.6481 | P61: =SUMIFS(Generation!K:K,Generation!$A:$A,Summary_CDP,Generation!$B:$B,IF($B$54="NEM","*",$B$54),Generation!$C:$C,$H61) -> 2348.422 | Q61: =SUMIFS(Generation!L:L,Generation!$A:$A,Summary_CDP,Generation!$B:$B,IF($B$54="NEM","*",$B$54),Generation!$C:$C,$H61) -> 2262.1237 | R61: =SUMIFS(Generation!M:M,Generation!$A:$A,Summary_CDP,Generation!$B:$B,IF($B$54="NEM","*",$B$54),Generation!$C:$C,$H61) -> 1368.7336 | S61: =SUMIFS(Generation!N:N,Generation!$A:$A,Summary_CDP,Generation!$B:$B,IF($B$54="NEM","*",$B$54),Generation!$C:$C,$H61) -> 474.53472 | T61: =SUMIFS(Generation!O:O,Generation!$A:$A,Summary_CDP,Generation!$B:$B,IF($B$54="NEM","*",$B$54),Generation!$C:$C,$H61) -> 2398.1575 | U61: =SUMIFS(Generation!P:P,Generation!$A:$A,Summary_CDP,Generation!$B:$B,IF($B$54="NEM","*",$B$54),Generation!$C:$C,$H61) -> 693.6924 | V61: =SUMIFS(Generation!Q:Q,Generation!$A:$A,Summary_CDP,Generation!$B:$B,IF($B$54="NEM","*",$B$54),Generation!$C:$C,$H61) -> 1255.5171 | W61: =SUMIFS(Generation!R:R,Generation!$A:$A,Summary_CDP,Generation!$B:$B,IF($B$54="NEM","*",$B$54),Generation!$C:$C,$H61) -> 1049.3641 | X61: =SUMIFS(Generation!S:S,Generation!$A:$A,Summary_CDP,Generation!$B:$B,IF($B$54="NEM","*",$B$54),Generation!$C:$C,$H61) -> 5793.6926 | Y61: =SUMIFS(Generation!T:T,Generation!$A:$A,Summary_CDP,Generation!$B:$B,IF($B$54="NEM","*",$B$54),Generation!$C:$C,$H61) -> 1877.5298 | Z61: =SUMIFS(Generation!U:U,Generation!$A:$A,Summary_CDP,Generation!$B:$B,IF($B$54="NEM","*",$B$54),Generation!$C:$C,$H61) -> 1509.1851 | AA61: =SUMIFS(Generation!V:V,Generation!$A:$A,Summary_CDP,Generation!$B:$B,IF($B$54="NEM","*",$B$54),Generation!$C:$C,$H61) -> 3645.8208 | AB61: =SUMIFS(Generation!W:W,Generation!$A:$A,Summary_CDP,Generation!$B:$B,IF($B$54="NEM","*",$B$54),Generation!$C:$C,$H61) -> 3476.5998 | AC61: =SUMIFS(Generation!X:X,Generation!$A:$A,Summary_CDP,Generation!$B:$B,IF($B$54="NEM","*",$B$54),Generation!$C:$C,$H61) -> 6590.1216 | AD61: =SUMIFS(Generation!Y:Y,Generation!$A:$A,Summary_CDP,Generation!$B:$B,IF($B$54="NEM","*",$B$54),Generation!$C:$C,$H61) -> 2543.3981 | AE61: =SUMIFS(Generation!Z:Z,Generation!$A:$A,Summary_CDP,Generation!$B:$B,IF($B$54="NEM","*",$B$54),Generation!$C:$C,$H61) -> 4126.3339 | AF61: =SUMIFS(Generation!AA:AA,Generation!$A:$A,Summary_CDP,Generation!$B:$B,IF($B$54="NEM","*",$B$54),Generation!$C:$C,$H61) -> 1448.0937 | AG61: =SUMIFS(Generation!AB:AB,Generation!$A:$A,Summary_CDP,Generation!$B:$B,IF($B$54="NEM","*",$B$54),Generation!$C:$C,$H61) -> 2988.5135 | AH61: =SUMIFS(Generation!AC:AC,Generation!$A:$A,Summary_CDP,Generation!$B:$B,IF($B$54="NEM","*",$B$54),Generation!$C:$C,$H61) -> 1672.2859 | AI61: =SUMIFS(Generation!AD:AD,Generation!$A:$A,Summary_CDP,Generation!$B:$B,IF($B$54="NEM","*",$B$54),Generation!$C:$C,$H61) -> 8892.7641 | AJ61: =SUMIFS(Generation!AE:AE,Generation!$A:$A,Summary_CDP,Generation!$B:$B,IF($B$54="NEM","*",$B$54),Generation!$C:$C,$H61) -> 4.6565712
H62: Hydrogen Turbine | I62: =SUMIFS(Generation!D:D,Generation!$A:$A,Summary_CDP,Generation!$B:$B,IF($B$54="NEM","*",$B$54),Generation!$C:$C,$H62) -> 0 | J62: =SUMIFS(Generation!E:E,Generation!$A:$A,Summary_CDP,Generation!$B:$B,IF($B$54="NEM","*",$B$54),Generation!$C:$C,$H62) -> 0 | K62: =SUMIFS(Generation!F:F,Generation!$A:$A,Summary_CDP,Generation!$B:$B,IF($B$54="NEM","*",$B$54),Generation!$C:$C,$H62) -> 0 | L62: =SUMIFS(Generation!G:G,Generation!$A:$A,Summary_CDP,Generation!$B:$B,IF($B$54="NEM","*",$B$54),Generation!$C:$C,$H62) -> 0 | M62: =SUMIFS(Generation!H:H,Generation!$A:$A,Summary_CDP,Generation!$B:$B,IF($B$54="NEM","*",$B$54),Generation!$C:$C,$H62) -> 0 | N62: =SUMIFS(Generation!I:I,Generation!$A:$A,Summary_CDP,Generation!$B:$B,IF($B$54="NEM","*",$B$54),Generation!$C:$C,$H62) -> 0 | O62: =SUMIFS(Generation!J:J,Generation!$A:$A,Summary_CDP,Generation!$B:$B,IF($B$54="NEM","*",$B$54),Generation!$C:$C,$H62) -> 0 | P62: =SUMIFS(Generation!K:K,Generation!$A:$A,Summary_CDP,Generation!$B:$B,IF($B$54="NEM","*",$B$54),Generation!$C:$C,$H62) -> 0 | Q62: =SUMIFS(Generation!L:L,Generation!$A:$A,Summary_CDP,Generation!$B:$B,IF($B$54="NEM","*",$B$54),Generation!$C:$C,$H62) -> 0 | R62: =SUMIFS(Generation!M:M,Generation!$A:$A,Summary_CDP,Generation!$B:$B,IF($B$54="NEM","*",$B$54),Generation!$C:$C,$H62) -> 0 | S62: =SUMIFS(Generation!N:N,Generation!$A:$A,Summary_CDP,Generation!$B:$B,IF($B$54="NEM","*",$B$54),Generation!$C:$C,$H62) -> 0 | T62: =SUMIFS(Generation!O:O,Generation!$A:$A,Summary_CDP,Generation!$B:$B,IF($B$54="NEM","*",$B$54),Generation!$C:$C,$H62) -> 0 | U62: =SUMIFS(Generation!P:P,Generation!$A:$A,Summary_CDP,Generation!$B:$B,IF($B$54="NEM","*",$B$54),Generation!$C:$C,$H62) -> 0 | V62: =SUMIFS(Generation!Q:Q,Generation!$A:$A,Summary_CDP,Generation!$B:$B,IF($B$54="NEM","*",$B$54),Generation!$C:$C,$H62) -> 0 | W62: =SUMIFS(Generation!R:R,Generation!$A:$A,Summary_CDP,Generation!$B:$B,IF($B$54="NEM","*",$B$54),Generation!$C:$C,$H62) -> 0 | X62: =SUMIFS(Generation!S:S,Generation!$A:$A,Summary_CDP,Generation!$B:$B,IF($B$54="NEM","*",$B$54),Generation!$C:$C,$H62) -> 0 | Y62: =SUMIFS(Generation!T:T,Generation!$A:$A,Summary_CDP,Generation!$B:$B,IF($B$54="NEM","*",$B$54),Generation!$C:$C,$H62) -> 0 | Z62: =SUMIFS(Generation!U:U,Generation!$A:$A,Summary_CDP,Generation!$B:$B,IF($B$54="NEM","*",$B$54),Generation!$C:$C,$H62) -> 0 | AA62: =SUMIFS(Generation!V:V,Generation!$A:$A,Summary_CDP,Generation!$B:$B,IF($B$54="NEM","*",$B$54),Generation!$C:$C,$H62) -> 0 | AB62: =SUMIFS(Generation!W:W,Generation!$A:$A,Summary_CDP,Generation!$B:$B,IF($B$54="NEM","*",$B$54),Generation!$C:$C,$H62) -> 0 | AC62: =SUMIFS(Generation!X:X,Generation!$A:$A,Summary_CDP,Generation!$B:$B,IF($B$54="NEM","*",$B$54),Generation!$C:$C,$H62) -> 0 | AD62: =SUMIFS(Generation!Y:Y,Generation!$A:$A,Summary_CDP,Generation!$B:$B,IF($B$54="NEM","*",$B$54),Generation!$C:$C,$H62) -> 0 | AE62: =SUMIFS(Generation!Z:Z,Generation!$A:$A,Summary_CDP,Generation!$B:$B,IF($B$54="NEM","*",$B$54),Generation!$C:$C,$H62) -> 0 | AF62: =SUMIFS(Generation!AA:AA,Generation!$A:$A,Summary_CDP,Generation!$B:$B,IF($B$54="NEM","*",$B$54),Generation!$C:$C,$H62) -> 0 | AG62: =SUMIFS(Generation!AB:AB,Generation!$A:$A,Summary_CDP,Generation!$B:$B,IF($B$54="NEM","*",$B$54),Generation!$C:$C,$H62) -> 0 | AH62: =SUMIFS(Generation!AC:AC,Generation!$A:$A,Summary_CDP,Generation!$B:$B,IF($B$54="NEM","*",$B$54),Generation!$C:$C,$H62) -> 0 | AI62: =SUMIFS(Generation!AD:AD,Generation!$A:$A,Summary_CDP,Generation!$B:$B,IF($B$54="NEM","*",$B$54),Generation!$C:$C,$H62) -> 1508.9294 | AJ62: =SUMIFS(Generation!AE:AE,Generation!$A:$A,Summary_CDP,Generation!$B:$B,IF($B$54="NEM","*",$B$54),Generation!$C:$C,$H62) -> 1508.9294
H63: Hydro | I63: =SUMIFS(Generation!D:D,Generation!$A:$A,Summary_CDP,Generation!$B:$B,IF($B$54="NEM","*",$B$54),Generation!$C:$C,$H63) -> 15034.845 | J63: =SUMIFS(Generation!E:E,Generation!$A:$A,Summary_CDP,Generation!$B:$B,IF($B$54="NEM","*",$B$54),Generation!$C:$C,$H63) -> 13425.519 | K63: =SUMIFS(Generation!F:F,Generation!$A:$A,Summary_CDP,Generation!$B:$B,IF($B$54="NEM","*",$B$54),Generation!$C:$C,$H63) -> 12577.676 | L63: =SUMIFS(Generation!G:G,Generation!$A:$A,Summary_CDP,Generation!$B:$B,IF($B$54="NEM","*",$B$54),Generation!$C:$C,$H63) -> 13509.514 | M63: =SUMIFS(Generation!H:H,Generation!$A:$A,Summary_CDP,Generation!$B:$B,IF($B$54="NEM","*",$B$54),Generation!$C:$C,$H63) -> 16868.966 | N63: =SUMIFS(Generation!I:I,Generation!$A:$A,Summary_CDP,Generation!$B:$B,IF($B$54="NEM","*",$B$54),Generation!$C:$C,$H63) -> 14123.168 | O63: =SUMIFS(Generation!J:J,Generation!$A:$A,Summary_CDP,Generation!$B:$B,IF($B$54="NEM","*",$B$54),Generation!$C:$C,$H63) -> 12784.524 | P63: =SUMIFS(Generation!K:K,Generation!$A:$A,Summary_CDP,Generation!$B:$B,IF($B$54="NEM","*",$B$54),Generation!$C:$C,$H63) -> 15324.98 | Q63: =SUMIFS(Generation!L:L,Generation!$A:$A,Summary_CDP,Generation!$B:$B,IF($B$54="NEM","*",$B$54),Generation!$C:$C,$H63) -> 10903.404 | R63: =SUMIFS(Generation!M:M,Generation!$A:$A,Summary_CDP,Generation!$B:$B,IF($B$54="NEM","*",$B$54),Generation!$C:$C,$H63) -> 14422.804 | S63: =SUMIFS(Generation!N:N,Generation!$A:$A,Summary_CDP,Generation!$B:$B,IF($B$54="NEM","*",$B$54),Generation!$C:$C,$H63) -> 13621.435 | T63: =SUMIFS(Generation!O:O,Generation!$A:$A,Summary_CDP,Generation!$B:$B,IF($B$54="NEM","*",$B$54),Generation!$C:$C,$H63) -> 12539.948 | U63: =SUMIFS(Generation!P:P,Generation!$A:$A,Summary_CDP,Generation!$B:$B,IF($B$54="NEM","*",$B$54),Generation!$C:$C,$H63) -> 13052.464 | V63: =SUMIFS(Generation!Q:Q,Generation!$A:$A,Summary_CDP,Generation!$B:$B,IF($B$54="NEM","*",$B$54),Generation!$C:$C,$H63) -> 11712.808 | W63: =SUMIFS(Generation!R:R,Generation!$A:$A,Summary_CDP,Generation!$B:$B,IF($B$54="NEM","*",$B$54),Generation!$C:$C,$H63) -> 13235.077 | X63: =SUMIFS(Generation!S:S,Generation!$A:$A,Summary_CDP,Generation!$B:$B,IF($B$54="NEM","*",$B$54),Generation!$C:$C,$H63) -> 14671.453 | Y63: =SUMIFS(Generation!T:T,Generation!$A:$A,Summary_CDP,Generation!$B:$B,IF($B$54="NEM","*",$B$54),Generation!$C:$C,$H63) -> 8128.075 | Z63: =SUMIFS(Generation!U:U,Generation!$A:$A,Summary_CDP,Generation!$B:$B,IF($B$54="NEM","*",$B$54),Generation!$C:$C,$H63) -> 12522.101 | AA63: =SUMIFS(Generation!V:V,Generation!$A:$A,Summary_CDP,Generation!$B:$B,IF($B$54="NEM","*",$B$54),Generation!$C:$C,$H63) -> 12834.796 | AB63: =SUMIFS(Generation!W:W,Generation!$A:$A,Summary_CDP,Generation!$B:$B,IF($B$54="NEM","*",$B$54),Generation!$C:$C,$H63) -> 9554.442 | AC63: =SUMIFS(Generation!X:X,Generation!$A:$A,Summary_CDP,Generation!$B:$B,IF($B$54="NEM","*",$B$54),Generation!$C:$C,$H63) -> 11395.753 | AD63: =SUMIFS(Generation!Y:Y,Generation!$A:$A,Summary_CDP,Generation!$B:$B,IF($B$54="NEM","*",$B$54),Generation!$C:$C,$H63) -> 12964.749 | AE63: =SUMIFS(Generation!Z:Z,Generation!$A:$A,Summary_CDP,Generation!$B:$B,IF($B$54="NEM","*",$B$54),Generation!$C:$C,$H63) -> 9645.9349 | AF63: =SUMIFS(Generation!AA:AA,Generation!$A:$A,Summary_CDP,Generation!$B:$B,IF($B$54="NEM","*",$B$54),Generation!$C:$C,$H63) -> 10478.557 | AG63: =SUMIFS(Generation!AB:AB,Generation!$A:$A,Summary_CDP,Generation!$B:$B,IF($B$54="NEM","*",$B$54),Generation!$C:$C,$H63) -> 11133.406 | AH63: =SUMIFS(Generation!AC:AC,Generation!$A:$A,Summary_CDP,Generation!$B:$B,IF($B$54="NEM","*",$B$54),Generation!$C:$C,$H63) -> 11696.498 | AI63: =SUMIFS(Generation!AD:AD,Generation!$A:$A,Summary_CDP,Generation!$B:$B,IF($B$54="NEM","*",$B$54),Generation!$C:$C,$H63) -> 12098.996 | AJ63: =SUMIFS(Generation!AE:AE,Generation!$A:$A,Summary_CDP,Generation!$B:$B,IF($B$54="NEM","*",$B$54),Generation!$C:$C,$H63) -> 6652.0833
H64: Utility-scale Storage | I64: =SUMIFS(Generation!D:D,Generation!$A:$A,Summary_CDP,Generation!$B:$B,IF($B$54="NEM","*",$B$54),Generation!$C:$C,$H64) -> 1059.6369 | J64: =SUMIFS(Generation!E:E,Generation!$A:$A,Summary_CDP,Generation!$B:$B,IF($B$54="NEM","*",$B$54),Generation!$C:$C,$H64) -> 1810.8888 | K64: =SUMIFS(Generation!F:F,Generation!$A:$A,Summary_CDP,Generation!$B:$B,IF($B$54="NEM","*",$B$54),Generation!$C:$C,$H64) -> 4391.7801 | L64: =SUMIFS(Generation!G:G,Generation!$A:$A,Summary_CDP,Generation!$B:$B,IF($B$54="NEM","*",$B$54),Generation!$C:$C,$H64) -> 8099.8498 | M64: =SUMIFS(Generation!H:H,Generation!$A:$A,Summary_CDP,Generation!$B:$B,IF($B$54="NEM","*",$B$54),Generation!$C:$C,$H64) -> 13949.786 | N64: =SUMIFS(Generation!I:I,Generation!$A:$A,Summary_CDP,Generation!$B:$B,IF($B$54="NEM","*",$B$54),Generation!$C:$C,$H64) -> 21938.734 | O64: =SUMIFS(Generation!J:J,Generation!$A:$A,Summary_CDP,Generation!$B:$B,IF($B$54="NEM","*",$B$54),Generation!$C:$C,$H64) -> 21551.522 | P64: =SUMIFS(Generation!K:K,Generation!$A:$A,Summary_CDP,Generation!$B:$B,IF($B$54="NEM","*",$B$54),Generation!$C:$C,$H64) -> 26369.247 | Q64: =SUMIFS(Generation!L:L,Generation!$A:$A,Summary_CDP,Generation!$B:$B,IF($B$54="NEM","*",$B$54),Generation!$C:$C,$H64) -> 24405.825 | R64: =SUMIFS(Generation!M:M,Generation!$A:$A,Summary_CDP,Generation!$B:$B,IF($B$54="NEM","*",$B$54),Generation!$C:$C,$H64) -> 24212.258 | S64: =SUMIFS(Generation!N:N,Generation!$A:$A,Summary_CDP,Generation!$B:$B,IF($B$54="NEM","*",$B$54),Generation!$C:$C,$H64) -> 23880.281 | T64: =SUMIFS(Generation!O:O,Generation!$A:$A,Summary_CDP,Generation!$B:$B,IF($B$54="NEM","*",$B$54),Generation!$C:$C,$H64) -> 24483.651 | U64: =SUMIFS(Generation!P:P,Generation!$A:$A,Summary_CDP,Generation!$B:$B,IF($B$54="NEM","*",$B$54),Generation!$C:$C,$H64) -> 29169.518 | V64: =SUMIFS(Generation!Q:Q,Generation!$A:$A,Summary_CDP,Generation!$B:$B,IF($B$54="NEM","*",$B$54),Generation!$C:$C,$H64) -> 29854.19 | W64: =SUMIFS(Generation!R:R,Generation!$A:$A,Summary_CDP,Generation!$B:$B,IF($B$54="NEM","*",$B$54),Generation!$C:$C,$H64) -> 33308.514 | X64: =SUMIFS(Generation!S:S,Generation!$A:$A,Summary_CDP,Generation!$B:$B,IF($B$54="NEM","*",$B$54),Generation!$C:$C,$H64) -> 31462.627 | Y64: =SUMIFS(Generation!T:T,Generation!$A:$A,Summary_CDP,Generation!$B:$B,IF($B$54="NEM","*",$B$54),Generation!$C:$C,$H64) -> 34152.881 | Z64: =SUMIFS(Generation!U:U,Generation!$A:$A,Summary_CDP,Generation!$B:$B,IF($B$54="NEM","*",$B$54),Generation!$C:$C,$H64) -> 36101.53 | AA64: =SUMIFS(Generation!V:V,Generation!$A:$A,Summary_CDP,Generation!$B:$B,IF($B$54="NEM","*",$B$54),Generation!$C:$C,$H64) -> 50787.13 | AB64: =SUMIFS(Generation!W:W,Generation!$A:$A,Summary_CDP,Generation!$B:$B,IF($B$54="NEM","*",$B$54),Generation!$C:$C,$H64) -> 47720.142 | AC64: =SUMIFS(Generation!X:X,Generation!$A:$A,Summary_CDP,Generation!$B:$B,IF($B$54="NEM","*",$B$54),Generation!$C:$C,$H64) -> 42687.446 | AD64: =SUMIFS(Generation!Y:Y,Generation!$A:$A,Summary_CDP,Generation!$B:$B,IF($B$54="NEM","*",$B$54),Generation!$C:$C,$H64) -> 48413.967 | AE64: =SUMIFS(Generation!Z:Z,Generation!$A:$A,Summary_CDP,Generation!$B:$B,IF($B$54="NEM","*",$B$54),Generation!$C:$C,$H64) -> 58961.091 | AF64: =SUMIFS(Generation!AA:AA,Generation!$A:$A,Summary_CDP,Generation!$B:$B,IF($B$54="NEM","*",$B$54),Generation!$C:$C,$H64) -> 61049.424 | AG64: =SUMIFS(Generation!AB:AB,Generation!$A:$A,Summary_CDP,Generation!$B:$B,IF($B$54="NEM","*",$B$54),Generation!$C:$C,$H64) -> 59389.364 | AH64: =SUMIFS(Generation!AC:AC,Generation!$A:$A,Summary_CDP,Generation!$B:$B,IF($B$54="NEM","*",$B$54),Generation!$C:$C,$H64) -> 77167.254 | AI64: =SUMIFS(Generation!AD:AD,Generation!$A:$A,Summary_CDP,Generation!$B:$B,IF($B$54="NEM","*",$B$54),Generation!$C:$C,$H64) -> 110718.45 | AJ64: =SUMIFS(Generation!AE:AE,Generation!$A:$A,Summary_CDP,Generation!$B:$B,IF($B$54="NEM","*",$B$54),Generation!$C:$C,$H64) -> 111193.39
H65: Coordinated DER Storage | I65: =SUMIFS(Generation!D:D,Generation!$A:$A,Summary_CDP,Generation!$B:$B,IF($B$54="NEM","*",$B$54),Generation!$C:$C,$H65) -> 182.53473 | J65: =SUMIFS(Generation!E:E,Generation!$A:$A,Summary_CDP,Generation!$B:$B,IF($B$54="NEM","*",$B$54),Generation!$C:$C,$H65) -> 471.83508 | K65: =SUMIFS(Generation!F:F,Generation!$A:$A,Summary_CDP,Generation!$B:$B,IF($B$54="NEM","*",$B$54),Generation!$C:$C,$H65) -> 805.63802 | L65: =SUMIFS(Generation!G:G,Generation!$A:$A,Summary_CDP,Generation!$B:$B,IF($B$54="NEM","*",$B$54),Generation!$C:$C,$H65) -> 1192.3043 | M65: =SUMIFS(Generation!H:H,Generation!$A:$A,Summary_CDP,Generation!$B:$B,IF($B$54="NEM","*",$B$54),Generation!$C:$C,$H65) -> 1702.6055 | N65: =SUMIFS(Generation!I:I,Generation!$A:$A,Summary_CDP,Generation!$B:$B,IF($B$54="NEM","*",$B$54),Generation!$C:$C,$H65) -> 2208.4374 | O65: =SUMIFS(Generation!J:J,Generation!$A:$A,Summary_CDP,Generation!$B:$B,IF($B$54="NEM","*",$B$54),Generation!$C:$C,$H65) -> 2999.8878 | P65: =SUMIFS(Generation!K:K,Generation!$A:$A,Summary_CDP,Generation!$B:$B,IF($B$54="NEM","*",$B$54),Generation!$C:$C,$H65) -> 3691.3573 | Q65: =SUMIFS(Generation!L:L,Generation!$A:$A,Summary_CDP,Generation!$B:$B,IF($B$54="NEM","*",$B$54),Generation!$C:$C,$H65) -> 4529.4534 | R65: =SUMIFS(Generation!M:M,Generation!$A:$A,Summary_CDP,Generation!$B:$B,IF($B$54="NEM","*",$B$54),Generation!$C:$C,$H65) -> 5125.9545 | S65: =SUMIFS(Generation!N:N,Generation!$A:$A,Summary_CDP,Generation!$B:$B,IF($B$54="NEM","*",$B$54),Generation!$C:$C,$H65) -> 6515.265 | T65: =SUMIFS(Generation!O:O,Generation!$A:$A,Summary_CDP,Generation!$B:$B,IF($B$54="NEM","*",$B$54),Generation!$C:$C,$H65) -> 7875.4559 | U65: =SUMIFS(Generation!P:P,Generation!$A:$A,Summary_CDP,Generation!$B:$B,IF($B$54="NEM","*",$B$54),Generation!$C:$C,$H65) -> 9684.6863 | V65: =SUMIFS(Generation!Q:Q,Generation!$A:$A,Summary_CDP,Generation!$B:$B,IF($B$54="NEM","*",$B$54),Generation!$C:$C,$H65) -> 11289.774 | W65: =SUMIFS(Generation!R:R,Generation!$A:$A,Summary_CDP,Generation!$B:$B,IF($B$54="NEM","*",$B$54),Generation!$C:$C,$H65) -> 13343.186 | X65: =SUMIFS(Generation!S:S,Generation!$A:$A,Summary_CDP,Generation!$B:$B,IF($B$54="NEM","*",$B$54),Generation!$C:$C,$H65) -> 14384.599 | Y65: =SUMIFS(Generation!T:T,Generation!$A:$A,Summary_CDP,Generation!$B:$B,IF($B$54="NEM","*",$B$54),Generation!$C:$C,$H65) -> 16636.001 | Z65: =SUMIFS(Generation!U:U,Generation!$A:$A,Summary_CDP,Generation!$B:$B,IF($B$54="NEM","*",$B$54),Generation!$C:$C,$H65) -> 18350.516 | AA65: =SUMIFS(Generation!V:V,Generation!$A:$A,Summary_CDP,Generation!$B:$B,IF($B$54="NEM","*",$B$54),Generation!$C:$C,$H65) -> 19388.639 | AB65: =SUMIFS(Generation!W:W,Generation!$A:$A,Summary_CDP,Generation!$B:$B,IF($B$54="NEM","*",$B$54),Generation!$C:$C,$H65) -> 21050.685 | AC65: =SUMIFS(Generation!X:X,Generation!$A:$A,Summary_CDP,Generation!$B:$B,IF($B$54="NEM","*",$B$54),Generation!$C:$C,$H65) -> 20832.117 | AD65: =SUMIFS(Generation!Y:Y,Generation!$A:$A,Summary_CDP,Generation!$B:$B,IF($B$54="NEM","*",$B$54),Generation!$C:$C,$H65) -> 23701.051 | AE65: =SUMIFS(Generation!Z:Z,Generation!$A:$A,Summary_CDP,Generation!$B:$B,IF($B$54="NEM","*",$B$54),Generation!$C:$C,$H65) -> 26372.796 | AF65: =SUMIFS(Generation!AA:AA,Generation!$A:$A,Summary_CDP,Generation!$B:$B,IF($B$54="NEM","*",$B$54),Generation!$C:$C,$H65) -> 26919.289 | AG65: =SUMIFS(Generation!AB:AB,Generation!$A:$A,Summary_CDP,Generation!$B:$B,IF($B$54="NEM","*",$B$54),Generation!$C:$C,$H65) -> 27507.88 | AH65: =SUMIFS(Generation!AC:AC,Generation!$A:$A,Summary_CDP,Generation!$B:$B,IF($B$54="NEM","*",$B$54),Generation!$C:$C,$H65) -> 29278.605 | AI65: =SUMIFS(Generation!AD:AD,Generation!$A:$A,Summary_CDP,Generation!$B:$B,IF($B$54="NEM","*",$B$54),Generation!$C:$C,$H65) -> 31394.667 | AJ65: =SUMIFS(Generation!AE:AE,Generation!$A:$A,Summary_CDP,Generation!$B:$B,IF($B$54="NEM","*",$B$54),Generation!$C:$C,$H65) -> 33516.186
H66: Distributed Storage | I66: =SUMIFS(Generation!D:D,Generation!$A:$A,Summary_CDP,Generation!$B:$B,IF($B$54="NEM","*",$B$54),Generation!$C:$C,$H66) -> 414.76654 | J66: =SUMIFS(Generation!E:E,Generation!$A:$A,Summary_CDP,Generation!$B:$B,IF($B$54="NEM","*",$B$54),Generation!$C:$C,$H66) -> 721.89838 | K66: =SUMIFS(Generation!F:F,Generation!$A:$A,Summary_CDP,Generation!$B:$B,IF($B$54="NEM","*",$B$54),Generation!$C:$C,$H66) -> 1016.2529 | L66: =SUMIFS(Generation!G:G,Generation!$A:$A,Summary_CDP,Generation!$B:$B,IF($B$54="NEM","*",$B$54),Generation!$C:$C,$H66) -> 1278.2457 | M66: =SUMIFS(Generation!H:H,Generation!$A:$A,Summary_CDP,Generation!$B:$B,IF($B$54="NEM","*",$B$54),Generation!$C:$C,$H66) -> 1495.991 | N66: =SUMIFS(Generation!I:I,Generation!$A:$A,Summary_CDP,Generation!$B:$B,IF($B$54="NEM","*",$B$54),Generation!$C:$C,$H66) -> 1678.0142 | O66: =SUMIFS(Generation!J:J,Generation!$A:$A,Summary_CDP,Generation!$B:$B,IF($B$54="NEM","*",$B$54),Generation!$C:$C,$H66) -> 1908.8211 | P66: =SUMIFS(Generation!K:K,Generation!$A:$A,Summary_CDP,Generation!$B:$B,IF($B$54="NEM","*",$B$54),Generation!$C:$C,$H66) -> 2276.8832 | Q66: =SUMIFS(Generation!L:L,Generation!$A:$A,Summary_CDP,Generation!$B:$B,IF($B$54="NEM","*",$B$54),Generation!$C:$C,$H66) -> 2622.6311 | R66: =SUMIFS(Generation!M:M,Generation!$A:$A,Summary_CDP,Generation!$B:$B,IF($B$54="NEM","*",$B$54),Generation!$C:$C,$H66) -> 2955.3469 | S66: =SUMIFS(Generation!N:N,Generation!$A:$A,Summary_CDP,Generation!$B:$B,IF($B$54="NEM","*",$B$54),Generation!$C:$C,$H66) -> 3366.5609 | T66: =SUMIFS(Generation!O:O,Generation!$A:$A,Summary_CDP,Generation!$B:$B,IF($B$54="NEM","*",$B$54),Generation!$C:$C,$H66) -> 3799.6629 | U66: =SUMIFS(Generation!P:P,Generation!$A:$A,Summary_CDP,Generation!$B:$B,IF($B$54="NEM","*",$B$54),Generation!$C:$C,$H66) -> 4251.2772 | V66: =SUMIFS(Generation!Q:Q,Generation!$A:$A,Summary_CDP,Generation!$B:$B,IF($B$54="NEM","*",$B$54),Generation!$C:$C,$H66) -> 4614.9548 | W66: =SUMIFS(Generation!R:R,Generation!$A:$A,Summary_CDP,Generation!$B:$B,IF($B$54="NEM","*",$B$54),Generation!$C:$C,$H66) -> 4970.3285 | X66: =SUMIFS(Generation!S:S,Generation!$A:$A,Summary_CDP,Generation!$B:$B,IF($B$54="NEM","*",$B$54),Generation!$C:$C,$H66) -> 5228.5645 | Y66: =SUMIFS(Generation!T:T,Generation!$A:$A,Summary_CDP,Generation!$B:$B,IF($B$54="NEM","*",$B$54),Generation!$C:$C,$H66) -> 5432.8314 | Z66: =SUMIFS(Generation!U:U,Generation!$A:$A,Summary_CDP,Generation!$B:$B,IF($B$54="NEM","*",$B$54),Generation!$C:$C,$H66) -> 5487.5818 | AA66: =SUMIFS(Generation!V:V,Generation!$A:$A,Summary_CDP,Generation!$B:$B,IF($B$54="NEM","*",$B$54),Generation!$C:$C,$H66) -> 5546.6898 | AB66: =SUMIFS(Generation!W:W,Generation!$A:$A,Summary_CDP,Generation!$B:$B,IF($B$54="NEM","*",$B$54),Generation!$C:$C,$H66) -> 5530.8055 | AC66: =SUMIFS(Generation!X:X,Generation!$A:$A,Summary_CDP,Generation!$B:$B,IF($B$54="NEM","*",$B$54),Generation!$C:$C,$H66) -> 5522.6439 | AD66: =SUMIFS(Generation!Y:Y,Generation!$A:$A,Summary_CDP,Generation!$B:$B,IF($B$54="NEM","*",$B$54),Generation!$C:$C,$H66) -> 5479.8501 | AE66: =SUMIFS(Generation!Z:Z,Generation!$A:$A,Summary_CDP,Generation!$B:$B,IF($B$54="NEM","*",$B$54),Generation!$C:$C,$H66) -> 5437.2508 | AF66: =SUMIFS(Generation!AA:AA,Generation!$A:$A,Summary_CDP,Generation!$B:$B,IF($B$54="NEM","*",$B$54),Generation!$C:$C,$H66) -> 5423.0956 | AG66: =SUMIFS(Generation!AB:AB,Generation!$A:$A,Summary_CDP,Generation!$B:$B,IF($B$54="NEM","*",$B$54),Generation!$C:$C,$H66) -> 5380.6321 | AH66: =SUMIFS(Generation!AC:AC,Generation!$A:$A,Summary_CDP,Generation!$B:$B,IF($B$54="NEM","*",$B$54),Generation!$C:$C,$H66) -> 5319.5914 | AI66: =SUMIFS(Generation!AD:AD,Generation!$A:$A,Summary_CDP,Generation!$B:$B,IF($B$54="NEM","*",$B$54),Generation!$C:$C,$H66) -> 5249.4186 | AJ66: =SUMIFS(Generation!AE:AE,Generation!$A:$A,Summary_CDP,Generation!$B:$B,IF($B$54="NEM","*",$B$54),Generation!$C:$C,$H66) -> 5306.3911
H67: Solar Thermal | I67: =SUMIFS(Generation!D:D,Generation!$A:$A,Summary_CDP,Generation!$B:$B,IF($B$54="NEM","*",$B$54),Generation!$C:$C,$H67) -> 0 | J67: =SUMIFS(Generation!E:E,Generation!$A:$A,Summary_CDP,Generation!$B:$B,IF($B$54="NEM","*",$B$54),Generation!$C:$C,$H67) -> 0 | K67: =SUMIFS(Generation!F:F,Generation!$A:$A,Summary_CDP,Generation!$B:$B,IF($B$54="NEM","*",$B$54),Generation!$C:$C,$H67) -> 0 | L67: =SUMIFS(Generation!G:G,Generation!$A:$A,Summary_CDP,Generation!$B:$B,IF($B$54="NEM","*",$B$54),Generation!$C:$C,$H67) -> 0 | M67: =SUMIFS(Generation!H:H,Generation!$A:$A,Summary_CDP,Generation!$B:$B,IF($B$54="NEM","*",$B$54),Generation!$C:$C,$H67) -> 0 | N67: =SUMIFS(Generation!I:I,Generation!$A:$A,Summary_CDP,Generation!$B:$B,IF($B$54="NEM","*",$B$54),Generation!$C:$C,$H67) -> 0 | O67: =SUMIFS(Generation!J:J,Generation!$A:$A,Summary_CDP,Generation!$B:$B,IF($B$54="NEM","*",$B$54),Generation!$C:$C,$H67) -> 0 | P67: =SUMIFS(Generation!K:K,Generation!$A:$A,Summary_CDP,Generation!$B:$B,IF($B$54="NEM","*",$B$54),Generation!$C:$C,$H67) -> 0 | Q67: =SUMIFS(Generation!L:L,Generation!$A:$A,Summary_CDP,Generation!$B:$B,IF($B$54="NEM","*",$B$54),Generation!$C:$C,$H67) -> 0 | R67: =SUMIFS(Generation!M:M,Generation!$A:$A,Summary_CDP,Generation!$B:$B,IF($B$54="NEM","*",$B$54),Generation!$C:$C,$H67) -> 0 | S67: =SUMIFS(Generation!N:N,Generation!$A:$A,Summary_CDP,Generation!$B:$B,IF($B$54="NEM","*",$B$54),Generation!$C:$C,$H67) -> 0 | T67: =SUMIFS(Generation!O:O,Generation!$A:$A,Summary_CDP,Generation!$B:$B,IF($B$54="NEM","*",$B$54),Generation!$C:$C,$H67) -> 0 | U67: =SUMIFS(Generation!P:P,Generation!$A:$A,Summary_CDP,Generation!$B:$B,IF($B$54="NEM","*",$B$54),Generation!$C:$C,$H67) -> 0 | V67: =SUMIFS(Generation!Q:Q,Generation!$A:$A,Summary_CDP,Generation!$B:$B,IF($B$54="NEM","*",$B$54),Generation!$C:$C,$H67) -> 0 | W67: =SUMIFS(Generation!R:R,Generation!$A:$A,Summary_CDP,Generation!$B:$B,IF($B$54="NEM","*",$B$54),Generation!$C:$C,$H67) -> 0 | X67: =SUMIFS(Generation!S:S,Generation!$A:$A,Summary_CDP,Generation!$B:$B,IF($B$54="NEM","*",$B$54),Generation!$C:$C,$H67) -> 0 | Y67: =SUMIFS(Generation!T:T,Generation!$A:$A,Summary_CDP,Generation!$B:$B,IF($B$54="NEM","*",$B$54),Generation!$C:$C,$H67) -> 0 | Z67: =SUMIFS(Generation!U:U,Generation!$A:$A,Summary_CDP,Generation!$B:$B,IF($B$54="NEM","*",$B$54),Generation!$C:$C,$H67) -> 0 | AA67: =SUMIFS(Generation!V:V,Generation!$A:$A,Summary_CDP,Generation!$B:$B,IF($B$54="NEM","*",$B$54),Generation!$C:$C,$H67) -> 0 | AB67: =SUMIFS(Generation!W:W,Generation!$A:$A,Summary_CDP,Generation!$B:$B,IF($B$54="NEM","*",$B$54),Generation!$C:$C,$H67) -> 0 | AC67: =SUMIFS(Generation!X:X,Generation!$A:$A,Summary_CDP,Generation!$B:$B,IF($B$54="NEM","*",$B$54),Generation!$C:$C,$H67) -> 0 | AD67: =SUMIFS(Generation!Y:Y,Generation!$A:$A,Summary_CDP,Generation!$B:$B,IF($B$54="NEM","*",$B$54),Generation!$C:$C,$H67) -> 0 | AE67: =SUMIFS(Generation!Z:Z,Generation!$A:$A,Summary_CDP,Generation!$B:$B,IF($B$54="NEM","*",$B$54),Generation!$C:$C,$H67) -> 0 | AF67: =SUMIFS(Generation!AA:AA,Generation!$A:$A,Summary_CDP,Generation!$B:$B,IF($B$54="NEM","*",$B$54),Generation!$C:$C,$H67) -> 0 | AG67: =SUMIFS(Generation!AB:AB,Generation!$A:$A,Summary_CDP,Generation!$B:$B,IF($B$54="NEM","*",$B$54),Generation!$C:$C,$H67) -> 0 | AH67: =SUMIFS(Generation!AC:AC,Generation!$A:$A,Summary_CDP,Generation!$B:$B,IF($B$54="NEM","*",$B$54),Generation!$C:$C,$H67) -> 0 | AI67: =SUMIFS(Generation!AD:AD,Generation!$A:$A,Summary_CDP,Generation!$B:$B,IF($B$54="NEM","*",$B$54),Generation!$C:$C,$H67) -> 0 | AJ67: =SUMIFS(Generation!AE:AE,Generation!$A:$A,Summary_CDP,Generation!$B:$B,IF($B$54="NEM","*",$B$54),Generation!$C:$C,$H67) -> 0
H68: Offshore Wind | I68: =SUMIFS(Generation!D:D,Generation!$A:$A,Summary_CDP,Generation!$B:$B,IF($B$54="NEM","*",$B$54),Generation!$C:$C,$H68) -> 0 | J68: =SUMIFS(Generation!E:E,Generation!$A:$A,Summary_CDP,Generation!$B:$B,IF($B$54="NEM","*",$B$54),Generation!$C:$C,$H68) -> 0 | K68: =SUMIFS(Generation!F:F,Generation!$A:$A,Summary_CDP,Generation!$B:$B,IF($B$54="NEM","*",$B$54),Generation!$C:$C,$H68) -> 0 | L68: =SUMIFS(Generation!G:G,Generation!$A:$A,Summary_CDP,Generation!$B:$B,IF($B$54="NEM","*",$B$54),Generation!$C:$C,$H68) -> 0 | M68: =SUMIFS(Generation!H:H,Generation!$A:$A,Summary_CDP,Generation!$B:$B,IF($B$54="NEM","*",$B$54),Generation!$C:$C,$H68) -> 0 | N68: =SUMIFS(Generation!I:I,Generation!$A:$A,Summary_CDP,Generation!$B:$B,IF($B$54="NEM","*",$B$54),Generation!$C:$C,$H68) -> 0 | O68: =SUMIFS(Generation!J:J,Generation!$A:$A,Summary_CDP,Generation!$B:$B,IF($B$54="NEM","*",$B$54),Generation!$C:$C,$H68) -> 0 | P68: =SUMIFS(Generation!K:K,Generation!$A:$A,Summary_CDP,Generation!$B:$B,IF($B$54="NEM","*",$B$54),Generation!$C:$C,$H68) -> 0 | Q68: =SUMIFS(Generation!L:L,Generation!$A:$A,Summary_CDP,Generation!$B:$B,IF($B$54="NEM","*",$B$54),Generation!$C:$C,$H68) -> 0 | R68: =SUMIFS(Generation!M:M,Generation!$A:$A,Summary_CDP,Generation!$B:$B,IF($B$54="NEM","*",$B$54),Generation!$C:$C,$H68) -> 0 | S68: =SUMIFS(Generation!N:N,Generation!$A:$A,Summary_CDP,Generation!$B:$B,IF($B$54="NEM","*",$B$54),Generation!$C:$C,$H68) -> 0 | T68: =SUMIFS(Generation!O:O,Generation!$A:$A,Summary_CDP,Generation!$B:$B,IF($B$54="NEM","*",$B$54),Generation!$C:$C,$H68) -> 0 | U68: =SUMIFS(Generation!P:P,Generation!$A:$A,Summary_CDP,Generation!$B:$B,IF($B$54="NEM","*",$B$54),Generation!$C:$C,$H68) -> 0 | V68: =SUMIFS(Generation!Q:Q,Generation!$A:$A,Summary_CDP,Generation!$B:$B,IF($B$54="NEM","*",$B$54),Generation!$C:$C,$H68) -> 0 | W68: =SUMIFS(Generation!R:R,Generation!$A:$A,Summary_CDP,Generation!$B:$B,IF($B$54="NEM","*",$B$54),Generation!$C:$C,$H68) -> 0 | X68: =SUMIFS(Generation!S:S,Generation!$A:$A,Summary_CDP,Generation!$B:$B,IF($B$54="NEM","*",$B$54),Generation!$C:$C,$H68) -> 0 | Y68: =SUMIFS(Generation!T:T,Generation!$A:$A,Summary_CDP,Generation!$B:$B,IF($B$54="NEM","*",$B$54),Generation!$C:$C,$H68) -> 0 | Z68: =SUMIFS(Generation!U:U,Generation!$A:$A,Summary_CDP,Generation!$B:$B,IF($B$54="NEM","*",$B$54),Generation!$C:$C,$H68) -> 0 | AA68: =SUMIFS(Generation!V:V,Generation!$A:$A,Summary_CDP,Generation!$B:$B,IF($B$54="NEM","*",$B$54),Generation!$C:$C,$H68) -> 0 | AB68: =SUMIFS(Generation!W:W,Generation!$A:$A,Summary_CDP,Generation!$B:$B,IF($B$54="NEM","*",$B$54),Generation!$C:$C,$H68) -> 0 | AC68: =SUMIFS(Generation!X:X,Generation!$A:$A,Summary_CDP,Generation!$B:$B,IF($B$54="NEM","*",$B$54),Generation!$C:$C,$H68) -> 0 | AD68: =SUMIFS(Generation!Y:Y,Generation!$A:$A,Summary_CDP,Generation!$B:$B,IF($B$54="NEM","*",$B$54),Generation!$C:$C,$H68) -> 0 | AE68: =SUMIFS(Generation!Z:Z,Generation!$A:$A,Summary_CDP,Generation!$B:$B,IF($B$54="NEM","*",$B$54),Generation!$C:$C,$H68) -> 0 | AF68: =SUMIFS(Generation!AA:AA,Generation!$A:$A,Summary_CDP,Generation!$B:$B,IF($B$54="NEM","*",$B$54),Generation!$C:$C,$H68) -> 0 | AG68: =SUMIFS(Generation!AB:AB,Generation!$A:$A,Summary_CDP,Generation!$B:$B,IF($B$54="NEM","*",$B$54),Generation!$C:$C,$H68) -> 0 | AH68: =SUMIFS(Generation!AC:AC,Generation!$A:$A,Summary_CDP,Generation!$B:$B,IF($B$54="NEM","*",$B$54),Generation!$C:$C,$H68) -> 0 | AI68: =SUMIFS(Generation!AD:AD,Generation!$A:$A,Summary_CDP,Generation!$B:$B,IF($B$54="NEM","*",$B$54),Generation!$C:$C,$H68) -> 0 | AJ68: =SUMIFS(Generation!AE:AE,Generation!$A:$A,Summary_CDP,Generation!$B:$B,IF($B$54="NEM","*",$B$54),Generation!$C:$C,$H68) -> 0
... H71: Distributed PV | I71: =SUMIFS(Generation!D:D,Generation!$A:$A,Summary_CDP,Generation!$B:$B,IF($B$54="NEM","*",$B$54),Generation!$C:$C,$H71) -> 27394.521 | J71: =SUMIFS(Generation!E:E,Generation!$A:$A,Summary_CDP,Generation!$B:$B,IF($B$54="NEM","*",$B$54),Generation!$C:$C,$H71) -> 31259.901 | K71: =SUMIFS(Generation!F:F,Generation!$A:$A,Summary_CDP,Generation!$B:$B,IF($B$54="NEM","*",$B$54),Generation!$C:$C,$H71) -> 35302.649 | L71: =SUMIFS(Generation!G:G,Generation!$A:$A,Summary_CDP,Generation!$B:$B,IF($B$54="NEM","*",$B$54),Generation!$C:$C,$H71) -> 39343.037 | M71: =SUMIFS(Generation!H:H,Generation!$A:$A,Summary_CDP,Generation!$B:$B,IF($B$54="NEM","*",$B$54),Generation!$C:$C,$H71) -> 43418.262 | N71: =SUMIFS(Generation!I:I,Generation!$A:$A,Summary_CDP,Generation!$B:$B,IF($B$54="NEM","*",$B$54),Generation!$C:$C,$H71) -> 47283.751 | O71: =SUMIFS(Generation!J:J,Generation!$A:$A,Summary_CDP,Generation!$B:$B,IF($B$54="NEM","*",$B$54),Generation!$C:$C,$H71) -> 51036.76 | P71: =SUMIFS(Generation!K:K,Generation!$A:$A,Summary_CDP,Generation!$B:$B,IF($B$54="NEM","*",$B$54),Generation!$C:$C,$H71) -> 54712.407 | Q71: =SUMIFS(Generation!L:L,Generation!$A:$A,Summary_CDP,Generation!$B:$B,IF($B$54="NEM","*",$B$54),Generation!$C:$C,$H71) -> 58294.878 | R71: =SUMIFS(Generation!M:M,Generation!$A:$A,Summary_CDP,Generation!$B:$B,IF($B$54="NEM","*",$B$54),Generation!$C:$C,$H71) -> 61592.358 | S71: =SUMIFS(Generation!N:N,Generation!$A:$A,Summary_CDP,Generation!$B:$B,IF($B$54="NEM","*",$B$54),Generation!$C:$C,$H71) -> 64893.298 | T71: =SUMIFS(Generation!O:O,Generation!$A:$A,Summary_CDP,Generation!$B:$B,IF($B$54="NEM","*",$B$54),Generation!$C:$C,$H71) -> 68225.264 | U71: =SUMIFS(Generation!P:P,Generation!$A:$A,Summary_CDP,Generation!$B:$B,IF($B$54="NEM","*",$B$54),Generation!$C:$C,$H71) -> 71597.534 | V71: =SUMIFS(Generation!Q:Q,Generation!$A:$A,Summary_CDP,Generation!$B:$B,IF($B$54="NEM","*",$B$54),Generation!$C:$C,$H71) -> 74554.741 | W71: =SUMIFS(Generation!R:R,Generation!$A:$A,Summary_CDP,Generation!$B:$B,IF($B$54="NEM","*",$B$54),Generation!$C:$C,$H71) -> 77387.35 | X71: =SUMIFS(Generation!S:S,Generation!$A:$A,Summary_CDP,Generation!$B:$B,IF($B$54="NEM","*",$B$54),Generation!$C:$C,$H71) -> 80232.793 | Y71: =SUMIFS(Generation!T:T,Generation!$A:$A,Summary_CDP,Generation!$B:$B,IF($B$54="NEM","*",$B$54),Generation!$C:$C,$H71) -> 83314.882 | Z71: =SUMIFS(Generation!U:U,Generation!$A:$A,Summary_CDP,Generation!$B:$B,IF($B$54="NEM","*",$B$54),Generation!$C:$C,$H71) -> 86124.175 | AA71: =SUMIFS(Generation!V:V,Generation!$A:$A,Summary_CDP,Generation!$B:$B,IF($B$54="NEM","*",$B$54),Generation!$C:$C,$H71) -> 88984.135 | AB71: =SUMIFS(Generation!W:W,Generation!$A:$A,Summary_CDP,Generation!$B:$B,IF($B$54="NEM","*",$B$54),Generation!$C:$C,$H71) -> 91895.467 | AC71: =SUMIFS(Generation!X:X,Generation!$A:$A,Summary_CDP,Generation!$B:$B,IF($B$54="NEM","*",$B$54),Generation!$C:$C,$H71) -> 95009.064 | AD71: =SUMIFS(Generation!Y:Y,Generation!$A:$A,Summary_CDP,Generation!$B:$B,IF($B$54="NEM","*",$B$54),Generation!$C:$C,$H71) -> 97753.277 | AE71: =SUMIFS(Generation!Z:Z,Generation!$A:$A,Summary_CDP,Generation!$B:$B,IF($B$54="NEM","*",$B$54),Generation!$C:$C,$H71) -> 100531.88 | AF71: =SUMIFS(Generation!AA:AA,Generation!$A:$A,Summary_CDP,Generation!$B:$B,IF($B$54="NEM","*",$B$54),Generation!$C:$C,$H71) -> 103357.29 | AG71: =SUMIFS(Generation!AB:AB,Generation!$A:$A,Summary_CDP,Generation!$B:$B,IF($B$54="NEM","*",$B$54),Generation!$C:$C,$H71) -> 106407.2 | AH71: =SUMIFS(Generation!AC:AC,Generation!$A:$A,Summary_CDP,Generation!$B:$B,IF($B$54="NEM","*",$B$54),Generation!$C:$C,$H71) -> 109033.34 | AI71: =SUMIFS(Generation!AD:AD,Generation!$A:$A,Summary_CDP,Generation!$B:$B,IF($B$54="NEM","*",$B$54),Generation!$C:$C,$H71) -> 111724.66 | AJ71: =SUMIFS(Generation!AE:AE,Generation!$A:$A,Summary_CDP,Generation!$B:$B,IF($B$54="NEM","*",$B$54),Generation!$C:$C,$H71) -> 111724.66
H72: Storage Charging (GWh)
H73: Utility-scale Storage Load | I73: =SUMIFS(Generation!D:D,Generation!$A:$A,Summary_CDP,Generation!$B:$B,IF($B$54="NEM","*",$B$54),Generation!$C:$C,$H73) -> -2192.379 | J73: =SUMIFS(Generation!E:E,Generation!$A:$A,Summary_CDP,Generation!$B:$B,IF($B$54="NEM","*",$B$54),Generation!$C:$C,$H73) -> -3879.3632 | K73: =SUMIFS(Generation!F:F,Generation!$A:$A,Summary_CDP,Generation!$B:$B,IF($B$54="NEM","*",$B$54),Generation!$C:$C,$H73) -> -6952.3111 | L73: =SUMIFS(Generation!G:G,Generation!$A:$A,Summary_CDP,Generation!$B:$B,IF($B$54="NEM","*",$B$54),Generation!$C:$C,$H73) -> -11578.54 | M73: =SUMIFS(Generation!H:H,Generation!$A:$A,Summary_CDP,Generation!$B:$B,IF($B$54="NEM","*",$B$54),Generation!$C:$C,$H73) -> -18727.364 | N73: =SUMIFS(Generation!I:I,Generation!$A:$A,Summary_CDP,Generation!$B:$B,IF($B$54="NEM","*",$B$54),Generation!$C:$C,$H73) -> -28974.781 | O73: =SUMIFS(Generation!J:J,Generation!$A:$A,Summary_CDP,Generation!$B:$B,IF($B$54="NEM","*",$B$54),Generation!$C:$C,$H73) -> -28628.779 | P73: =SUMIFS(Generation!K:K,Generation!$A:$A,Summary_CDP,Generation!$B:$B,IF($B$54="NEM","*",$B$54),Generation!$C:$C,$H73) -> -34205.829 | Q73: =SUMIFS(Generation!L:L,Generation!$A:$A,Summary_CDP,Generation!$B:$B,IF($B$54="NEM","*",$B$54),Generation!$C:$C,$H73) -> -31931.802 | R73: =SUMIFS(Generation!M:M,Generation!$A:$A,Summary_CDP,Generation!$B:$B,IF($B$54="NEM","*",$B$54),Generation!$C:$C,$H73) -> -31270.164 | S73: =SUMIFS(Generation!N:N,Generation!$A:$A,Summary_CDP,Generation!$B:$B,IF($B$54="NEM","*",$B$54),Generation!$C:$C,$H73) -> -31207.757 | T73: =SUMIFS(Generation!O:O,Generation!$A:$A,Summary_CDP,Generation!$B:$B,IF($B$54="NEM","*",$B$54),Generation!$C:$C,$H73) -> -31180.836 | U73: =SUMIFS(Generation!P:P,Generation!$A:$A,Summary_CDP,Generation!$B:$B,IF($B$54="NEM","*",$B$54),Generation!$C:$C,$H73) -> -37752.334 | V73: =SUMIFS(Generation!Q:Q,Generation!$A:$A,Summary_CDP,Generation!$B:$B,IF($B$54="NEM","*",$B$54),Generation!$C:$C,$H73) -> -38027.361 | W73: =SUMIFS(Generation!R:R,Generation!$A:$A,Summary_CDP,Generation!$B:$B,IF($B$54="NEM","*",$B$54),Generation!$C:$C,$H73) -> -42795.965 | X73: =SUMIFS(Generation!S:S,Generation!$A:$A,Summary_CDP,Generation!$B:$B,IF($B$54="NEM","*",$B$54),Generation!$C:$C,$H73) -> -40294.502 | Y73: =SUMIFS(Generation!T:T,Generation!$A:$A,Summary_CDP,Generation!$B:$B,IF($B$54="NEM","*",$B$54),Generation!$C:$C,$H73) -> -43640.316 | Z73: =SUMIFS(Generation!U:U,Generation!$A:$A,Summary_CDP,Generation!$B:$B,IF($B$54="NEM","*",$B$54),Generation!$C:$C,$H73) -> -46100.952 | AA73: =SUMIFS(Generation!V:V,Generation!$A:$A,Summary_CDP,Generation!$B:$B,IF($B$54="NEM","*",$B$54),Generation!$C:$C,$H73) -> -63717.798 | AB73: =SUMIFS(Generation!W:W,Generation!$A:$A,Summary_CDP,Generation!$B:$B,IF($B$54="NEM","*",$B$54),Generation!$C:$C,$H73) -> -60227.747 | AC73: =SUMIFS(Generation!X:X,Generation!$A:$A,Summary_CDP,Generation!$B:$B,IF($B$54="NEM","*",$B$54),Generation!$C:$C,$H73) -> -54157.153 | AD73: =SUMIFS(Generation!Y:Y,Generation!$A:$A,Summary_CDP,Generation!$B:$B,IF($B$54="NEM","*",$B$54),Generation!$C:$C,$H73) -> -61542.858 | AE73: =SUMIFS(Generation!Z:Z,Generation!$A:$A,Summary_CDP,Generation!$B:$B,IF($B$54="NEM","*",$B$54),Generation!$C:$C,$H73) -> -74245.886 | AF73: =SUMIFS(Generation!AA:AA,Generation!$A:$A,Summary_CDP,Generation!$B:$B,IF($B$54="NEM","*",$B$54),Generation!$C:$C,$H73) -> -77163.585 | AG73: =SUMIFS(Generation!AB:AB,Generation!$A:$A,Summary_CDP,Generation!$B:$B,IF($B$54="NEM","*",$B$54),Generation!$C:$C,$H73) -> -74166.532 | AH73: =SUMIFS(Generation!AC:AC,Generation!$A:$A,Summary_CDP,Generation!$B:$B,IF($B$54="NEM","*",$B$54),Generation!$C:$C,$H73) -> -96373.707 | AI73: =SUMIFS(Generation!AD:AD,Generation!$A:$A,Summary_CDP,Generation!$B:$B,IF($B$54="NEM","*",$B$54),Generation!$C:$C,$H73) -> -137657.48 | AJ73: =SUMIFS(Generation!AE:AE,Generation!$A:$A,Summary_CDP,Generation!$B:$B,IF($B$54="NEM","*",$B$54),Generation!$C:$C,$H73) -> -137879.75
H74: Coordinated DER Storage Load | I74: =SUMIFS(Generation!D:D,Generation!$A:$A,Summary_CDP,Generation!$B:$B,IF($B$54="NEM","*",$B$54),Generation!$C:$C,$H74) -> -214.72553 | J74: =SUMIFS(Generation!E:E,Generation!$A:$A,Summary_CDP,Generation!$B:$B,IF($B$54="NEM","*",$B$54),Generation!$C:$C,$H74) -> -555.8986 | K74: =SUMIFS(Generation!F:F,Generation!$A:$A,Summary_CDP,Generation!$B:$B,IF($B$54="NEM","*",$B$54),Generation!$C:$C,$H74) -> -947.17831 | L74: =SUMIFS(Generation!G:G,Generation!$A:$A,Summary_CDP,Generation!$B:$B,IF($B$54="NEM","*",$B$54),Generation!$C:$C,$H74) -> -1404.7106 | M74: =SUMIFS(Generation!H:H,Generation!$A:$A,Summary_CDP,Generation!$B:$B,IF($B$54="NEM","*",$B$54),Generation!$C:$C,$H74) -> -2000.5392 | N74: =SUMIFS(Generation!I:I,Generation!$A:$A,Summary_CDP,Generation!$B:$B,IF($B$54="NEM","*",$B$54),Generation!$C:$C,$H74) -> -2600.0459 | O74: =SUMIFS(Generation!J:J,Generation!$A:$A,Summary_CDP,Generation!$B:$B,IF($B$54="NEM","*",$B$54),Generation!$C:$C,$H74) -> -3526.664 | P74: =SUMIFS(Generation!K:K,Generation!$A:$A,Summary_CDP,Generation!$B:$B,IF($B$54="NEM","*",$B$54),Generation!$C:$C,$H74) -> -4386.859 | Q74: =SUMIFS(Generation!L:L,Generation!$A:$A,Summary_CDP,Generation!$B:$B,IF($B$54="NEM","*",$B$54),Generation!$C:$C,$H74) -> -5421.1989 | R74: =SUMIFS(Generation!M:M,Generation!$A:$A,Summary_CDP,Generation!$B:$B,IF($B$54="NEM","*",$B$54),Generation!$C:$C,$H74) -> -6170.153 | S74: =SUMIFS(Generation!N:N,Generation!$A:$A,Summary_CDP,Generation!$B:$B,IF($B$54="NEM","*",$B$54),Generation!$C:$C,$H74) -> -7920.4012 | T74: =SUMIFS(Generation!O:O,Generation!$A:$A,Summary_CDP,Generation!$B:$B,IF($B$54="NEM","*",$B$54),Generation!$C:$C,$H74) -> -9604.9559 | U74: =SUMIFS(Generation!P:P,Generation!$A:$A,Summary_CDP,Generation!$B:$B,IF($B$54="NEM","*",$B$54),Generation!$C:$C,$H74) -> -11901.968 | V74: =SUMIFS(Generation!Q:Q,Generation!$A:$A,Summary_CDP,Generation!$B:$B,IF($B$54="NEM","*",$B$54),Generation!$C:$C,$H74) -> -13892.392 | W74: =SUMIFS(Generation!R:R,Generation!$A:$A,Summary_CDP,Generation!$B:$B,IF($B$54="NEM","*",$B$54),Generation!$C:$C,$H74) -> -16515.466 | X74: =SUMIFS(Generation!S:S,Generation!$A:$A,Summary_CDP,Generation!$B:$B,IF($B$54="NEM","*",$B$54),Generation!$C:$C,$H74) -> -17843.539 | Y74: =SUMIFS(Generation!T:T,Generation!$A:$A,Summary_CDP,Generation!$B:$B,IF($B$54="NEM","*",$B$54),Generation!$C:$C,$H74) -> -20771.841 | Z74: =SUMIFS(Generation!U:U,Generation!$A:$A,Summary_CDP,Generation!$B:$B,IF($B$54="NEM","*",$B$54),Generation!$C:$C,$H74) -> -23011.66 | AA74: =SUMIFS(Generation!V:V,Generation!$A:$A,Summary_CDP,Generation!$B:$B,IF($B$54="NEM","*",$B$54),Generation!$C:$C,$H74) -> -24529.835 | AB74: =SUMIFS(Generation!W:W,Generation!$A:$A,Summary_CDP,Generation!$B:$B,IF($B$54="NEM","*",$B$54),Generation!$C:$C,$H74) -> -26636.672 | AC74: =SUMIFS(Generation!X:X,Generation!$A:$A,Summary_CDP,Generation!$B:$B,IF($B$54="NEM","*",$B$54),Generation!$C:$C,$H74) -> -26489.669 | AD74: =SUMIFS(Generation!Y:Y,Generation!$A:$A,Summary_CDP,Generation!$B:$B,IF($B$54="NEM","*",$B$54),Generation!$C:$C,$H74) -> -30382.597 | AE74: =SUMIFS(Generation!Z:Z,Generation!$A:$A,Summary_CDP,Generation!$B:$B,IF($B$54="NEM","*",$B$54),Generation!$C:$C,$H74) -> -33509.735 | AF74: =SUMIFS(Generation!AA:AA,Generation!$A:$A,Summary_CDP,Generation!$B:$B,IF($B$54="NEM","*",$B$54),Generation!$C:$C,$H74) -> -34523.791 | AG74: =SUMIFS(Generation!AB:AB,Generation!$A:$A,Summary_CDP,Generation!$B:$B,IF($B$54="NEM","*",$B$54),Generation!$C:$C,$H74) -> -35117.151 | AH74: =SUMIFS(Generation!AC:AC,Generation!$A:$A,Summary_CDP,Generation!$B:$B,IF($B$54="NEM","*",$B$54),Generation!$C:$C,$H74) -> -37656.956 | AI74: =SUMIFS(Generation!AD:AD,Generation!$A:$A,Summary_CDP,Generation!$B:$B,IF($B$54="NEM","*",$B$54),Generation!$C:$C,$H74) -> -40213.117 | AJ74: =SUMIFS(Generation!AE:AE,Generation!$A:$A,Summary_CDP,Generation!$B:$B,IF($B$54="NEM","*",$B$54),Generation!$C:$C,$H74) -> -43020.871
H75: Distributed Storage Load | I75: =SUMIFS(Generation!D:D,Generation!$A:$A,Summary_CDP,Generation!$B:$B,IF($B$54="NEM","*",$B$54),Generation!$C:$C,$H75) -> -486.52982 | J75: =SUMIFS(Generation!E:E,Generation!$A:$A,Summary_CDP,Generation!$B:$B,IF($B$54="NEM","*",$B$54),Generation!$C:$C,$H75) -> -848.60531 | K75: =SUMIFS(Generation!F:F,Generation!$A:$A,Summary_CDP,Generation!$B:$B,IF($B$54="NEM","*",$B$54),Generation!$C:$C,$H75) -> -1198.2947 | L75: =SUMIFS(Generation!G:G,Generation!$A:$A,Summary_CDP,Generation!$B:$B,IF($B$54="NEM","*",$B$54),Generation!$C:$C,$H75) -> -1503.5803 | M75: =SUMIFS(Generation!H:H,Generation!$A:$A,Summary_CDP,Generation!$B:$B,IF($B$54="NEM","*",$B$54),Generation!$C:$C,$H75) -> -1758.3265 | N75: =SUMIFS(Generation!I:I,Generation!$A:$A,Summary_CDP,Generation!$B:$B,IF($B$54="NEM","*",$B$54),Generation!$C:$C,$H75) -> -1975.0765 | O75: =SUMIFS(Generation!J:J,Generation!$A:$A,Summary_CDP,Generation!$B:$B,IF($B$54="NEM","*",$B$54),Generation!$C:$C,$H75) -> -2251.4056 | P75: =SUMIFS(Generation!K:K,Generation!$A:$A,Summary_CDP,Generation!$B:$B,IF($B$54="NEM","*",$B$54),Generation!$C:$C,$H75) -> -2680.6513 | Q75: =SUMIFS(Generation!L:L,Generation!$A:$A,Summary_CDP,Generation!$B:$B,IF($B$54="NEM","*",$B$54),Generation!$C:$C,$H75) -> -3090.7231 | R75: =SUMIFS(Generation!M:M,Generation!$A:$A,Summary_CDP,Generation!$B:$B,IF($B$54="NEM","*",$B$54),Generation!$C:$C,$H75) -> -3480.7459 | S75: =SUMIFS(Generation!N:N,Generation!$A:$A,Summary_CDP,Generation!$B:$B,IF($B$54="NEM","*",$B$54),Generation!$C:$C,$H75) -> -3963.8461 | T75: =SUMIFS(Generation!O:O,Generation!$A:$A,Summary_CDP,Generation!$B:$B,IF($B$54="NEM","*",$B$54),Generation!$C:$C,$H75) -> -4478.9259 | U75: =SUMIFS(Generation!P:P,Generation!$A:$A,Summary_CDP,Generation!$B:$B,IF($B$54="NEM","*",$B$54),Generation!$C:$C,$H75) -> -5013.2032 | V75: =SUMIFS(Generation!Q:Q,Generation!$A:$A,Summary_CDP,Generation!$B:$B,IF($B$54="NEM","*",$B$54),Generation!$C:$C,$H75) -> -5451.3727 | W75: =SUMIFS(Generation!R:R,Generation!$A:$A,Summary_CDP,Generation!$B:$B,IF($B$54="NEM","*",$B$54),Generation!$C:$C,$H75) -> -5853.028 | X75: =SUMIFS(Generation!S:S,Generation!$A:$A,Summary_CDP,Generation!$B:$B,IF($B$54="NEM","*",$B$54),Generation!$C:$C,$H75) -> -6159.5038 | Y75: =SUMIFS(Generation!T:T,Generation!$A:$A,Summary_CDP,Generation!$B:$B,IF($B$54="NEM","*",$B$54),Generation!$C:$C,$H75) -> -6397.3789 | Z75: =SUMIFS(Generation!U:U,Generation!$A:$A,Summary_CDP,Generation!$B:$B,IF($B$54="NEM","*",$B$54),Generation!$C:$C,$H75) -> -6494.9302 | AA75: =SUMIFS(Generation!V:V,Generation!$A:$A,Summary_CDP,Generation!$B:$B,IF($B$54="NEM","*",$B$54),Generation!$C:$C,$H75) -> -6536.2788 | AB75: =SUMIFS(Generation!W:W,Generation!$A:$A,Summary_CDP,Generation!$B:$B,IF($B$54="NEM","*",$B$54),Generation!$C:$C,$H75) -> -6532.9186 | AC75: =SUMIFS(Generation!X:X,Generation!$A:$A,Summary_CDP,Generation!$B:$B,IF($B$54="NEM","*",$B$54),Generation!$C:$C,$H75) -> -6498.7137 | AD75: =SUMIFS(Generation!Y:Y,Generation!$A:$A,Summary_CDP,Generation!$B:$B,IF($B$54="NEM","*",$B$54),Generation!$C:$C,$H75) -> -6455.8472 | AE75: =SUMIFS(Generation!Z:Z,Generation!$A:$A,Summary_CDP,Generation!$B:$B,IF($B$54="NEM","*",$B$54),Generation!$C:$C,$H75) -> -6410.1943 | AF75: =SUMIFS(Generation!AA:AA,Generation!$A:$A,Summary_CDP,Generation!$B:$B,IF($B$54="NEM","*",$B$54),Generation!$C:$C,$H75) -> -6404.9426 | AG75: =SUMIFS(Generation!AB:AB,Generation!$A:$A,Summary_CDP,Generation!$B:$B,IF($B$54="NEM","*",$B$54),Generation!$C:$C,$H75) -> -6342.8662 | AH75: =SUMIFS(Generation!AC:AC,Generation!$A:$A,Summary_CDP,Generation!$B:$B,IF($B$54="NEM","*",$B$54),Generation!$C:$C,$H75) -> -6264.8533 | AI75: =SUMIFS(Generation!AD:AD,Generation!$A:$A,Summary_CDP,Generation!$B:$B,IF($B$54="NEM","*",$B$54),Generation!$C:$C,$H75) -> -6181.6223 | AJ75: =SUMIFS(Generation!AE:AE,Generation!$A:$A,Summary_CDP,Generation!$B:$B,IF($B$54="NEM","*",$B$54),Generation!$C:$C,$H75) -> -6247.8695
H77: DSP | I77: =SUMIFS(Generation!D:D,Generation!$A:$A,Summary_CDP,Generation!$B:$B,IF($B$54="NEM","*",$B$54),Generation!$C:$C,$H77) -> 0 | J77: =SUMIFS(Generation!E:E,Generation!$A:$A,Summary_CDP,Generation!$B:$B,IF($B$54="NEM","*",$B$54),Generation!$C:$C,$H77) -> 0 | K77: =SUMIFS(Generation!F:F,Generation!$A:$A,Summary_CDP,Generation!$B:$B,IF($B$54="NEM","*",$B$54),Generation!$C:$C,$H77) -> 0.0255805 | L77: =SUMIFS(Generation!G:G,Generation!$A:$A,Summary_CDP,Generation!$B:$B,IF($B$54="NEM","*",$B$54),Generation!$C:$C,$H77) -> 2.9453874 | M77: =SUMIFS(Generation!H:H,Generation!$A:$A,Summary_CDP,Generation!$B:$B,IF($B$54="NEM","*",$B$54),Generation!$C:$C,$H77) -> 3.063366 | N77: =SUMIFS(Generation!I:I,Generation!$A:$A,Summary_CDP,Generation!$B:$B,IF($B$54="NEM","*",$B$54),Generation!$C:$C,$H77) -> 20.713244 | O77: =SUMIFS(Generation!J:J,Generation!$A:$A,Summary_CDP,Generation!$B:$B,IF($B$54="NEM","*",$B$54),Generation!$C:$C,$H77) -> 0 | P77: =SUMIFS(Generation!K:K,Generation!$A:$A,Summary_CDP,Generation!$B:$B,IF($B$54="NEM","*",$B$54),Generation!$C:$C,$H77) -> 77.497508 | Q77: =SUMIFS(Generation!L:L,Generation!$A:$A,Summary_CDP,Generation!$B:$B,IF($B$54="NEM","*",$B$54),Generation!$C:$C,$H77) -> 95.850165 | R77: =SUMIFS(Generation!M:M,Generation!$A:$A,Summary_CDP,Generation!$B:$B,IF($B$54="NEM","*",$B$54),Generation!$C:$C,$H77) -> 133.5967 | S77: =SUMIFS(Generation!N:N,Generation!$A:$A,Summary_CDP,Generation!$B:$B,IF($B$54="NEM","*",$B$54),Generation!$C:$C,$H77) -> 17.855734 | T77: =SUMIFS(Generation!O:O,Generation!$A:$A,Summary_CDP,Generation!$B:$B,IF($B$54="NEM","*",$B$54),Generation!$C:$C,$H77) -> 482.80791 | U77: =SUMIFS(Generation!P:P,Generation!$A:$A,Summary_CDP,Generation!$B:$B,IF($B$54="NEM","*",$B$54),Generation!$C:$C,$H77) -> 320.70199 | V77: =SUMIFS(Generation!Q:Q,Generation!$A:$A,Summary_CDP,Generation!$B:$B,IF($B$54="NEM","*",$B$54),Generation!$C:$C,$H77) -> 551.03142 | W77: =SUMIFS(Generation!R:R,Generation!$A:$A,Summary_CDP,Generation!$B:$B,IF($B$54="NEM","*",$B$54),Generation!$C:$C,$H77) -> 397.58745 | X77: =SUMIFS(Generation!S:S,Generation!$A:$A,Summary_CDP,Generation!$B:$B,IF($B$54="NEM","*",$B$54),Generation!$C:$C,$H77) -> 1847.0568 | Y77: =SUMIFS(Generation!T:T,Generation!$A:$A,Summary_CDP,Generation!$B:$B,IF($B$54="NEM","*",$B$54),Generation!$C:$C,$H77) -> 870.457 | Z77: =SUMIFS(Generation!U:U,Generation!$A:$A,Summary_CDP,Generation!$B:$B,IF($B$54="NEM","*",$B$54),Generation!$C:$C,$H77) -> 1689.3247 | AA77: =SUMIFS(Generation!V:V,Generation!$A:$A,Summary_CDP,Generation!$B:$B,IF($B$54="NEM","*",$B$54),Generation!$C:$C,$H77) -> 2008.628 | AB77: =SUMIFS(Generation!W:W,Generation!$A:$A,Summary_CDP,Generation!$B:$B,IF($B$54="NEM","*",$B$54),Generation!$C:$C,$H77) -> 1998.7673 | AC77: =SUMIFS(Generation!X:X,Generation!$A:$A,Summary_CDP,Generation!$B:$B,IF($B$54="NEM","*",$B$54),Generation!$C:$C,$H77) -> 2219.1056 | AD77: =SUMIFS(Generation!Y:Y,Generation!$A:$A,Summary_CDP,Generation!$B:$B,IF($B$54="NEM","*",$B$54),Generation!$C:$C,$H77) -> 2382.7933 | AE77: =SUMIFS(Generation!Z:Z,Generation!$A:$A,Summary_CDP,Generation!$B:$B,IF($B$54="NEM","*",$B$54),Generation!$C:$C,$H77) -> 2363.5309 | AF77: =SUMIFS(Generation!AA:AA,Generation!$A:$A,Summary_CDP,Generation!$B:$B,IF($B$54="NEM","*",$B$54),Generation!$C:$C,$H77) -> 3196.593 | AG77: =SUMIFS(Generation!AB:AB,Generation!$A:$A,Summary_CDP,Generation!$B:$B,IF($B$54="NEM","*",$B$54),Generation!$C:$C,$H77) -> 1638.037 | AH77: =SUMIFS(Generation!AC:AC,Generation!$A:$A,Summary_CDP,Generation!$B:$B,IF($B$54="NEM","*",$B$54),Generation!$C:$C,$H77) -> 2443.9071 | AI77: =SUMIFS(Generation!AD:AD,Generation!$A:$A,Summary_CDP,Generation!$B:$B,IF($B$54="NEM","*",$B$54),Generation!$C:$C,$H77) -> 3651.4333 | AJ77: =SUMIFS(Generation!AE:AE,Generation!$A:$A,Summary_CDP,Generation!$B:$B,IF($B$54="NEM","*",$B$54),Generation!$C:$C,$H77) -> 1149.7463
A81: =B82&" generation by technology type" -> NEM generation by technology type
A82: Select region | B82: NEM
H84: As-generated generation (GWh) | I84: 2023-24 | J84: 2030-31 | K84: 2040-41 | L84: 2050-51
H85: Black Coal | I85: =SUMIFS(Generation!D:D,Generation!$A:$A,Summary_CDP,Generation!$B:$B,IF($B$82="NEM","*",$B$82),Generation!$C:$C,$H85) -> 77553.079 | J85: =SUMIFS(Generation!K:K,Generation!$A:$A,Summary_CDP,Generation!$B:$B,IF($B$82="NEM","*",$B$82),Generation!$C:$C,$H85) -> 0 | K85: =SUMIFS(Generation!U:U,Generation!$A:$A,Summary_CDP,Generation!$B:$B,IF($B$82="NEM","*",$B$82),Generation!$C:$C,$H85) -> 0 | L85: =SUMIFS(Generation!AE:AE,Generation!$A:$A,Summary_CDP,Generation!$B:$B,IF($B$82="NEM","*",$B$82),Generation!$C:$C,$H85) -> 0
H86: Brown Coal | I86: =SUMIFS(Generation!D:D,Generation!$A:$A,Summary_CDP,Generation!$B:$B,IF($B$82="NEM","*",$B$82),Generation!$C:$C,$H86) -> 31199.076 | J86: =SUMIFS(Generation!K:K,Generation!$A:$A,Summary_CDP,Generation!$B:$B,IF($B$82="NEM","*",$B$82),Generation!$C:$C,$H86) -> 0 | K86: =SUMIFS(Generation!U:U,Generation!$A:$A,Summary_CDP,Generation!$B:$B,IF($B$82="NEM","*",$B$82),Generation!$C:$C,$H86) -> 0 | L86: =SUMIFS(Generation!AE:AE,Generation!$A:$A,Summary_CDP,Generation!$B:$B,IF($B$82="NEM","*",$B$82),Generation!$C:$C,$H86) -> 0
H87: Mid-merit Gas | I87: =SUMIFS(Generation!D:D,Generation!$A:$A,Summary_CDP,Generation!$B:$B,IF($B$82="NEM","*",$B$82),Generation!$C:$C,$H87) -> 8716.0503 | J87: =SUMIFS(Generation!K:K,Generation!$A:$A,Summary_CDP,Generation!$B:$B,IF($B$82="NEM","*",$B$82),Generation!$C:$C,$H87) -> 5097.5172 | K87: =SUMIFS(Generation!U:U,Generation!$A:$A,Summary_CDP,Generation!$B:$B,IF($B$82="NEM","*",$B$82),Generation!$C:$C,$H87) -> 2407.4759 | L87: =SUMIFS(Generation!AE:AE,Generation!$A:$A,Summary_CDP,Generation!$B:$B,IF($B$82="NEM","*",$B$82),Generation!$C:$C,$H87) -> 0
H88: Mid-merit Gas with CCS | I88: =SUMIFS(Generation!D:D,Generation!$A:$A,Summary_CDP,Generation!$B:$B,IF($B$82="NEM","*",$B$82),Generation!$C:$C,$H88) -> 0 | J88: =SUMIFS(Generation!K:K,Generation!$A:$A,Summary_CDP,Generation!$B:$B,IF($B$82="NEM","*",$B$82),Generation!$C:$C,$H88) -> 0 | K88: =SUMIFS(Generation!U:U,Generation!$A:$A,Summary_CDP,Generation!$B:$B,IF($B$82="NEM","*",$B$82),Generation!$C:$C,$H88) -> 0 | L88: =SUMIFS(Generation!AE:AE,Generation!$A:$A,Summary_CDP,Generation!$B:$B,IF($B$82="NEM","*",$B$82),Generation!$C:$C,$H88) -> 0
H89: Peaking Gas+Liquids | I89: =SUMIFS(Generation!D:D,Generation!$A:$A,Summary_CDP,Generation!$B:$B,IF($B$82="NEM","*",$B$82),Generation!$C:$C,$H89) -> 471.31127 | J89: =SUMIFS(Generation!K:K,Generation!$A:$A,Summary_CDP,Generation!$B:$B,IF($B$82="NEM","*",$B$82),Generation!$C:$C,$H89) -> 2348.422 | K89: =SUMIFS(Generation!U:U,Generation!$A:$A,Summary_CDP,Generation!$B:$B,IF($B$82="NEM","*",$B$82),Generation!$C:$C,$H89) -> 1509.1851 | L89: =SUMIFS(Generation!AE:AE,Generation!$A:$A,Summary_CDP,Generation!$B:$B,IF($B$82="NEM","*",$B$82),Generation!$C:$C,$H89) -> 4.6565712
H90: Hydrogen Turbine | I90: =SUMIFS(Generation!D:D,Generation!$A:$A,Summary_CDP,Generation!$B:$B,IF($B$82="NEM","*",$B$82),Generation!$C:$C,$H90) -> 0 | J90: =SUMIFS(Generation!K:K,Generation!$A:$A,Summary_CDP,Generation!$B:$B,IF($B$82="NEM","*",$B$82),Generation!$C:$C,$H90) -> 0 | K90: =SUMIFS(Generation!U:U,Generation!$A:$A,Summary_CDP,Generation!$B:$B,IF($B$82="NEM","*",$B$82),Generation!$C:$C,$H90) -> 0 | L90: =SUMIFS(Generation!AE:AE,Generation!$A:$A,Summary_CDP,Generation!$B:$B,IF($B$82="NEM","*",$B$82),Generation!$C:$C,$H90) -> 1508.9294
H91: Hydro | I91: =SUMIFS(Generation!D:D,Generation!$A:$A,Summary_CDP,Generation!$B:$B,IF($B$82="NEM","*",$B$82),Generation!$C:$C,$H91) -> 15034.845 | J91: =SUMIFS(Generation!K:K,Generation!$A:$A,Summary_CDP,Generation!$B:$B,IF($B$82="NEM","*",$B$82),Generation!$C:$C,$H91) -> 15324.98 | K91: =SUMIFS(Generation!U:U,Generation!$A:$A,Summary_CDP,Generation!$B:$B,IF($B$82="NEM","*",$B$82),Generation!$C:$C,$H91) -> 12522.101 | L91: =SUMIFS(Generation!AE:AE,Generation!$A:$A,Summary_CDP,Generation!$B:$B,IF($B$82="NEM","*",$B$82),Generation!$C:$C,$H91) -> 6652.0833
H92: Utility-scale Storage | I92: =SUMIFS(Generation!D:D,Generation!$A:$A,Summary_CDP,Generation!$B:$B,IF($B$82="NEM","*",$B$82),Generation!$C:$C,$H92) -> 1059.6369 | J92: =SUMIFS(Generation!K:K,Generation!$A:$A,Summary_CDP,Generation!$B:$B,IF($B$82="NEM","*",$B$82),Generation!$C:$C,$H92) -> 26369.247 | K92: =SUMIFS(Generation!U:U,Generation!$A:$A,Summary_CDP,Generation!$B:$B,IF($B$82="NEM","*",$B$82),Generation!$C:$C,$H92) -> 36101.53 | L92: =SUMIFS(Generation!AE:AE,Generation!$A:$A,Summary_CDP,Generation!$B:$B,IF($B$82="NEM","*",$B$82),Generation!$C:$C,$H92) -> 111193.39
H93: Coordinated DER Storage | I93: =SUMIFS(Generation!D:D,Generation!$A:$A,Summary_CDP,Generation!$B:$B,IF($B$82="NEM","*",$B$82),Generation!$C:$C,$H93) -> 182.53473 | J93: =SUMIFS(Generation!K:K,Generation!$A:$A,Summary_CDP,Generation!$B:$B,IF($B$82="NEM","*",$B$82),Generation!$C:$C,$H93) -> 3691.3573 | K93: =SUMIFS(Generation!U:U,Generation!$A:$A,Summary_CDP,Generation!$B:$B,IF($B$82="NEM","*",$B$82),Generation!$C:$C,$H93) -> 18350.516 | L93: =SUMIFS(Generation!AE:AE,Generation!$A:$A,Summary_CDP,Generation!$B:$B,IF($B$82="NEM","*",$B$82),Generation!$C:$C,$H93) -> 33516.186
H94: Distributed Storage | I94: =SUMIFS(Generation!D:D,Generation!$A:$A,Summary_CDP,Generation!$B:$B,IF($B$82="NEM","*",$B$82),Generation!$C:$C,$H94) -> 414.76654 | J94: =SUMIFS(Generation!K:K,Generation!$A:$A,Summary_CDP,Generation!$B:$B,IF($B$82="NEM","*",$B$82),Generation!$C:$C,$H94) -> 2276.8832 | K94: =SUMIFS(Generation!U:U,Generation!$A:$A,Summary_CDP,Generation!$B:$B,IF($B$82="NEM","*",$B$82),Generation!$C:$C,$H94) -> 5487.5818 | L94: =SUMIFS(Generation!AE:AE,Generation!$A:$A,Summary_CDP,Generation!$B:$B,IF($B$82="NEM","*",$B$82),Generation!$C:$C,$H94) -> 5306.3911
H95: Solar Thermal | I95: =SUMIFS(Generation!D:D,Generation!$A:$A,Summary_CDP,Generation!$B:$B,IF($B$82="NEM","*",$B$82),Generation!$C:$C,$H95) -> 0 | J95: =SUMIFS(Generation!K:K,Generation!$A:$A,Summary_CDP,Generation!$B:$B,IF($B$82="NEM","*",$B$82),Generation!$C:$C,$H95) -> 0 | K95: =SUMIFS(Generation!U:U,Generation!$A:$A,Summary_CDP,Generation!$B:$B,IF($B$82="NEM","*",$B$82),Generation!$C:$C,$H95) -> 0 | L95: =SUMIFS(Generation!AE:AE,Generation!$A:$A,Summary_CDP,Generation!$B:$B,IF($B$82="NEM","*",$B$82),Generation!$C:$C,$H95) -> 0
H96: Offshore Wind | I96: =SUMIFS(Generation!D:D,Generation!$A:$A,Summary_CDP,Generation!$B:$B,IF($B$82="NEM","*",$B$82),Generation!$C:$C,$H96) -> 0 | J96: =SUMIFS(Generation!K:K,Generation!$A:$A,Summary_CDP,Generation!$B:$B,IF($B$82="NEM","*",$B$82),Generation!$C:$C,$H96) -> 0 | K96: =SUMIFS(Generation!U:U,Generation!$A:$A,Summary_CDP,Generation!$B:$B,IF($B$82="NEM","*",$B$82),Generation!$C:$C,$H96) -> 0 | L96: =SUMIFS(Generation!AE:AE,Generation!$A:$A,Summary_CDP,Generation!$B:$B,IF($B$82="NEM","*",$B$82),Generation!$C:$C,$H96) -> 0
... H99: Distributed PV | I99: =SUMIFS(Generation!D:D,Generation!$A:$A,Summary_CDP,Generation!$B:$B,IF($B$82="NEM","*",$B$82),Generation!$C:$C,$H99) -> 27394.521 | J99: =SUMIFS(Generation!K:K,Generation!$A:$A,Summary_CDP,Generation!$B:$B,IF($B$82="NEM","*",$B$82),Generation!$C:$C,$H99) -> 54712.407 | K99: =SUMIFS(Generation!U:U,Generation!$A:$A,Summary_CDP,Generation!$B:$B,IF($B$82="NEM","*",$B$82),Generation!$C:$C,$H99) -> 86124.175 | L99: =SUMIFS(Generation!AE:AE,Generation!$A:$A,Summary_CDP,Generation!$B:$B,IF($B$82="NEM","*",$B$82),Generation!$C:$C,$H99) -> 111724.66
H100: Storage Charging (GWh)
H101: Utility-scale Storage Load | I101: =SUMIFS(Generation!D:D,Generation!$A:$A,Summary_CDP,Generation!$B:$B,IF($B$82="NEM","*",$B$82),Generation!$C:$C,$H101) -> -2192.379 | J101: =SUMIFS(Generation!K:K,Generation!$A:$A,Summary_CDP,Generation!$B:$B,IF($B$82="NEM","*",$B$82),Generation!$C:$C,$H101) -> -34205.829 | K101: =SUMIFS(Generation!U:U,Generation!$A:$A,Summary_CDP,Generation!$B:$B,IF($B$82="NEM","*",$B$82),Generation!$C:$C,$H101) -> -46100.952 | L101: =SUMIFS(Generation!AE:AE,Generation!$A:$A,Summary_CDP,Generation!$B:$B,IF($B$82="NEM","*",$B$82),Generation!$C:$C,$H101) -> -137879.75
H102: Coordinated DER Storage Load | I102: =SUMIFS(Generation!D:D,Generation!$A:$A,Summary_CDP,Generation!$B:$B,IF($B$82="NEM","*",$B$82),Generation!$C:$C,$H102) -> -214.72553 | J102: =SUMIFS(Generation!K:K,Generation!$A:$A,Summary_CDP,Generation!$B:$B,IF($B$82="NEM","*",$B$82),Generation!$C:$C,$H102) -> -4386.859 | K102: =SUMIFS(Generation!U:U,Generation!$A:$A,Summary_CDP,Generation!$B:$B,IF($B$82="NEM","*",$B$82),Generation!$C:$C,$H102) -> -23011.66 | L102: =SUMIFS(Generation!AE:AE,Generation!$A:$A,Summary_CDP,Generation!$B:$B,IF($B$82="NEM","*",$B$82),Generation!$C:$C,$H102) -> -43020.871
H103: Distributed Storage Load | I103: =SUMIFS(Generation!D:D,Generation!$A:$A,Summary_CDP,Generation!$B:$B,IF($B$82="NEM","*",$B$82),Generation!$C:$C,$H103) -> -486.52982 | J103: =SUMIFS(Generation!K:K,Generation!$A:$A,Summary_CDP,Generation!$B:$B,IF($B$82="NEM","*",$B$82),Generation!$C:$C,$H103) -> -2680.6513 | K103: =SUMIFS(Generation!U:U,Generation!$A:$A,Summary_CDP,Generation!$B:$B,IF($B$82="NEM","*",$B$82),Generation!$C:$C,$H103) -> -6494.9302 | L103: =SUMIFS(Generation!AE:AE,Generation!$A:$A,Summary_CDP,Generation!$B:$B,IF($B$82="NEM","*",$B$82),Generation!$C:$C,$H103) -> -6247.8695
H105: DSP | I105: =SUMIFS(Generation!D:D,Generation!$A:$A,Summary_CDP,Generation!$B:$B,IF($B$82="NEM","*",$B$82),Generation!$C:$C,$H105) -> 0 | J105: =SUMIFS(Generation!K:K,Generation!$A:$A,Summary_CDP,Generation!$B:$B,IF($B$82="NEM","*",$B$82),Generation!$C:$C,$H105) -> 77.497508 | K105: =SUMIFS(Generation!U:U,Generation!$A:$A,Summary_CDP,Generation!$B:$B,IF($B$82="NEM","*",$B$82),Generation!$C:$C,$H105) -> 1689.3247 | L105: =SUMIFS(Generation!AE:AE,Generation!$A:$A,Summary_CDP,Generation!$B:$B,IF($B$82="NEM","*",$B$82),Generation!$C:$C,$H105) -> 1149.7463
A108: =B109&" Capacity by storage type" -> NEM Capacity by storage type
A109: Select region | B109: NEM
H111: Capacity (MW) | I111: 2023-24 | J111: 2030-31 | K111: 2040-41 | L111: 2050-51
H112: Snowy 2.0 | I112: =SUMIFS('Storage Capacity'!D:D,'Storage Capacity'!$A:$A,Summary_CDP,'Storage Capacity'!$B:$B,IF($B$109="NEM","*",$B$109),'Storage Capacity'!$C:$C,$H112) -> 0 | J112: =SUMIFS('Storage Capacity'!K:K,'Storage Capacity'!$A:$A,Summary_CDP,'Storage Capacity'!$B:$B,IF($B$109="NEM","*",$B$109),'Storage Capacity'!$C:$C,$H112) -> 2040 | K112: =SUMIFS('Storage Capacity'!U:U,'Storage Capacity'!$A:$A,Summary_CDP,'Storage Capacity'!$B:$B,IF($B$109="NEM","*",$B$109),'Storage Capacity'!$C:$C,$H112) -> 2040 | L112: =SUMIFS('Storage Capacity'!AE:AE,'Storage Capacity'!$A:$A,Summary_CDP,'Storage Capacity'!$B:$B,IF($B$109="NEM","*",$B$109),'Storage Capacity'!$C:$C,$H112) -> 2040
H113: Deep Storage | I113: =SUMIFS('Storage Capacity'!D:D,'Storage Capacity'!$A:$A,Summary_CDP,'Storage Capacity'!$B:$B,IF($B$109="NEM","*",$B$109),'Storage Capacity'!$C:$C,$H113) -> 160 | J113: =SUMIFS('Storage Capacity'!K:K,'Storage Capacity'!$A:$A,Summary_CDP,'Storage Capacity'!$B:$B,IF($B$109="NEM","*",$B$109),'Storage Capacity'!$C:$C,$H113) -> 1616.4738 | K113: =SUMIFS('Storage Capacity'!U:U,'Storage Capacity'!$A:$A,Summary_CDP,'Storage Capacity'!$B:$B,IF($B$109="NEM","*",$B$109),'Storage Capacity'!$C:$C,$H113) -> 1616.4738 | L113: =SUMIFS('Storage Capacity'!AE:AE,'Storage Capacity'!$A:$A,Summary_CDP,'Storage Capacity'!$B:$B,IF($B$109="NEM","*",$B$109),'Storage Capacity'!$C:$C,$H113) -> 3578.4001
H114: Medium Storage | I114: =SUMIFS('Storage Capacity'!D:D,'Storage Capacity'!$A:$A,Summary_CDP,'Storage Capacity'!$B:$B,IF($B$109="NEM","*",$B$109),'Storage Capacity'!$C:$C,$H114) -> 650 | J114: =SUMIFS('Storage Capacity'!K:K,'Storage Capacity'!$A:$A,Summary_CDP,'Storage Capacity'!$B:$B,IF($B$109="NEM","*",$B$109),'Storage Capacity'!$C:$C,$H114) -> 8633.023 | K114: =SUMIFS('Storage Capacity'!U:U,'Storage Capacity'!$A:$A,Summary_CDP,'Storage Capacity'!$B:$B,IF($B$109="NEM","*",$B$109),'Storage Capacity'!$C:$C,$H114) -> 15297.202 | L114: =SUMIFS('Storage Capacity'!AE:AE,'Storage Capacity'!$A:$A,Summary_CDP,'Storage Capacity'!$B:$B,IF($B$109="NEM","*",$B$109),'Storage Capacity'!$C:$C,$H114) -> 63296.172
H115: Shallow Storage | I115: =SUMIFS('Storage Capacity'!D:D,'Storage Capacity'!$A:$A,Summary_CDP,'Storage Capacity'!$B:$B,IF($B$109="NEM","*",$B$109),'Storage Capacity'!$C:$C,$H115) -> 748.56 | J115: =SUMIFS('Storage Capacity'!K:K,'Storage Capacity'!$A:$A,Summary_CDP,'Storage Capacity'!$B:$B,IF($B$109="NEM","*",$B$109),'Storage Capacity'!$C:$C,$H115) -> 1150.0312 | K115: =SUMIFS('Storage Capacity'!U:U,'Storage Capacity'!$A:$A,Summary_CDP,'Storage Capacity'!$B:$B,IF($B$109="NEM","*",$B$109),'Storage Capacity'!$C:$C,$H115) -> 1150.0312 | L115: =SUMIFS('Storage Capacity'!AE:AE,'Storage Capacity'!$A:$A,Summary_CDP,'Storage Capacity'!$B:$B,IF($B$109="NEM","*",$B$109),'Storage Capacity'!$C:$C,$H115) -> 998.56
H116: Coordinated DER Storage | I116: =SUMIFS('Storage Capacity'!D:D,'Storage Capacity'!$A:$A,Summary_CDP,'Storage Capacity'!$B:$B,IF($B$109="NEM","*",$B$109),'Storage Capacity'!$C:$C,$H116) -> 366.507 | J116: =SUMIFS('Storage Capacity'!K:K,'Storage Capacity'!$A:$A,Summary_CDP,'Storage Capacity'!$B:$B,IF($B$109="NEM","*",$B$109),'Storage Capacity'!$C:$C,$H116) -> 5829.8005 | K116: =SUMIFS('Storage Capacity'!U:U,'Storage Capacity'!$A:$A,Summary_CDP,'Storage Capacity'!$B:$B,IF($B$109="NEM","*",$B$109),'Storage Capacity'!$C:$C,$H116) -> 23318.225 | L116: =SUMIFS('Storage Capacity'!AE:AE,'Storage Capacity'!$A:$A,Summary_CDP,'Storage Capacity'!$B:$B,IF($B$109="NEM","*",$B$109),'Storage Capacity'!$C:$C,$H116) -> 37421.09
H117: Distributed Storage | I117: =SUMIFS('Storage Capacity'!D:D,'Storage Capacity'!$A:$A,Summary_CDP,'Storage Capacity'!$B:$B,IF($B$109="NEM","*",$B$109),'Storage Capacity'!$C:$C,$H117) -> 1615.687 | J117: =SUMIFS('Storage Capacity'!K:K,'Storage Capacity'!$A:$A,Summary_CDP,'Storage Capacity'!$B:$B,IF($B$109="NEM","*",$B$109),'Storage Capacity'!$C:$C,$H117) -> 6883.914 | K117: =SUMIFS('Storage Capacity'!U:U,'Storage Capacity'!$A:$A,Summary_CDP,'Storage Capacity'!$B:$B,IF($B$109="NEM","*",$B$109),'Storage Capacity'!$C:$C,$H117) -> 15594.936 | L117: =SUMIFS('Storage Capacity'!AE:AE,'Storage Capacity'!$A:$A,Summary_CDP,'Storage Capacity'!$B:$B,IF($B$109="NEM","*",$B$109),'Storage Capacity'!$C:$C,$H117) -> 14832.36
A126: =B127&" storage capacity by year" -> NEM storage capacity by year
A127: Select region | B127: NEM
H129: Capacity (MW) | I129: 2023-24 | J129: 2024-25 | K129: 2025-26 | L129: 2026-27 | M129: 2027-28 | N129: 2028-29 | O129: 2029-30 | P129: 2030-31 | Q129: 2031-32 | R129: 2032-33 | S129: 2033-34 | T129: 2034-35 | U129: 2035-36 | V129: 2036-37 | W129: 2037-38 | X129: 2038-39 | Y129: 2039-40 | Z129: 2040-41 | AA129: 2041-42 | AB129: 2042-43 | AC129: 2043-44 | AD129: 2044-45 | AE129: 2045-46 | AF129: 2046-47 | AG129: 2047-48 | AH129: 2048-49 | AI129: 2049-50 | AJ129: 2050-51
H130: Snowy 2.0 | I130: =SUMIFS('Storage Capacity'!D:D,'Storage Capacity'!$A:$A,Summary_CDP,'Storage Capacity'!$B:$B,IF($B$127="NEM","*",$B$127),'Storage Capacity'!$C:$C,$H130) -> 0 | J130: =SUMIFS('Storage Capacity'!E:E,'Storage Capacity'!$A:$A,Summary_CDP,'Storage Capacity'!$B:$B,IF($B$127="NEM","*",$B$127),'Storage Capacity'!$C:$C,$H130) -> 0 | K130: =SUMIFS('Storage Capacity'!F:F,'Storage Capacity'!$A:$A,Summary_CDP,'Storage Capacity'!$B:$B,IF($B$127="NEM","*",$B$127),'Storage Capacity'!$C:$C,$H130) -> 680 | L130: =SUMIFS('Storage Capacity'!G:G,'Storage Capacity'!$A:$A,Summary_CDP,'Storage Capacity'!$B:$B,IF($B$127="NEM","*",$B$127),'Storage Capacity'!$C:$C,$H130) -> 2040 | M130: =SUMIFS('Storage Capacity'!H:H,'Storage Capacity'!$A:$A,Summary_CDP,'Storage Capacity'!$B:$B,IF($B$127="NEM","*",$B$127),'Storage Capacity'!$C:$C,$H130) -> 2040 | N130: =SUMIFS('Storage Capacity'!I:I,'Storage Capacity'!$A:$A,Summary_CDP,'Storage Capacity'!$B:$B,IF($B$127="NEM","*",$B$127),'Storage Capacity'!$C:$C,$H130) -> 2040 | O130: =SUMIFS('Storage Capacity'!J:J,'Storage Capacity'!$A:$A,Summary_CDP,'Storage Capacity'!$B:$B,IF($B$127="NEM","*",$B$127),'Storage Capacity'!$C:$C,$H130) -> 2040 | P130: =SUMIFS('Storage Capacity'!K:K,'Storage Capacity'!$A:$A,Summary_CDP,'Storage Capacity'!$B:$B,IF($B$127="NEM","*",$B$127),'Storage Capacity'!$C:$C,$H130) -> 2040 | Q130: =SUMIFS('Storage Capacity'!L:L,'Storage Capacity'!$A:$A,Summary_CDP,'Storage Capacity'!$B:$B,IF($B$127="NEM","*",$B$127),'Storage Capacity'!$C:$C,$H130) -> 2040 | R130: =SUMIFS('Storage Capacity'!M:M,'Storage Capacity'!$A:$A,Summary_CDP,'Storage Capacity'!$B:$B,IF($B$127="NEM","*",$B$127),'Storage Capacity'!$C:$C,$H130) -> 2040 | S130: =SUMIFS('Storage Capacity'!N:N,'Storage Capacity'!$A:$A,Summary_CDP,'Storage Capacity'!$B:$B,IF($B$127="NEM","*",$B$127),'Storage Capacity'!$C:$C,$H130) -> 2040 | T130: =SUMIFS('Storage Capacity'!O:O,'Storage Capacity'!$A:$A,Summary_CDP,'Storage Capacity'!$B:$B,IF($B$127="NEM","*",$B$127),'Storage Capacity'!$C:$C,$H130) -> 2040 | U130: =SUMIFS('Storage Capacity'!P:P,'Storage Capacity'!$A:$A,Summary_CDP,'Storage Capacity'!$B:$B,IF($B$127="NEM","*",$B$127),'Storage Capacity'!$C:$C,$H130) -> 2040 | V130: =SUMIFS('Storage Capacity'!Q:Q,'Storage Capacity'!$A:$A,Summary_CDP,'Storage Capacity'!$B:$B,IF($B$127="NEM","*",$B$127),'Storage Capacity'!$C:$C,$H130) -> 2040 | W130: =SUMIFS('Storage Capacity'!R:R,'Storage Capacity'!$A:$A,Summary_CDP,'Storage Capacity'!$B:$B,IF($B$127="NEM","*",$B$127),'Storage Capacity'!$C:$C,$H130) -> 2040 | X130: =SUMIFS('Storage Capacity'!S:S,'Storage Capacity'!$A:$A,Summary_CDP,'Storage Capacity'!$B:$B,IF($B$127="NEM","*",$B$127),'Storage Capacity'!$C:$C,$H130) -> 2040 | Y130: =SUMIFS('Storage Capacity'!T:T,'Storage Capacity'!$A:$A,Summary_CDP,'Storage Capacity'!$B:$B,IF($B$127="NEM","*",$B$127),'Storage Capacity'!$C:$C,$H130) -> 2040 | Z130: =SUMIFS('Storage Capacity'!U:U,'Storage Capacity'!$A:$A,Summary_CDP,'Storage Capacity'!$B:$B,IF($B$127="NEM","*",$B$127),'Storage Capacity'!$C:$C,$H130) -> 2040 | AA130: =SUMIFS('Storage Capacity'!V:V,'Storage Capacity'!$A:$A,Summary_CDP,'Storage Capacity'!$B:$B,IF($B$127="NEM","*",$B$127),'Storage Capacity'!$C:$C,$H130) -> 2040 | AB130: =SUMIFS('Storage Capacity'!W:W,'Storage Capacity'!$A:$A,Summary_CDP,'Storage Capacity'!$B:$B,IF($B$127="NEM","*",$B$127),'Storage Capacity'!$C:$C,$H130) -> 2040 | AC130: =SUMIFS('Storage Capacity'!X:X,'Storage Capacity'!$A:$A,Summary_CDP,'Storage Capacity'!$B:$B,IF($B$127="NEM","*",$B$127),'Storage Capacity'!$C:$C,$H130) -> 2040 | AD130: =SUMIFS('Storage Capacity'!Y:Y,'Storage Capacity'!$A:$A,Summary_CDP,'Storage Capacity'!$B:$B,IF($B$127="NEM","*",$B$127),'Storage Capacity'!$C:$C,$H130) -> 2040 | AE130: =SUMIFS('Storage Capacity'!Z:Z,'Storage Capacity'!$A:$A,Summary_CDP,'Storage Capacity'!$B:$B,IF($B$127="NEM","*",$B$127),'Storage Capacity'!$C:$C,$H130) -> 2040 | AF130: =SUMIFS('Storage Capacity'!AA:AA,'Storage Capacity'!$A:$A,Summary_CDP,'Storage Capacity'!$B:$B,IF($B$127="NEM","*",$B$127),'Storage Capacity'!$C:$C,$H130) -> 2040 | AG130: =SUMIFS('Storage Capacity'!AB:AB,'Storage Capacity'!$A:$A,Summary_CDP,'Storage Capacity'!$B:$B,IF($B$127="NEM","*",$B$127),'Storage Capacity'!$C:$C,$H130) -> 2040 | AH130: =SUMIFS('Storage Capacity'!AC:AC,'Storage Capacity'!$A:$A,Summary_CDP,'Storage Capacity'!$B:$B,IF($B$127="NEM","*",$B$127),'Storage Capacity'!$C:$C,$H130) -> 2040 | AI130: =SUMIFS('Storage Capacity'!AD:AD,'Storage Capacity'!$A:$A,Summary_CDP,'Storage Capacity'!$B:$B,IF($B$127="NEM","*",$B$127),'Storage Capacity'!$C:$C,$H130) -> 2040 | AJ130: =SUMIFS('Storage Capacity'!AE:AE,'Storage Capacity'!$A:$A,Summary_CDP,'Storage Capacity'!$B:$B,IF($B$127="NEM","*",$B$127),'Storage Capacity'!$C:$C,$H130) -> 2040
H131: Deep Storage | I131: =SUMIFS('Storage Capacity'!D:D,'Storage Capacity'!$A:$A,Summary_CDP,'Storage Capacity'!$B:$B,IF($B$127="NEM","*",$B$127),'Storage Capacity'!$C:$C,$H131) -> 160 | J131: =SUMIFS('Storage Capacity'!E:E,'Storage Capacity'!$A:$A,Summary_CDP,'Storage Capacity'!$B:$B,IF($B$127="NEM","*",$B$127),'Storage Capacity'!$C:$C,$H131) -> 160 | K131: =SUMIFS('Storage Capacity'!F:F,'Storage Capacity'!$A:$A,Summary_CDP,'Storage Capacity'!$B:$B,IF($B$127="NEM","*",$B$127),'Storage Capacity'!$C:$C,$H131) -> 160 | L131: =SUMIFS('Storage Capacity'!G:G,'Storage Capacity'!$A:$A,Summary_CDP,'Storage Capacity'!$B:$B,IF($B$127="NEM","*",$B$127),'Storage Capacity'!$C:$C,$H131) -> 160 | M131: =SUMIFS('Storage Capacity'!H:H,'Storage Capacity'!$A:$A,Summary_CDP,'Storage Capacity'!$B:$B,IF($B$127="NEM","*",$B$127),'Storage Capacity'!$C:$C,$H131) -> 160 | N131: =SUMIFS('Storage Capacity'!I:I,'Storage Capacity'!$A:$A,Summary_CDP,'Storage Capacity'!$B:$B,IF($B$127="NEM","*",$B$127),'Storage Capacity'!$C:$C,$H131) -> 1281.026 | O131: =SUMIFS('Storage Capacity'!J:J,'Storage Capacity'!$A:$A,Summary_CDP,'Storage Capacity'!$B:$B,IF($B$127="NEM","*",$B$127),'Storage Capacity'!$C:$C,$H131) -> 1281.026 | P131: =SUMIFS('Storage Capacity'!K:K,'Storage Capacity'!$A:$A,Summary_CDP,'Storage Capacity'!$B:$B,IF($B$127="NEM","*",$B$127),'Storage Capacity'!$C:$C,$H131) -> 1616.4738 | Q131: =SUMIFS('Storage Capacity'!L:L,'Storage Capacity'!$A:$A,Summary_CDP,'Storage Capacity'!$B:$B,IF($B$127="NEM","*",$B$127),'Storage Capacity'!$C:$C,$H131) -> 1616.4738 | R131: =SUMIFS('Storage Capacity'!M:M,'Storage Capacity'!$A:$A,Summary_CDP,'Storage Capacity'!$B:$B,IF($B$127="NEM","*",$B$127),'Storage Capacity'!$C:$C,$H131) -> 1616.4738 | S131: =SUMIFS('Storage Capacity'!N:N,'Storage Capacity'!$A:$A,Summary_CDP,'Storage Capacity'!$B:$B,IF($B$127="NEM","*",$B$127),'Storage Capacity'!$C:$C,$H131) -> 1616.4738 | T131: =SUMIFS('Storage Capacity'!O:O,'Storage Capacity'!$A:$A,Summary_CDP,'Storage Capacity'!$B:$B,IF($B$127="NEM","*",$B$127),'Storage Capacity'!$C:$C,$H131) -> 1616.4738 | U131: =SUMIFS('Storage Capacity'!P:P,'Storage Capacity'!$A:$A,Summary_CDP,'Storage Capacity'!$B:$B,IF($B$127="NEM","*",$B$127),'Storage Capacity'!$C:$C,$H131) -> 1616.4738 | V131: =SUMIFS('Storage Capacity'!Q:Q,'Storage Capacity'!$A:$A,Summary_CDP,'Storage Capacity'!$B:$B,IF($B$127="NEM","*",$B$127),'Storage Capacity'!$C:$C,$H131) -> 1616.4738 | W131: =SUMIFS('Storage Capacity'!R:R,'Storage Capacity'!$A:$A,Summary_CDP,'Storage Capacity'!$B:$B,IF($B$127="NEM","*",$B$127),'Storage Capacity'!$C:$C,$H131) -> 1616.4738 | X131: =SUMIFS('Storage Capacity'!S:S,'Storage Capacity'!$A:$A,Summary_CDP,'Storage Capacity'!$B:$B,IF($B$127="NEM","*",$B$127),'Storage Capacity'!$C:$C,$H131) -> 1616.4738 | Y131: =SUMIFS('Storage Capacity'!T:T,'Storage Capacity'!$A:$A,Summary_CDP,'Storage Capacity'!$B:$B,IF($B$127="NEM","*",$B$127),'Storage Capacity'!$C:$C,$H131) -> 1616.4738 | Z131: =SUMIFS('Storage Capacity'!U:U,'Storage Capacity'!$A:$A,Summary_CDP,'Storage Capacity'!$B:$B,IF($B$127="NEM","*",$B$127),'Storage Capacity'!$C:$C,$H131) -> 1616.4738 | AA131: =SUMIFS('Storage Capacity'!V:V,'Storage Capacity'!$A:$A,Summary_CDP,'Storage Capacity'!$B:$B,IF($B$127="NEM","*",$B$127),'Storage Capacity'!$C:$C,$H131) -> 1915.2072 | AB131: =SUMIFS('Storage Capacity'!W:W,'Storage Capacity'!$A:$A,Summary_CDP,'Storage Capacity'!$B:$B,IF($B$127="NEM","*",$B$127),'Storage Capacity'!$C:$C,$H131) -> 2016.6643 | AC131: =SUMIFS('Storage Capacity'!X:X,'Storage Capacity'!$A:$A,Summary_CDP,'Storage Capacity'!$B:$B,IF($B$127="NEM","*",$B$127),'Storage Capacity'!$C:$C,$H131) -> 2506.152 | AD131: =SUMIFS('Storage Capacity'!Y:Y,'Storage Capacity'!$A:$A,Summary_CDP,'Storage Capacity'!$B:$B,IF($B$127="NEM","*",$B$127),'Storage Capacity'!$C:$C,$H131) -> 2506.152 | AE131: =SUMIFS('Storage Capacity'!Z:Z,'Storage Capacity'!$A:$A,Summary_CDP,'Storage Capacity'!$B:$B,IF($B$127="NEM","*",$B$127),'Storage Capacity'!$C:$C,$H131) -> 2506.152 | AF131: =SUMIFS('Storage Capacity'!AA:AA,'Storage Capacity'!$A:$A,Summary_CDP,'Storage Capacity'!$B:$B,IF($B$127="NEM","*",$B$127),'Storage Capacity'!$C:$C,$H131) -> 2506.152 | AG131: =SUMIFS('Storage Capacity'!AB:AB,'Storage Capacity'!$A:$A,Summary_CDP,'Storage Capacity'!$B:$B,IF($B$127="NEM","*",$B$127),'Storage Capacity'!$C:$C,$H131) -> 2506.152 | AH131: =SUMIFS('Storage Capacity'!AC:AC,'Storage Capacity'!$A:$A,Summary_CDP,'Storage Capacity'!$B:$B,IF($B$127="NEM","*",$B$127),'Storage Capacity'!$C:$C,$H131) -> 2981.0877 | AI131: =SUMIFS('Storage Capacity'!AD:AD,'Storage Capacity'!$A:$A,Summary_CDP,'Storage Capacity'!$B:$B,IF($B$127="NEM","*",$B$127),'Storage Capacity'!$C:$C,$H131) -> 3578.4001 | AJ131: =SUMIFS('Storage Capacity'!AE:AE,'Storage Capacity'!$A:$A,Summary_CDP,'Storage Capacity'!$B:$B,IF($B$127="NEM","*",$B$127),'Storage Capacity'!$C:$C,$H131) -> 3578.4001
H132: Medium Storage | I132: =SUMIFS('Storage Capacity'!D:D,'Storage Capacity'!$A:$A,Summary_CDP,'Storage Capacity'!$B:$B,IF($B$127="NEM","*",$B$127),'Storage Capacity'!$C:$C,$H132) -> 650 | J132: =SUMIFS('Storage Capacity'!E:E,'Storage Capacity'!$A:$A,Summary_CDP,'Storage Capacity'!$B:$B,IF($B$127="NEM","*",$B$127),'Storage Capacity'!$C:$C,$H132) -> 650 | K132: =SUMIFS('Storage Capacity'!F:F,'Storage Capacity'!$A:$A,Summary_CDP,'Storage Capacity'!$B:$B,IF($B$127="NEM","*",$B$127),'Storage Capacity'!$C:$C,$H132) -> 1815.2107 | L132: =SUMIFS('Storage Capacity'!G:G,'Storage Capacity'!$A:$A,Summary_CDP,'Storage Capacity'!$B:$B,IF($B$127="NEM","*",$B$127),'Storage Capacity'!$C:$C,$H132) -> 3381.0151 | M132: =SUMIFS('Storage Capacity'!H:H,'Storage Capacity'!$A:$A,Summary_CDP,'Storage Capacity'!$B:$B,IF($B$127="NEM","*",$B$127),'Storage Capacity'!$C:$C,$H132) -> 6114.987 | N132: =SUMIFS('Storage Capacity'!I:I,'Storage Capacity'!$A:$A,Summary_CDP,'Storage Capacity'!$B:$B,IF($B$127="NEM","*",$B$127),'Storage Capacity'!$C:$C,$H132) -> 6834.2438 | O132: =SUMIFS('Storage Capacity'!J:J,'Storage Capacity'!$A:$A,Summary_CDP,'Storage Capacity'!$B:$B,IF($B$127="NEM","*",$B$127),'Storage Capacity'!$C:$C,$H132) -> 6836.1873 | P132: =SUMIFS('Storage Capacity'!K:K,'Storage Capacity'!$A:$A,Summary_CDP,'Storage Capacity'!$B:$B,IF($B$127="NEM","*",$B$127),'Storage Capacity'!$C:$C,$H132) -> 8633.023 | Q132: =SUMIFS('Storage Capacity'!L:L,'Storage Capacity'!$A:$A,Summary_CDP,'Storage Capacity'!$B:$B,IF($B$127="NEM","*",$B$127),'Storage Capacity'!$C:$C,$H132) -> 8633.023 | R132: =SUMIFS('Storage Capacity'!M:M,'Storage Capacity'!$A:$A,Summary_CDP,'Storage Capacity'!$B:$B,IF($B$127="NEM","*",$B$127),'Storage Capacity'!$C:$C,$H132) -> 8633.023 | S132: =SUMIFS('Storage Capacity'!N:N,'Storage Capacity'!$A:$A,Summary_CDP,'Storage Capacity'!$B:$B,IF($B$127="NEM","*",$B$127),'Storage Capacity'!$C:$C,$H132) -> 8704.3225 | T132: =SUMIFS('Storage Capacity'!O:O,'Storage Capacity'!$A:$A,Summary_CDP,'Storage Capacity'!$B:$B,IF($B$127="NEM","*",$B$127),'Storage Capacity'!$C:$C,$H132) -> 8775.5307 | U132: =SUMIFS('Storage Capacity'!P:P,'Storage Capacity'!$A:$A,Summary_CDP,'Storage Capacity'!$B:$B,IF($B$127="NEM","*",$B$127),'Storage Capacity'!$C:$C,$H132) -> 11370.926 | V132: =SUMIFS('Storage Capacity'!Q:Q,'Storage Capacity'!$A:$A,Summary_CDP,'Storage Capacity'!$B:$B,IF($B$127="NEM","*",$B$127),'Storage Capacity'!$C:$C,$H132) -> 12199.365 | W132: =SUMIFS('Storage Capacity'!R:R,'Storage Capacity'!$A:$A,Summary_CDP,'Storage Capacity'!$B:$B,IF($B$127="NEM","*",$B$127),'Storage Capacity'!$C:$C,$H132) -> 13679.189 | X132: =SUMIFS('Storage Capacity'!S:S,'Storage Capacity'!$A:$A,Summary_CDP,'Storage Capacity'!$B:$B,IF($B$127="NEM","*",$B$127),'Storage Capacity'!$C:$C,$H132) -> 13985.77 | Y132: =SUMIFS('Storage Capacity'!T:T,'Storage Capacity'!$A:$A,Summary_CDP,'Storage Capacity'!$B:$B,IF($B$127="NEM","*",$B$127),'Storage Capacity'!$C:$C,$H132) -> 13985.77 | Z132: =SUMIFS('Storage Capacity'!U:U,'Storage Capacity'!$A:$A,Summary_CDP,'Storage Capacity'!$B:$B,IF($B$127="NEM","*",$B$127),'Storage Capacity'!$C:$C,$H132) -> 15297.202 | AA132: =SUMIFS('Storage Capacity'!V:V,'Storage Capacity'!$A:$A,Summary_CDP,'Storage Capacity'!$B:$B,IF($B$127="NEM","*",$B$127),'Storage Capacity'!$C:$C,$H132) -> 23142.95 | AB132: =SUMIFS('Storage Capacity'!W:W,'Storage Capacity'!$A:$A,Summary_CDP,'Storage Capacity'!$B:$B,IF($B$127="NEM","*",$B$127),'Storage Capacity'!$C:$C,$H132) -> 23142.95 | AC132: =SUMIFS('Storage Capacity'!X:X,'Storage Capacity'!$A:$A,Summary_CDP,'Storage Capacity'!$B:$B,IF($B$127="NEM","*",$B$127),'Storage Capacity'!$C:$C,$H132) -> 23142.95 | AD132: =SUMIFS('Storage Capacity'!Y:Y,'Storage Capacity'!$A:$A,Summary_CDP,'Storage Capacity'!$B:$B,IF($B$127="NEM","*",$B$127),'Storage Capacity'!$C:$C,$H132) -> 25081.27 | AE132: =SUMIFS('Storage Capacity'!Z:Z,'Storage Capacity'!$A:$A,Summary_CDP,'Storage Capacity'!$B:$B,IF($B$127="NEM","*",$B$127),'Storage Capacity'!$C:$C,$H132) -> 31910.779 | AF132: =SUMIFS('Storage Capacity'!AA:AA,'Storage Capacity'!$A:$A,Summary_CDP,'Storage Capacity'!$B:$B,IF($B$127="NEM","*",$B$127),'Storage Capacity'!$C:$C,$H132) -> 31838.021 | AG132: =SUMIFS('Storage Capacity'!AB:AB,'Storage Capacity'!$A:$A,Summary_CDP,'Storage Capacity'!$B:$B,IF($B$127="NEM","*",$B$127),'Storage Capacity'!$C:$C,$H132) -> 31502.34 | AH132: =SUMIFS('Storage Capacity'!AC:AC,'Storage Capacity'!$A:$A,Summary_CDP,'Storage Capacity'!$B:$B,IF($B$127="NEM","*",$B$127),'Storage Capacity'!$C:$C,$H132) -> 41730.753 | AI132: =SUMIFS('Storage Capacity'!AD:AD,'Storage Capacity'!$A:$A,Summary_CDP,'Storage Capacity'!$B:$B,IF($B$127="NEM","*",$B$127),'Storage Capacity'!$C:$C,$H132) -> 65093.008 | AJ132: =SUMIFS('Storage Capacity'!AE:AE,'Storage Capacity'!$A:$A,Summary_CDP,'Storage Capacity'!$B:$B,IF($B$127="NEM","*",$B$127),'Storage Capacity'!$C:$C,$H132) -> 63296.172
H133: Shallow Storage | I133: =SUMIFS('Storage Capacity'!D:D,'Storage Capacity'!$A:$A,Summary_CDP,'Storage Capacity'!$B:$B,IF($B$127="NEM","*",$B$127),'Storage Capacity'!$C:$C,$H133) -> 748.56 | J133: =SUMIFS('Storage Capacity'!E:E,'Storage Capacity'!$A:$A,Summary_CDP,'Storage Capacity'!$B:$B,IF($B$127="NEM","*",$B$127),'Storage Capacity'!$C:$C,$H133) -> 747.46 | K133: =SUMIFS('Storage Capacity'!F:F,'Storage Capacity'!$A:$A,Summary_CDP,'Storage Capacity'!$B:$B,IF($B$127="NEM","*",$B$127),'Storage Capacity'!$C:$C,$H133) -> 900.03118 | L133: =SUMIFS('Storage Capacity'!G:G,'Storage Capacity'!$A:$A,Summary_CDP,'Storage Capacity'!$B:$B,IF($B$127="NEM","*",$B$127),'Storage Capacity'!$C:$C,$H133) -> 900.03118 | M133: =SUMIFS('Storage Capacity'!H:H,'Storage Capacity'!$A:$A,Summary_CDP,'Storage Capacity'!$B:$B,IF($B$127="NEM","*",$B$127),'Storage Capacity'!$C:$C,$H133) -> 901.13118 | N133: =SUMIFS('Storage Capacity'!I:I,'Storage Capacity'!$A:$A,Summary_CDP,'Storage Capacity'!$B:$B,IF($B$127="NEM","*",$B$127),'Storage Capacity'!$C:$C,$H133) -> 900.03118 | O133: =SUMIFS('Storage Capacity'!J:J,'Storage Capacity'!$A:$A,Summary_CDP,'Storage Capacity'!$B:$B,IF($B$127="NEM","*",$B$127),'Storage Capacity'!$C:$C,$H133) -> 900.03118 | P133: =SUMIFS('Storage Capacity'!K:K,'Storage Capacity'!$A:$A,Summary_CDP,'Storage Capacity'!$B:$B,IF($B$127="NEM","*",$B$127),'Storage Capacity'!$C:$C,$H133) -> 1150.0312 | Q133: =SUMIFS('Storage Capacity'!L:L,'Storage Capacity'!$A:$A,Summary_CDP,'Storage Capacity'!$B:$B,IF($B$127="NEM","*",$B$127),'Storage Capacity'!$C:$C,$H133) -> 1150.0312 | R133: =SUMIFS('Storage Capacity'!M:M,'Storage Capacity'!$A:$A,Summary_CDP,'Storage Capacity'!$B:$B,IF($B$127="NEM","*",$B$127),'Storage Capacity'!$C:$C,$H133) -> 1151.1312 | S133: =SUMIFS('Storage Capacity'!N:N,'Storage Capacity'!$A:$A,Summary_CDP,'Storage Capacity'!$B:$B,IF($B$127="NEM","*",$B$127),'Storage Capacity'!$C:$C,$H133) -> 1150.0312 | T133: =SUMIFS('Storage Capacity'!O:O,'Storage Capacity'!$A:$A,Summary_CDP,'Storage Capacity'!$B:$B,IF($B$127="NEM","*",$B$127),'Storage Capacity'!$C:$C,$H133) -> 1151.1312 | U133: =SUMIFS('Storage Capacity'!P:P,'Storage Capacity'!$A:$A,Summary_CDP,'Storage Capacity'!$B:$B,IF($B$127="NEM","*",$B$127),'Storage Capacity'!$C:$C,$H133) -> 1150.0312 | V133: =SUMIFS('Storage Capacity'!Q:Q,'Storage Capacity'!$A:$A,Summary_CDP,'Storage Capacity'!$B:$B,IF($B$127="NEM","*",$B$127),'Storage Capacity'!$C:$C,$H133) -> 1150.0312 | W133: =SUMIFS('Storage Capacity'!R:R,'Storage Capacity'!$A:$A,Summary_CDP,'Storage Capacity'!$B:$B,IF($B$127="NEM","*",$B$127),'Storage Capacity'!$C:$C,$H133) -> 1150.0312 | X133: =SUMIFS('Storage Capacity'!S:S,'Storage Capacity'!$A:$A,Summary_CDP,'Storage Capacity'!$B:$B,IF($B$127="NEM","*",$B$127),'Storage Capacity'!$C:$C,$H133) -> 1151.1312 | Y133: =SUMIFS('Storage Capacity'!T:T,'Storage Capacity'!$A:$A,Summary_CDP,'Storage Capacity'!$B:$B,IF($B$127="NEM","*",$B$127),'Storage Capacity'!$C:$C,$H133) -> 1150.0312 | Z133: =SUMIFS('Storage Capacity'!U:U,'Storage Capacity'!$A:$A,Summary_CDP,'Storage Capacity'!$B:$B,IF($B$127="NEM","*",$B$127),'Storage Capacity'!$C:$C,$H133) -> 1150.0312 | AA133: =SUMIFS('Storage Capacity'!V:V,'Storage Capacity'!$A:$A,Summary_CDP,'Storage Capacity'!$B:$B,IF($B$127="NEM","*",$B$127),'Storage Capacity'!$C:$C,$H133) -> 1150.0312 | AB133: =SUMIFS('Storage Capacity'!W:W,'Storage Capacity'!$A:$A,Summary_CDP,'Storage Capacity'!$B:$B,IF($B$127="NEM","*",$B$127),'Storage Capacity'!$C:$C,$H133) -> 1150.0312 | AC133: =SUMIFS('Storage Capacity'!X:X,'Storage Capacity'!$A:$A,Summary_CDP,'Storage Capacity'!$B:$B,IF($B$127="NEM","*",$B$127),'Storage Capacity'!$C:$C,$H133) -> 1151.1312 | AD133: =SUMIFS('Storage Capacity'!Y:Y,'Storage Capacity'!$A:$A,Summary_CDP,'Storage Capacity'!$B:$B,IF($B$127="NEM","*",$B$127),'Storage Capacity'!$C:$C,$H133) -> 1153.2312 | AE133: =SUMIFS('Storage Capacity'!Z:Z,'Storage Capacity'!$A:$A,Summary_CDP,'Storage Capacity'!$B:$B,IF($B$127="NEM","*",$B$127),'Storage Capacity'!$C:$C,$H133) -> 998.56 | AF133: =SUMIFS('Storage Capacity'!AA:AA,'Storage Capacity'!$A:$A,Summary_CDP,'Storage Capacity'!$B:$B,IF($B$127="NEM","*",$B$127),'Storage Capacity'!$C:$C,$H133) -> 998.56 | AG133: =SUMIFS('Storage Capacity'!AB:AB,'Storage Capacity'!$A:$A,Summary_CDP,'Storage Capacity'!$B:$B,IF($B$127="NEM","*",$B$127),'Storage Capacity'!$C:$C,$H133) -> 998.56 | AH133: =SUMIFS('Storage Capacity'!AC:AC,'Storage Capacity'!$A:$A,Summary_CDP,'Storage Capacity'!$B:$B,IF($B$127="NEM","*",$B$127),'Storage Capacity'!$C:$C,$H133) -> 998.56 | AI133: =SUMIFS('Storage Capacity'!AD:AD,'Storage Capacity'!$A:$A,Summary_CDP,'Storage Capacity'!$B:$B,IF($B$127="NEM","*",$B$127),'Storage Capacity'!$C:$C,$H133) -> 998.56 | AJ133: =SUMIFS('Storage Capacity'!AE:AE,'Storage Capacity'!$A:$A,Summary_CDP,'Storage Capacity'!$B:$B,IF($B$127="NEM","*",$B$127),'Storage Capacity'!$C:$C,$H133) -> 998.56
H134: Coordinated DER Storage | I134: =SUMIFS('Storage Capacity'!D:D,'Storage Capacity'!$A:$A,Summary_CDP,'Storage Capacity'!$B:$B,IF($B$127="NEM","*",$B$127),'Storage Capacity'!$C:$C,$H134) -> 366.507 | J134: =SUMIFS('Storage Capacity'!E:E,'Storage Capacity'!$A:$A,Summary_CDP,'Storage Capacity'!$B:$B,IF($B$127="NEM","*",$B$127),'Storage Capacity'!$C:$C,$H134) -> 731.507 | K134: =SUMIFS('Storage Capacity'!F:F,'Storage Capacity'!$A:$A,Summary_CDP,'Storage Capacity'!$B:$B,IF($B$127="NEM","*",$B$127),'Storage Capacity'!$C:$C,$H134) -> 1218.992 | L134: =SUMIFS('Storage Capacity'!G:G,'Storage Capacity'!$A:$A,Summary_CDP,'Storage Capacity'!$B:$B,IF($B$127="NEM","*",$B$127),'Storage Capacity'!$C:$C,$H134) -> 1822.853 | M134: =SUMIFS('Storage Capacity'!H:H,'Storage Capacity'!$A:$A,Summary_CDP,'Storage Capacity'!$B:$B,IF($B$127="NEM","*",$B$127),'Storage Capacity'!$C:$C,$H134) -> 2558.481 | N134: =SUMIFS('Storage Capacity'!I:I,'Storage Capacity'!$A:$A,Summary_CDP,'Storage Capacity'!$B:$B,IF($B$127="NEM","*",$B$127),'Storage Capacity'!$C:$C,$H134) -> 3412.119 | O134: =SUMIFS('Storage Capacity'!J:J,'Storage Capacity'!$A:$A,Summary_CDP,'Storage Capacity'!$B:$B,IF($B$127="NEM","*",$B$127),'Storage Capacity'!$C:$C,$H134) -> 4696.274 | P134: =SUMIFS('Storage Capacity'!K:K,'Storage Capacity'!$A:$A,Summary_CDP,'Storage Capacity'!$B:$B,IF($B$127="NEM","*",$B$127),'Storage Capacity'!$C:$C,$H134) -> 5829.8005 | Q134: =SUMIFS('Storage Capacity'!L:L,'Storage Capacity'!$A:$A,Summary_CDP,'Storage Capacity'!$B:$B,IF($B$127="NEM","*",$B$127),'Storage Capacity'!$C:$C,$H134) -> 7024.5443 | R134: =SUMIFS('Storage Capacity'!M:M,'Storage Capacity'!$A:$A,Summary_CDP,'Storage Capacity'!$B:$B,IF($B$127="NEM","*",$B$127),'Storage Capacity'!$C:$C,$H134) -> 8398.683 | S134: =SUMIFS('Storage Capacity'!N:N,'Storage Capacity'!$A:$A,Summary_CDP,'Storage Capacity'!$B:$B,IF($B$127="NEM","*",$B$127),'Storage Capacity'!$C:$C,$H134) -> 10091.142 | T134: =SUMIFS('Storage Capacity'!O:O,'Storage Capacity'!$A:$A,Summary_CDP,'Storage Capacity'!$B:$B,IF($B$127="NEM","*",$B$127),'Storage Capacity'!$C:$C,$H134) -> 11935.595 | U134: =SUMIFS('Storage Capacity'!P:P,'Storage Capacity'!$A:$A,Summary_CDP,'Storage Capacity'!$B:$B,IF($B$127="NEM","*",$B$127),'Storage Capacity'!$C:$C,$H134) -> 13875.121 | V134: =SUMIFS('Storage Capacity'!Q:Q,'Storage Capacity'!$A:$A,Summary_CDP,'Storage Capacity'!$B:$B,IF($B$127="NEM","*",$B$127),'Storage Capacity'!$C:$C,$H134) -> 15894.635 | W134: =SUMIFS('Storage Capacity'!R:R,'Storage Capacity'!$A:$A,Summary_CDP,'Storage Capacity'!$B:$B,IF($B$127="NEM","*",$B$127),'Storage Capacity'!$C:$C,$H134) -> 17933.751 | X134: =SUMIFS('Storage Capacity'!S:S,'Storage Capacity'!$A:$A,Summary_CDP,'Storage Capacity'!$B:$B,IF($B$127="NEM","*",$B$127),'Storage Capacity'!$C:$C,$H134) -> 19983.078 | Y134: =SUMIFS('Storage Capacity'!T:T,'Storage Capacity'!$A:$A,Summary_CDP,'Storage Capacity'!$B:$B,IF($B$127="NEM","*",$B$127),'Storage Capacity'!$C:$C,$H134) -> 21671.677 | Z134: =SUMIFS('Storage Capacity'!U:U,'Storage Capacity'!$A:$A,Summary_CDP,'Storage Capacity'!$B:$B,IF($B$127="NEM","*",$B$127),'Storage Capacity'!$C:$C,$H134) -> 23318.225 | AA134: =SUMIFS('Storage Capacity'!V:V,'Storage Capacity'!$A:$A,Summary_CDP,'Storage Capacity'!$B:$B,IF($B$127="NEM","*",$B$127),'Storage Capacity'!$C:$C,$H134) -> 24889.356 | AB134: =SUMIFS('Storage Capacity'!W:W,'Storage Capacity'!$A:$A,Summary_CDP,'Storage Capacity'!$B:$B,IF($B$127="NEM","*",$B$127),'Storage Capacity'!$C:$C,$H134) -> 26447.73 | AC134: =SUMIFS('Storage Capacity'!X:X,'Storage Capacity'!$A:$A,Summary_CDP,'Storage Capacity'!$B:$B,IF($B$127="NEM","*",$B$127),'Storage Capacity'!$C:$C,$H134) -> 28117.47 | AD134: =SUMIFS('Storage Capacity'!Y:Y,'Storage Capacity'!$A:$A,Summary_CDP,'Storage Capacity'!$B:$B,IF($B$127="NEM","*",$B$127),'Storage Capacity'!$C:$C,$H134) -> 29806.333 | AE134: =SUMIFS('Storage Capacity'!Z:Z,'Storage Capacity'!$A:$A,Summary_CDP,'Storage Capacity'!$B:$B,IF($B$127="NEM","*",$B$127),'Storage Capacity'!$C:$C,$H134) -> 31258.097 | AF134: =SUMIFS('Storage Capacity'!AA:AA,'Storage Capacity'!$A:$A,Summary_CDP,'Storage Capacity'!$B:$B,IF($B$127="NEM","*",$B$127),'Storage Capacity'!$C:$C,$H134) -> 32733.875 | AG134: =SUMIFS('Storage Capacity'!AB:AB,'Storage Capacity'!$A:$A,Summary_CDP,'Storage Capacity'!$B:$B,IF($B$127="NEM","*",$B$127),'Storage Capacity'!$C:$C,$H134) -> 34233.92 | AH134: =SUMIFS('Storage Capacity'!AC:AC,'Storage Capacity'!$A:$A,Summary_CDP,'Storage Capacity'!$B:$B,IF($B$127="NEM","*",$B$127),'Storage Capacity'!$C:$C,$H134) -> 35763.291 | AI134: =SUMIFS('Storage Capacity'!AD:AD,'Storage Capacity'!$A:$A,Summary_CDP,'Storage Capacity'!$B:$B,IF($B$127="NEM","*",$B$127),'Storage Capacity'!$C:$C,$H134) -> 37313.352 | AJ134: =SUMIFS('Storage Capacity'!AE:AE,'Storage Capacity'!$A:$A,Summary_CDP,'Storage Capacity'!$B:$B,IF($B$127="NEM","*",$B$127),'Storage Capacity'!$C:$C,$H134) -> 37421.09
H135: Distributed Storage | I135: =SUMIFS('Storage Capacity'!D:D,'Storage Capacity'!$A:$A,Summary_CDP,'Storage Capacity'!$B:$B,IF($B$127="NEM","*",$B$127),'Storage Capacity'!$C:$C,$H135) -> 1615.687 | J135: =SUMIFS('Storage Capacity'!E:E,'Storage Capacity'!$A:$A,Summary_CDP,'Storage Capacity'!$B:$B,IF($B$127="NEM","*",$B$127),'Storage Capacity'!$C:$C,$H135) -> 2523.858 | K135: =SUMIFS('Storage Capacity'!F:F,'Storage Capacity'!$A:$A,Summary_CDP,'Storage Capacity'!$B:$B,IF($B$127="NEM","*",$B$127),'Storage Capacity'!$C:$C,$H135) -> 3346.118 | L135: =SUMIFS('Storage Capacity'!G:G,'Storage Capacity'!$A:$A,Summary_CDP,'Storage Capacity'!$B:$B,IF($B$127="NEM","*",$B$127),'Storage Capacity'!$C:$C,$H135) -> 4039.736 | M135: =SUMIFS('Storage Capacity'!H:H,'Storage Capacity'!$A:$A,Summary_CDP,'Storage Capacity'!$B:$B,IF($B$127="NEM","*",$B$127),'Storage Capacity'!$C:$C,$H135) -> 4643.731 | N135: =SUMIFS('Storage Capacity'!I:I,'Storage Capacity'!$A:$A,Summary_CDP,'Storage Capacity'!$B:$B,IF($B$127="NEM","*",$B$127),'Storage Capacity'!$C:$C,$H135) -> 5111.685 | O135: =SUMIFS('Storage Capacity'!J:J,'Storage Capacity'!$A:$A,Summary_CDP,'Storage Capacity'!$B:$B,IF($B$127="NEM","*",$B$127),'Storage Capacity'!$C:$C,$H135) -> 5870.22 | P135: =SUMIFS('Storage Capacity'!K:K,'Storage Capacity'!$A:$A,Summary_CDP,'Storage Capacity'!$B:$B,IF($B$127="NEM","*",$B$127),'Storage Capacity'!$C:$C,$H135) -> 6883.914 | Q135: =SUMIFS('Storage Capacity'!L:L,'Storage Capacity'!$A:$A,Summary_CDP,'Storage Capacity'!$B:$B,IF($B$127="NEM","*",$B$127),'Storage Capacity'!$C:$C,$H135) -> 7823.741 | R135: =SUMIFS('Storage Capacity'!M:M,'Storage Capacity'!$A:$A,Summary_CDP,'Storage Capacity'!$B:$B,IF($B$127="NEM","*",$B$127),'Storage Capacity'!$C:$C,$H135) -> 8822.021 | S135: =SUMIFS('Storage Capacity'!N:N,'Storage Capacity'!$A:$A,Summary_CDP,'Storage Capacity'!$B:$B,IF($B$127="NEM","*",$B$127),'Storage Capacity'!$C:$C,$H135) -> 10032.986 | T135: =SUMIFS('Storage Capacity'!O:O,'Storage Capacity'!$A:$A,Summary_CDP,'Storage Capacity'!$B:$B,IF($B$127="NEM","*",$B$127),'Storage Capacity'!$C:$C,$H135) -> 11279.352 | U135: =SUMIFS('Storage Capacity'!P:P,'Storage Capacity'!$A:$A,Summary_CDP,'Storage Capacity'!$B:$B,IF($B$127="NEM","*",$B$127),'Storage Capacity'!$C:$C,$H135) -> 12411.971 | V135: =SUMIFS('Storage Capacity'!Q:Q,'Storage Capacity'!$A:$A,Summary_CDP,'Storage Capacity'!$B:$B,IF($B$127="NEM","*",$B$127),'Storage Capacity'!$C:$C,$H135) -> 13450.545 | W135: =SUMIFS('Storage Capacity'!R:R,'Storage Capacity'!$A:$A,Summary_CDP,'Storage Capacity'!$B:$B,IF($B$127="NEM","*",$B$127),'Storage Capacity'!$C:$C,$H135) -> 14351.891 | X135: =SUMIFS('Storage Capacity'!S:S,'Storage Capacity'!$A:$A,Summary_CDP,'Storage Capacity'!$B:$B,IF($B$127="NEM","*",$B$127),'Storage Capacity'!$C:$C,$H135) -> 15102.709 | Y135: =SUMIFS('Storage Capacity'!T:T,'Storage Capacity'!$A:$A,Summary_CDP,'Storage Capacity'!$B:$B,IF($B$127="NEM","*",$B$127),'Storage Capacity'!$C:$C,$H135) -> 15417.929 | Z135: =SUMIFS('Storage Capacity'!U:U,'Storage Capacity'!$A:$A,Summary_CDP,'Storage Capacity'!$B:$B,IF($B$127="NEM","*",$B$127),'Storage Capacity'!$C:$C,$H135) -> 15594.936 | AA135: =SUMIFS('Storage Capacity'!V:V,'Storage Capacity'!$A:$A,Summary_CDP,'Storage Capacity'!$B:$B,IF($B$127="NEM","*",$B$127),'Storage Capacity'!$C:$C,$H135) -> 15616.079 | AB135: =SUMIFS('Storage Capacity'!W:W,'Storage Capacity'!$A:$A,Summary_CDP,'Storage Capacity'!$B:$B,IF($B$127="NEM","*",$B$127),'Storage Capacity'!$C:$C,$H135) -> 15610.974 | AC135: =SUMIFS('Storage Capacity'!X:X,'Storage Capacity'!$A:$A,Summary_CDP,'Storage Capacity'!$B:$B,IF($B$127="NEM","*",$B$127),'Storage Capacity'!$C:$C,$H135) -> 15555.227 | AD135: =SUMIFS('Storage Capacity'!Y:Y,'Storage Capacity'!$A:$A,Summary_CDP,'Storage Capacity'!$B:$B,IF($B$127="NEM","*",$B$127),'Storage Capacity'!$C:$C,$H135) -> 15481.949 | AE135: =SUMIFS('Storage Capacity'!Z:Z,'Storage Capacity'!$A:$A,Summary_CDP,'Storage Capacity'!$B:$B,IF($B$127="NEM","*",$B$127),'Storage Capacity'!$C:$C,$H135) -> 15387.778 | AF135: =SUMIFS('Storage Capacity'!AA:AA,'Storage Capacity'!$A:$A,Summary_CDP,'Storage Capacity'!$B:$B,IF($B$127="NEM","*",$B$127),'Storage Capacity'!$C:$C,$H135) -> 15277.058 | AG135: =SUMIFS('Storage Capacity'!AB:AB,'Storage Capacity'!$A:$A,Summary_CDP,'Storage Capacity'!$B:$B,IF($B$127="NEM","*",$B$127),'Storage Capacity'!$C:$C,$H135) -> 15144.979 | AH135: =SUMIFS('Storage Capacity'!AC:AC,'Storage Capacity'!$A:$A,Summary_CDP,'Storage Capacity'!$B:$B,IF($B$127="NEM","*",$B$127),'Storage Capacity'!$C:$C,$H135) -> 15000.321 | AI135: =SUMIFS('Storage Capacity'!AD:AD,'Storage Capacity'!$A:$A,Summary_CDP,'Storage Capacity'!$B:$B,IF($B$127="NEM","*",$B$127),'Storage Capacity'!$C:$C,$H135) -> 14832.36 | AJ135: =SUMIFS('Storage Capacity'!AE:AE,'Storage Capacity'!$A:$A,Summary_CDP,'Storage Capacity'!$B:$B,IF($B$127="NEM","*",$B$127),'Storage Capacity'!$C:$C,$H135) -> 14832.36
A144: =B145&" storage energy by year" -> NEM storage energy by year
A145: Select region | B145: NEM
H147: Total Energy (GWh) | I147: 2023-24 | J147: 2024-25 | K147: 2025-26 | L147: 2026-27 | M147: 2027-28 | N147: 2028-29 | O147: 2029-30 | P147: 2030-31 | Q147: 2031-32 | R147: 2032-33 | S147: 2033-34 | T147: 2034-35 | U147: 2035-36 | V147: 2036-37 | W147: 2037-38 | X147: 2038-39 | Y147: 2039-40 | Z147: 2040-41 | AA147: 2041-42 | AB147: 2042-43 | AC147: 2043-44 | AD147: 2044-45 | AE147: 2045-46 | AF147: 2046-47 | AG147: 2047-48 | AH147: 2048-49 | AI147: 2049-50 | AJ147: 2050-51
H148: Snowy 2.0 | I148: =SUMIFS('Storage Energy'!D:D,'Storage Energy'!$A:$A,Summary_CDP,'Storage Energy'!$B:$B,IF($B$145="NEM","*",$B$145),'Storage Energy'!$C:$C,$H148) -> 0 | J148: =SUMIFS('Storage Energy'!E:E,'Storage Energy'!$A:$A,Summary_CDP,'Storage Energy'!$B:$B,IF($B$145="NEM","*",$B$145),'Storage Energy'!$C:$C,$H148) -> 0 | K148: =SUMIFS('Storage Energy'!F:F,'Storage Energy'!$A:$A,Summary_CDP,'Storage Energy'!$B:$B,IF($B$145="NEM","*",$B$145),'Storage Energy'!$C:$C,$H148) -> 116.28 | L148: =SUMIFS('Storage Energy'!G:G,'Storage Energy'!$A:$A,Summary_CDP,'Storage Energy'!$B:$B,IF($B$145="NEM","*",$B$145),'Storage Energy'!$C:$C,$H148) -> 348.84 | M148: =SUMIFS('Storage Energy'!H:H,'Storage Energy'!$A:$A,Summary_CDP,'Storage Energy'!$B:$B,IF($B$145="NEM","*",$B$145),'Storage Energy'!$C:$C,$H148) -> 348.84 | N148: =SUMIFS('Storage Energy'!I:I,'Storage Energy'!$A:$A,Summary_CDP,'Storage Energy'!$B:$B,IF($B$145="NEM","*",$B$145),'Storage Energy'!$C:$C,$H148) -> 348.84 | O148: =SUMIFS('Storage Energy'!J:J,'Storage Energy'!$A:$A,Summary_CDP,'Storage Energy'!$B:$B,IF($B$145="NEM","*",$B$145),'Storage Energy'!$C:$C,$H148) -> 348.84 | P148: =SUMIFS('Storage Energy'!K:K,'Storage Energy'!$A:$A,Summary_CDP,'Storage Energy'!$B:$B,IF($B$145="NEM","*",$B$145),'Storage Energy'!$C:$C,$H148) -> 348.84 | Q148: =SUMIFS('Storage Energy'!L:L,'Storage Energy'!$A:$A,Summary_CDP,'Storage Energy'!$B:$B,IF($B$145="NEM","*",$B$145),'Storage Energy'!$C:$C,$H148) -> 348.84 | R148: =SUMIFS('Storage Energy'!M:M,'Storage Energy'!$A:$A,Summary_CDP,'Storage Energy'!$B:$B,IF($B$145="NEM","*",$B$145),'Storage Energy'!$C:$C,$H148) -> 348.84 | S148: =SUMIFS('Storage Energy'!N:N,'Storage Energy'!$A:$A,Summary_CDP,'Storage Energy'!$B:$B,IF($B$145="NEM","*",$B$145),'Storage Energy'!$C:$C,$H148) -> 348.84 | T148: =SUMIFS('Storage Energy'!O:O,'Storage Energy'!$A:$A,Summary_CDP,'Storage Energy'!$B:$B,IF($B$145="NEM","*",$B$145),'Storage Energy'!$C:$C,$H148) -> 348.84 | U148: =SUMIFS('Storage Energy'!P:P,'Storage Energy'!$A:$A,Summary_CDP,'Storage Energy'!$B:$B,IF($B$145="NEM","*",$B$145),'Storage Energy'!$C:$C,$H148) -> 348.84 | V148: =SUMIFS('Storage Energy'!Q:Q,'Storage Energy'!$A:$A,Summary_CDP,'Storage Energy'!$B:$B,IF($B$145="NEM","*",$B$145),'Storage Energy'!$C:$C,$H148) -> 348.84 | W148: =SUMIFS('Storage Energy'!R:R,'Storage Energy'!$A:$A,Summary_CDP,'Storage Energy'!$B:$B,IF($B$145="NEM","*",$B$145),'Storage Energy'!$C:$C,$H148) -> 348.84 | X148: =SUMIFS('Storage Energy'!S:S,'Storage Energy'!$A:$A,Summary_CDP,'Storage Energy'!$B:$B,IF($B$145="NEM","*",$B$145),'Storage Energy'!$C:$C,$H148) -> 348.84 | Y148: =SUMIFS('Storage Energy'!T:T,'Storage Energy'!$A:$A,Summary_CDP,'Storage Energy'!$B:$B,IF($B$145="NEM","*",$B$145),'Storage Energy'!$C:$C,$H148) -> 348.84 | Z148: =SUMIFS('Storage Energy'!U:U,'Storage Energy'!$A:$A,Summary_CDP,'Storage Energy'!$B:$B,IF($B$145="NEM","*",$B$145),'Storage Energy'!$C:$C,$H148) -> 348.84 | AA148: =SUMIFS('Storage Energy'!V:V,'Storage Energy'!$A:$A,Summary_CDP,'Storage Energy'!$B:$B,IF($B$145="NEM","*",$B$145),'Storage Energy'!$C:$C,$H148) -> 348.84 | AB148: =SUMIFS('Storage Energy'!W:W,'Storage Energy'!$A:$A,Summary_CDP,'Storage Energy'!$B:$B,IF($B$145="NEM","*",$B$145),'Storage Energy'!$C:$C,$H148) -> 348.84 | AC148: =SUMIFS('Storage Energy'!X:X,'Storage Energy'!$A:$A,Summary_CDP,'Storage Energy'!$B:$B,IF($B$145="NEM","*",$B$145),'Storage Energy'!$C:$C,$H148) -> 348.84 | AD148: =SUMIFS('Storage Energy'!Y:Y,'Storage Energy'!$A:$A,Summary_CDP,'Storage Energy'!$B:$B,IF($B$145="NEM","*",$B$145),'Storage Energy'!$C:$C,$H148) -> 348.84 | AE148: =SUMIFS('Storage Energy'!Z:Z,'Storage Energy'!$A:$A,Summary_CDP,'Storage Energy'!$B:$B,IF($B$145="NEM","*",$B$145),'Storage Energy'!$C:$C,$H148) -> 348.84 | AF148: =SUMIFS('Storage Energy'!AA:AA,'Storage Energy'!$A:$A,Summary_CDP,'Storage Energy'!$B:$B,IF($B$145="NEM","*",$B$145),'Storage Energy'!$C:$C,$H148) -> 348.84 | AG148: =SUMIFS('Storage Energy'!AB:AB,'Storage Energy'!$A:$A,Summary_CDP,'Storage Energy'!$B:$B,IF($B$145="NEM","*",$B$145),'Storage Energy'!$C:$C,$H148) -> 348.84 | AH148: =SUMIFS('Storage Energy'!AC:AC,'Storage Energy'!$A:$A,Summary_CDP,'Storage Energy'!$B:$B,IF($B$145="NEM","*",$B$145),'Storage Energy'!$C:$C,$H148) -> 348.84 | AI148: =SUMIFS('Storage Energy'!AD:AD,'Storage Energy'!$A:$A,Summary_CDP,'Storage Energy'!$B:$B,IF($B$145="NEM","*",$B$145),'Storage Energy'!$C:$C,$H148) -> 348.84 | AJ148: =SUMIFS('Storage Energy'!AE:AE,'Storage Energy'!$A:$A,Summary_CDP,'Storage Energy'!$B:$B,IF($B$145="NEM","*",$B$145),'Storage Energy'!$C:$C,$H148) -> 348.84
H149: Deep Storage | I149: =SUMIFS('Storage Energy'!D:D,'Storage Energy'!$A:$A,Summary_CDP,'Storage Energy'!$B:$B,IF($B$145="NEM","*",$B$145),'Storage Energy'!$C:$C,$H149) -> 6.049 | J149: =SUMIFS('Storage Energy'!E:E,'Storage Energy'!$A:$A,Summary_CDP,'Storage Energy'!$B:$B,IF($B$145="NEM","*",$B$145),'Storage Energy'!$C:$C,$H149) -> 6.049 | K149: =SUMIFS('Storage Energy'!F:F,'Storage Energy'!$A:$A,Summary_CDP,'Storage Energy'!$B:$B,IF($B$145="NEM","*",$B$145),'Storage Energy'!$C:$C,$H149) -> 6.049 | L149: =SUMIFS('Storage Energy'!G:G,'Storage Energy'!$A:$A,Summary_CDP,'Storage Energy'!$B:$B,IF($B$145="NEM","*",$B$145),'Storage Energy'!$C:$C,$H149) -> 6.049 | M149: =SUMIFS('Storage Energy'!H:H,'Storage Energy'!$A:$A,Summary_CDP,'Storage Energy'!$B:$B,IF($B$145="NEM","*",$B$145),'Storage Energy'!$C:$C,$H149) -> 6.049 | N149: =SUMIFS('Storage Energy'!I:I,'Storage Energy'!$A:$A,Summary_CDP,'Storage Energy'!$B:$B,IF($B$145="NEM","*",$B$145),'Storage Energy'!$C:$C,$H149) -> 44.079947 | O149: =SUMIFS('Storage Energy'!J:J,'Storage Energy'!$A:$A,Summary_CDP,'Storage Energy'!$B:$B,IF($B$145="NEM","*",$B$145),'Storage Energy'!$C:$C,$H149) -> 44.079947 | P149: =SUMIFS('Storage Energy'!K:K,'Storage Energy'!$A:$A,Summary_CDP,'Storage Energy'!$B:$B,IF($B$145="NEM","*",$B$145),'Storage Energy'!$C:$C,$H149) -> 60.18144 | Q149: =SUMIFS('Storage Energy'!L:L,'Storage Energy'!$A:$A,Summary_CDP,'Storage Energy'!$B:$B,IF($B$145="NEM","*",$B$145),'Storage Energy'!$C:$C,$H149) -> 60.18144 | R149: =SUMIFS('Storage Energy'!M:M,'Storage Energy'!$A:$A,Summary_CDP,'Storage Energy'!$B:$B,IF($B$145="NEM","*",$B$145),'Storage Energy'!$C:$C,$H149) -> 60.18144 | S149: =SUMIFS('Storage Energy'!N:N,'Storage Energy'!$A:$A,Summary_CDP,'Storage Energy'!$B:$B,IF($B$145="NEM","*",$B$145),'Storage Energy'!$C:$C,$H149) -> 60.18144 | T149: =SUMIFS('Storage Energy'!O:O,'Storage Energy'!$A:$A,Summary_CDP,'Storage Energy'!$B:$B,IF($B$145="NEM","*",$B$145),'Storage Energy'!$C:$C,$H149) -> 60.18144 | U149: =SUMIFS('Storage Energy'!P:P,'Storage Energy'!$A:$A,Summary_CDP,'Storage Energy'!$B:$B,IF($B$145="NEM","*",$B$145),'Storage Energy'!$C:$C,$H149) -> 60.18144 | V149: =SUMIFS('Storage Energy'!Q:Q,'Storage Energy'!$A:$A,Summary_CDP,'Storage Energy'!$B:$B,IF($B$145="NEM","*",$B$145),'Storage Energy'!$C:$C,$H149) -> 60.18144 | W149: =SUMIFS('Storage Energy'!R:R,'Storage Energy'!$A:$A,Summary_CDP,'Storage Energy'!$B:$B,IF($B$145="NEM","*",$B$145),'Storage Energy'!$C:$C,$H149) -> 60.18144 | X149: =SUMIFS('Storage Energy'!S:S,'Storage Energy'!$A:$A,Summary_CDP,'Storage Energy'!$B:$B,IF($B$145="NEM","*",$B$145),'Storage Energy'!$C:$C,$H149) -> 60.18144 | Y149: =SUMIFS('Storage Energy'!T:T,'Storage Energy'!$A:$A,Summary_CDP,'Storage Energy'!$B:$B,IF($B$145="NEM","*",$B$145),'Storage Energy'!$C:$C,$H149) -> 60.18144 | Z149: =SUMIFS('Storage Energy'!U:U,'Storage Energy'!$A:$A,Summary_CDP,'Storage Energy'!$B:$B,IF($B$145="NEM","*",$B$145),'Storage Energy'!$C:$C,$H149) -> 60.18144 | AA149: =SUMIFS('Storage Energy'!V:V,'Storage Energy'!$A:$A,Summary_CDP,'Storage Energy'!$B:$B,IF($B$145="NEM","*",$B$145),'Storage Energy'!$C:$C,$H149) -> 67.351042 | AB149: =SUMIFS('Storage Energy'!W:W,'Storage Energy'!$A:$A,Summary_CDP,'Storage Energy'!$B:$B,IF($B$145="NEM","*",$B$145),'Storage Energy'!$C:$C,$H149) -> 71.197182 | AC149: =SUMIFS('Storage Energy'!X:X,'Storage Energy'!$A:$A,Summary_CDP,'Storage Energy'!$B:$B,IF($B$145="NEM","*",$B$145),'Storage Energy'!$C:$C,$H149) -> 82.160391 | AD149: =SUMIFS('Storage Energy'!Y:Y,'Storage Energy'!$A:$A,Summary_CDP,'Storage Energy'!$B:$B,IF($B$145="NEM","*",$B$145),'Storage Energy'!$C:$C,$H149) -> 82.160391 | AE149: =SUMIFS('Storage Energy'!Z:Z,'Storage Energy'!$A:$A,Summary_CDP,'Storage Energy'!$B:$B,IF($B$145="NEM","*",$B$145),'Storage Energy'!$C:$C,$H149) -> 82.160391 | AF149: =SUMIFS('Storage Energy'!AA:AA,'Storage Energy'!$A:$A,Summary_CDP,'Storage Energy'!$B:$B,IF($B$145="NEM","*",$B$145),'Storage Energy'!$C:$C,$H149) -> 82.160391 | AG149: =SUMIFS('Storage Energy'!AB:AB,'Storage Energy'!$A:$A,Summary_CDP,'Storage Energy'!$B:$B,IF($B$145="NEM","*",$B$145),'Storage Energy'!$C:$C,$H149) -> 82.160391 | AH149: =SUMIFS('Storage Energy'!AC:AC,'Storage Energy'!$A:$A,Summary_CDP,'Storage Energy'!$B:$B,IF($B$145="NEM","*",$B$145),'Storage Energy'!$C:$C,$H149) -> 91.659105 | AI149: =SUMIFS('Storage Energy'!AD:AD,'Storage Energy'!$A:$A,Summary_CDP,'Storage Energy'!$B:$B,IF($B$145="NEM","*",$B$145),'Storage Energy'!$C:$C,$H149) -> 105.9946 | AJ149: =SUMIFS('Storage Energy'!AE:AE,'Storage Energy'!$A:$A,Summary_CDP,'Storage Energy'!$B:$B,IF($B$145="NEM","*",$B$145),'Storage Energy'!$C:$C,$H149) -> 105.9946
...

Sheet Comparison
A2: ="Comparison - "&Comparison_CDP1&" vs. "&Comparison_CDP2 -> Comparison - CDP1 vs. Counterfactual
A3: Notes
A4: ="1. The discount rate used for calculation is "&TEXT(WACC,"0.0%") -> 1. The discount rate used for calculation is 7.5%
A5: 2. All costs exclude any additional reliability cost savings, competition benefits and early works costs. Further details on these components are provided in Appendix 6.
C7: Description:
A8: Select Case 1 | B8: CDP1 | C8: =INDEX(CDPs!$B$5:$B$20,MATCH(Comparison_CDP1,CDPs!$A$5:$A$20,0),1) -> Based on Progressive Change least-cost DP
A9: Select Case 2 | B9: Counterfactual | C9: =INDEX(CDPs!$B$5:$B$20,MATCH(Comparison_CDP2,CDPs!$A$5:$A$20,0),1) -> No future network augmentation other than committed and anticipated projects/ small intra-regional augmentations/ replacement expenditure projects
A11: Relative market benefits by year
H14: Real June 2021 dollars ($m) | I14: NPV | J14: 2023-24 | K14: 2024-25 | L14: 2025-26 | M14: 2026-27 | N14: 2027-28 | O14: 2028-29 | P14: 2029-30 | Q14: 2030-31 | R14: 2031-32 | S14: 2032-33 | T14: 2033-34 | U14: 2034-35 | V14: 2035-36 | W14: 2036-37 | X14: 2037-38 | Y14: 2038-39 | Z14: 2039-40 | AA14: 2040-41 | AB14: 2041-42 | AC14: 2042-43 | AD14: 2043-44 | AE14: 2044-45 | AF14: 2045-46 | AG14: 2046-47 | AH14: 2047-48 | AI14: 2048-49 | AJ14: 2049-50 | AK14: 2050-51
